Workbook

Sheet 汇总

Sheet 单品13GD31
A1: sku:100048028229 | D1: 销售出库 | V1: 流量 | AT1: 转化 | BH1: 京仓现货率 | BI1: 关键词排名 | BQ1: 流失分析 | CF1: 负同比每日分析
A2: 日期 | B2: 价格政策 | D2: 销售额 | L2: 模块销售占比 | V2: PV | X2: UV | Z2: 人均浏览量 | AB2: 平均停留时间 | AD2: 关注人数 | AF2: 加购人数 | AH2: 站内免费 | AJ2: 站内付费 | AL2: 站外免费 | AN2: 站外付费 | AP2: 搜索 | AR2: 内容 | AT2: 店铺转化率 | AV2: 询单 数 | AX2: 询单 率 | AZ2: 询单 成交数 | BB2: 询单 转化 | BD2: 静默成交数 | BF2: 静默转化 | BI2: 燃气热水器 | BM2: 热水器 | BQ2: 流量流失 | BV2: 销售流失
B3: Y-23 | C3: Y-22 | D3: Y-23 数量 | E3: Y-23 金额 | F3: 实际销售 | G3: Y-22 金额 | H3: 同比 | I3: 目标 | J3: 达成率 | K3: 类目占比 | L3: 推广成交金额 | M3: 同比 | N3: 占比 | O3: 客服成交金额 | P3: 同比 | Q3: 占比 | R3: Y-23 | S3: Y-22 | T3: 同比 | U3: 占比 | V3: Y-23 | W3: Y-22 | X3: Y-23 | Y3: Y-22 | Z3: Y-23 | AA3: Y-22 | AB3: Y-23 | AC3: Y-22 | AD3: Y-23 | AE3: Y-22 | AF3: Y-23 | AG3: Y-22 | AH3: Y-23 | AI3: Y-22 | AJ3: Y-23 | AK3: Y-22 | AL3: Y-23 | AM3: Y-22 | AN3: Y-23 | AO3: Y-22 | AP3: Y-23 | AQ3: Y-22 | AR3: Y-23 | AS3: Y-22 | AT3: Y-23 | AU3: Y-22 | AV3: Y-23 | AW3: Y-22 | AX3: Y-23 | AY3: Y-22 | AZ3: Y-23 | BA3: Y-22 | BB3: Y-23 | BC3: Y-22 | BD3: Y-23 | BE3: Y-22 | BF3: Y-23 | BG3: Y-22 | BI3: 层级 | BJ3: 排名 | BK3: 搜索曝光 | BL3: Y-22搜索曝光 | BM3: 层级 | BN3: 排名 | BO3: 搜索曝光 | BP3: Y-22搜索曝光 | BQ3: TOP 1 | BR3: TOP 2 | BS3: TOP 3 | BT3: TOP 4 | BU3: TOP 5 | BV3: TOP 1 | BW3: TOP 2 | BX3: TOP 3 | BY3: TOP 4 | BZ3: TOP 5 | CA3: TOP 6 | CB3: TOP 7 | CC3: TOP 8 | CD3: TOP 9 | CE3: TOP 10
A4: 填写人员 | B4: 运营 | C4: 运营 | D4: 张超 | E4: 张超 | F4: 运营 | G4: 张超 | H4: 张超 | I4: 张超 | J4: 张超 | K4: 张超 | L4: 推广 | M4: 推广 | N4: 推广 | O4: 客服 | P4: 客服 | Q4: 客服 | R4: 直播 | S4: 直播 | T4: 直播 | U4: 直播 | V4: 运营 | W4: 运营 | X4: 运营 | Y4: 运营 | Z4: 运营 | AA4: 运营 | AB4: 运营 | AC4: 运营 | AD4: 运营 | AE4: 运营 | AF4: 运营 | AG4: 运营 | AH4: 运营 | AI4: 运营 | AJ4: 运营 | AK4: 运营 | AL4: 运营 | AM4: 运营 | AN4: 运营 | AO4: 运营 | AP4: 运营 | AQ4: 运营 | AR4: 运营 | AS4: 运营 | AT4: 客服 | AU4: 客服 | AV4: 客服 | AW4: 客服 | AX4: 客服 | AY4: 客服 | AZ4: 客服 | BA4: 客服 | BB4: 客服 | BC4: 客服 | BD4: 客服 | BE4: 客服 | BF4: 客服 | BG4: 客服 | BH4: 供应链 | BI4: 运营 | BJ4: 运营 | BK4: 运营 | BL4: 运营 | BM4: 运营 | BN4: 运营 | BO4: 运营 | BP4: 运营 | BQ4: 运营 | BR4: 运营 | BS4: 运营 | BT4: 运营 | BU4: 运营 | BV4: 运营 | BW4: 运营 | BX4: 运营 | BY4: 运营 | BZ4: 运营 | CA4: 运营 | CB4: 运营 | CC4: 运营 | CD4: 运营 | CE4: 运营 | CF4: 运营
A5: 45108 | B5: A | C5: 无 | F5: 5.5081 | H5: =IFERROR(E5/G5-1,"") | I5: 5.2784 | J5: =IFERROR(E5/I5,"") | K5: =IFERROR(E5/#REF!,"") | L5: 43345 | M5: - | R5: 0 | S5: 0 | W5: - | Y5: - | AA5: - | AC5: - | AD5: 18 | AE5: - | AG5: - | AH5: 1291 | AI5: - | AJ5: 262 | AK5: - | AL5: 33 | AM5: - | AN5: 12 | AO5: - | AP5: 591 | AQ5: - | AR5: 169 | AS5: - | AT5: 0.0122 | AU5: - | BH5: 1 | BI5: E | BJ5: 85 | BK5: 877 | BL5: - | BM5: F | BN5: 383 | BO5: 342 | BP5: -
A6: 45109 | B6: A | C6: 无 | F6: 4.6384 | H6: =IFERROR(E6/G6-1,"") | I6: 5.6086 | J6: =IFERROR(E6/I6,"") | K6: =IFERROR(E6/#REF!,"") | L6: 18394 | M6: - | R6: 2899 | S6: 0 | W6: - | Y6: - | AA6: - | AC6: - | AD6: 12 | AE6: - | AG6: - | AH6: 1461 | AI6: - | AJ6: 327 | AK6: - | AL6: 39 | AM6: - | AN6: 11 | AO6: - | AP6: 716 | AQ6: - | AR6: 173 | AS6: - | AT6: 0.0094 | AU6: - | BH6: 1 | BI6: E | BJ6: 66 | BK6: 1205 | BL6: - | BM6: F | BN6: 353 | BO6: 365 | BP6: -
A7: 45110 | B7: 预约 | C7: 无 | F7: 0 | H7: =IFERROR(E7/G7-1,"") | I7: 0 | J7: =IFERROR(E7/I7,"") | K7: =IFERROR(E7/#REF!,"") | L7: 10817 | M7: - | R7: 0 | S7: 0 | W7: - | Y7: - | AA7: - | AC7: - | AD7: 19 | AE7: - | AG7: - | AH7: 1221 | AI7: - | AJ7: 399 | AK7: - | AL7: 36 | AM7: - | AN7: 13 | AO7: - | AP7: 543 | AQ7: - | AR7: 156 | AS7: - | AT7: 0 | AU7: - | BH7: 1 | BI7: E | BJ7: 92 | BK7: 771 | BL7: - | BM7: F | BN7: 553 | BO7: 198 | BP7: - | BV7: 13QC05 | BW7: POP13QS04 | BX7: 16GD31 | BY7: 13GD32 | BZ7: 13QD31 | CA7: 13QD06W | CB7: POP13QC05 | CC7: 16QD31 | CD7: 16QD06W | CE7: 能率13EA2
A8: 45111 | B8: A | C8: 无 | F8: 11.3064 | H8: =IFERROR(E8/G8-1,"") | I8: 6.9279 | J8: =IFERROR(E8/I8,"") | K8: =IFERROR(E8/#REF!,"") | L8: 27091 | M8: - | R8: 0 | S8: 0 | W8: - | Y8: - | AA8: - | AC8: - | AD8: 33 | AE8: - | AG8: - | AH8: 1259 | AI8: - | AJ8: 378 | AK8: - | AL8: 35 | AM8: - | AN8: 16 | AO8: - | AP8: 525 | AQ8: - | AR8: 141 | AS8: - | AT8: 0.0256 | AU8: - | BH8: 1 | BI8: E | BJ8: 93 | BK8: 743 | BL8: - | BM8: F | BN8: 447 | BO8: 248 | BP8: -
A9: 45112 | B9: A | C9: 无 | F9: 8.687 | H9: =IFERROR(E9/G9-1,"") | I9: 10.5571 | J9: =IFERROR(E9/I9,"") | K9: =IFERROR(E9/#REF!,"") | L9: 44505 | M9: - | R9: 0 | S9: 0 | W9: - | Y9: - | AA9: - | AC9: - | AD9: 27 | AE9: - | AG9: - | AH9: 1459 | AI9: - | AJ9: 414 | AK9: - | AL9: 49 | AM9: - | AN9: 16 | AO9: - | AP9: 697 | AQ9: - | AR9: 119 | AS9: - | AT9: 0.0165 | AU9: - | BH9: 0.95 | BI9: E | BJ9: 68 | BK9: 961 | BL9: - | BM9: F | BN9: 319 | BO9: 357 | BP9: -
A10: 45113 | B10: 预约 | C10: 无 | F10: 0.2799 | H10: =IFERROR(E10/G10-1,"") | I10: 0.8998 | J10: =IFERROR(E10/I10,"") | K10: =IFERROR(E10/#REF!,"") | L10: 8757 | M10: - | R10: 0 | S10: 0 | W10: - | Y10: - | AA10: - | AC10: - | AD10: 22 | AE10: - | AG10: - | AH10: 973 | AI10: - | AJ10: 430 | AK10: - | AL10: 33 | AM10: - | AN10: 16 | AO10: - | AP10: 377 | AQ10: - | AR10: 113 | AS10: - | AT10: 0 | AU10: - | BH10: 0.95 | BI10: F | BJ10: 121 | BK10: 482 | BL10: - | BM10: F | BN10: 464 | BO10: 229 | BP10: -
A11: 45114 | B11: A | C11: 无 | F11: 8.697 | H11: =IFERROR(E11/G11-1,"") | I11: 8.9073 | J11: =IFERROR(E11/I11,"") | K11: =IFERROR(E11/#REF!,"") | L11: 28790 | M11: - | R11: 0 | S11: 0 | W11: - | Y11: - | AA11: - | AC11: - | AD11: 24 | AE11: - | AG11: - | AH11: 1219 | AI11: - | AJ11: 361 | AK11: - | AL11: 23 | AM11: - | AN11: 13 | AO11: - | AP11: 628 | AQ11: - | AR11: 91 | AS11: - | AT11: 0.0189 | AU11: - | BH11: 0.95 | BI11: E | BJ11: 90 | BK11: 684 | BL11: - | BM11: F | BN11: 427 | BO11: 233 | BP11: -
A12: 45115 | B12: A | C12: 无 | F12: 5.798 | H12: =IFERROR(E12/G12-1,"") | I12: 5.9385 | J12: =IFERROR(E12/I12,"") | K12: =IFERROR(E12/#REF!,"") | L12: 14405 | M12: - | R12: 0 | S12: 0 | W12: - | Y12: - | AA12: - | AC12: - | AD12: 24 | AE12: - | AG12: - | AH12: 1471 | AI12: - | AJ12: 468 | AK12: - | AL12: 41 | AM12: - | AN12: 11 | AO12: - | AP12: 799 | AQ12: - | AR12: 106 | AS12: - | AT12: 0.0111 | AU12: - | BH12: 0.93 | BI12: E | BJ12: 67 | BK12: 1041 | BL12: - | BM12: F | BN12: 267 | BO12: 470 | BP12: -
A13: 45116 | B13: 预约 | C13: 无 | F13: 0 | H13: =IFERROR(E13/G13-1,"") | I13: 0 | J13: =IFERROR(E13/I13,"") | K13: =IFERROR(E13/#REF!,"") | L13: 22082 | M13: - | R13: 0 | S13: 0 | W13: - | Y13: - | AA13: - | AC13: - | AD13: 32 | AE13: - | AG13: - | AH13: 1237 | AI13: - | AJ13: 503 | AK13: - | AL13: 28 | AM13: - | AN13: 12 | AO13: - | AP13: 511 | AQ13: - | AR13: 132 | AS13: - | AT13: 0 | AU13: - | BI13: E | BJ13: 98 | BK13: 741 | BL13: - | BM13: F | BN13: 574 | BO13: 192 | BP13: -
A14: 45117 | B14: 预约 | C14: 无 | F14: 0.5598 | H14: =IFERROR(E14/G14-1,"") | I14: 0 | J14: =IFERROR(E14/I14,"") | K14: =IFERROR(E14/#REF!,"") | L14: 15715 | M14: - | R14: 0 | S14: 0 | W14: - | Y14: - | AA14: - | AC14: - | AD14: 27 | AE14: - | AG14: - | AH14: 1008 | AI14: - | AJ14: 414 | AK14: - | AL14: 48 | AM14: - | AN14: 16 | AO14: - | AP14: 362 | AQ14: - | AR14: 114 | AS14: - | AT14: 0 | AU14: - | BH14: 0.95 | BI14: F | BJ14: 162 | BK14: 413 | BL14: - | BM14: F | BN14: 779 | BO14: 119 | BP14: -
A15: 45118 | B15: A | C15: 无 | F15: 7.8273 | H15: =IFERROR(E15/G15-1,"") | I15: 10.5568 | J15: =IFERROR(E15/I15,"") | K15: =IFERROR(E15/#REF!,"") | L15: 61678 | M15: - | R15: 2998 | S15: 0 | W15: - | Y15: - | AA15: - | AC15: - | AD15: 44 | AE15: - | AG15: - | AH15: 1129 | AI15: - | AJ15: 443 | AK15: - | AL15: 45 | AM15: - | AN15: 6 | AO15: - | AP15: 500 | AQ15: - | AR15: 146 | AS15: - | AT15: 0.018 | AU15: - | BI15: F | BJ15: 102 | BK15: 623 | BL15: - | BM15: F | BN15: 467 | BO15: 229 | BP15: - | BV15: 13QC05 | BW15: 13GD32 | BX15: 16GD31 | BY15: POP13QS04 | BZ15: 13QD31 | CA15: POP13QC05 | CB15: 13GD31 | CC15: 16QC05 | CD15: 13QD06W | CE15: 五星13QS04
A16: 45119 | B16: A | C16: 无 | F16: 4.6384 | H16: =IFERROR(E16/G16-1,"") | I16: 14.3 | J16: =IFERROR(E16/I16,"") | K16: =IFERROR(E16/#REF!,"") | L16: 27290 | M16: - | R16: 2899 | S16: 0 | W16: - | Y16: - | AA16: - | AC16: - | AD16: 37 | AE16: - | AG16: - | AH16: 1229 | AI16: - | AJ16: 335 | AK16: - | AL16: 37 | AM16: - | AN16: 13 | AO16: - | AP16: 592 | AQ16: - | AR16: 120 | AS16: - | AT16: 0.0109 | AU16: - | BH16: 1 | BI16: E | BJ16: 78 | BK16: 883 | BL16: - | BM16: F | BN16: 403 | BO16: 282 | BP16: -
A17: 45120 | B17: A | C17: 无 | F17: 8.697 | H17: =IFERROR(E17/G17-1,"") | I17: 11.7 | J17: =IFERROR(E17/I17,"") | K17: =IFERROR(E17/#REF!,"") | L17: 53304 | M17: - | R17: 11596 | S17: 0 | W17: - | Y17: - | AA17: - | AC17: - | AD17: 18 | AE17: - | AG17: - | AH17: 1295 | AI17: - | AJ17: 471 | AK17: - | AL17: 47 | AM17: - | AN17: 29 | AO17: - | AP17: 661 | AQ17: - | AR17: 114 | AS17: - | AT17: 0.0187 | AU17: - | BH17: 1 | BI17: E | BJ17: 78 | BK17: 893 | BL17: - | BM17: F | BN17: 440 | BO17: 254 | BP17: -
A18: 45121 | B18: 预售 | C18: 无 | F18: 0 | H18: =IFERROR(E18/G18-1,"") | I18: 0 | J18: =IFERROR(E18/I18,"") | K18: =IFERROR(E18/#REF!,"") | L18: 73478 | M18: - | R18: ？ | S18: 0 | W18: - | Y18: - | AA18: - | AC18: - | AD18: 28 | AE18: - | AG18: - | AH18: 1514 | AI18: - | AJ18: 665 | AK18: - | AL18: 60 | AM18: - | AN18: 18 | AO18: - | AP18: 805 | AQ18: - | AR18: 146 | AS18: - | AT18: 0 | AU18: - | BH18: 1 | BI18: E | BJ18: 70 | BK18: 936 | BL18: - | BM18: F | BN18: 393 | BO18: 301 | BP18: -
A19: 45122 | B19: 预售 | C19: 无 | F19: 0 | H19: =IFERROR(E19/G19-1,"") | I19: 0 | J19: =IFERROR(E19/I19,"") | K19: =IFERROR(E19/#REF!,"") | L19: 70076 | M19: - | R19: 0 | S19: 0 | W19: - | Y19: - | AA19: - | AC19: - | AD19: 26 | AE19: - | AG19: - | AH19: 1804 | AI19: - | AJ19: 726 | AK19: - | AL19: 64 | AM19: - | AN19: 26 | AO19: - | AP19: 1041 | AQ19: - | AR19: 120 | AS19: - | AT19: 0 | AU19: - | BI19: E | BJ19: 61 | BK19: 1155 | BL19: - | BM19: F | BN19: 241 | BO19: 509 | BP19: -
A20: 45123 | B20: S | C20: 无 | F20: 22.1923 | H20: =IFERROR(E20/G20-1,"") | I20: 36.4 | J20: =IFERROR(E20/I20,"") | K20: =IFERROR(E20/#REF!,"") | L20: 71151 | M20: - | R20: 0 | S20: 0 | W20: - | Y20: - | AA20: - | AC20: - | AD20: 41 | AE20: - | AG20: - | AH20: 1368 | AI20: - | AJ20: 570 | AK20: - | AL20: 56 | AM20: - | AN20: 27 | AO20: - | AP20: 613 | AQ20: - | AR20: 87 | AS20: - | AT20: 0.0386 | AU20: - | BI20: F | BJ20: 101 | BK20: 713 | BL20: - | BM20: F | BN20: 881 | BO20: 170 | BP20: -
A21: 45124 | B21: S | C21: 无 | F21: 8.0472 | H21: =IFERROR(E21/G21-1,"") | I21: 23.4 | J21: =IFERROR(E21/I21,"") | K21: =IFERROR(E21/#REF!,"") | L21: 54312 | M21: - | R21: 0 | S21: 0 | W21: - | Y21: - | AA21: - | AC21: - | AD21: 21 | AE21: - | AG21: - | AH21: 1084 | AI21: - | AJ21: 452 | AK21: - | AL21: 50 | AM21: - | AN21: 21 | AO21: - | AP21: 446 | AQ21: - | AR21: 49 | AS21: - | AT21: 0.0149 | AU21: - | BH21: 0.7 | BI21: F | BJ21: 141 | BK21: 457 | BL21: - | BM21: F | BN21: 1306 | BO21: 106 | BP21: -
A22: 45125 | B22: A | C22: 无 | F22: 3.4288 | H22: =IFERROR(E22/G22-1,"") | I22: 11.7 | J22: =IFERROR(E22/I22,"") | K22: =IFERROR(E22/#REF!,"") | L22: 61073 | M22: - | R22: 2899 | S22: 0 | W22: - | Y22: - | AA22: - | AC22: - | AD22: 19 | AE22: - | AG22: - | AH22: 989 | AI22: - | AJ22: 457 | AK22: - | AL22: 41 | AM22: - | AN22: 22 | AO22: - | AP22: 436 | AQ22: - | AR22: 58 | AS22: - | AT22: 0.0054 | AU22: - | BH22: 0.85 | BI22: F | BJ22: 144 | BK22: 442 | BL22: - | BM22: F | BN22: 762 | BO22: 152 | BP22: - | BV22: 13QC05 | BW22: 16GD31 | BX22: POP13QS04 | BY22: 13GD32 | BZ22: 13QD31 | CA22: 13QD06W | CB22: 海尔锦绣 | CC22: 16GD32 | CD22: 16QD31 | CE22: 五星13QS04
A23: 45126 | B23: A | C23: 无 | F23: 4.2845 | H23: =IFERROR(E23/G23-1,"") | I23: 0 | J23: =IFERROR(E23/I23,"") | K23: =IFERROR(E23/#REF!,"") | L23: 63908 | M23: - | R23: 2899 | S23: 0 | W23: - | Y23: - | AA23: - | AC23: - | AD23: 15 | AE23: - | AG23: - | AH23: 946 | AI23: - | AJ23: 411 | AK23: - | AL23: 40 | AM23: - | AN23: 9 | AO23: - | AP23: 392 | AQ23: - | AR23: 60 | AS23: - | AT23: 0.0082 | AU23: - | BH23: 1 | BI23: F | BJ23: 172 | BK23: 373 | BL23: - | BM23: F | BN23: 1064 | BO23: 108 | BP23: -
A24: 45127 | B24: A | C24: 无 | F24: 6.2818 | H24: =IFERROR(E24/G24-1,"") | I24: 22.1 | J24: =IFERROR(E24/I24,"") | K24: =IFERROR(E24/#REF!,"") | L24: 285852 | M24: - | R24: 2899 | S24: 0 | W24: - | Y24: - | AA24: - | AC24: - | AD24: 17 | AE24: - | AG24: - | AH24: 982 | AI24: - | AJ24: 450 | AK24: - | AL24: 27 | AM24: - | AN24: 20 | AO24: - | AP24: 407 | AQ24: - | AR24: 48 | AS24: - | AT24: 0.0139 | AU24: - | BH24: 1 | BI24: F | BJ24: 171 | BK24: 382 | BL24: - | BM24: F | BN24: 853 | BO24: 112 | BP24: -
A25: 45128 | B25: A | C25: 无 | F25: 8.669 | H25: =IFERROR(E25/G25-1,"") | I25: 16.9 | J25: =IFERROR(E25/I25,"") | K25: =IFERROR(E25/#REF!,"") | L25: 678109 | M25: - | R25: 2759 | S25: 0 | W25: - | Y25: - | AA25: - | AC25: - | AD25: 16 | AE25: - | AG25: - | AH25: 1205 | AI25: - | AJ25: 566 | AK25: - | AL25: 41 | AM25: - | AN25: 889 | AO25: - | AP25: 602 | AQ25: - | AR25: 73 | AS25: - | AT25: 0.0108 | AU25: - | BH25: 1 | BI25: F | BJ25: 101 | BK25: 597 | BL25: - | BM25: F | BN25: 413 | BO25: 268 | BP25: -
A26: 45129 | B26: 预售 | C26: 无 | F26: 0.8397 | H26: =IFERROR(E26/G26-1,"") | I26: 11.7 | J26: =IFERROR(E26/I26,"") | K26: =IFERROR(E26/#REF!,"") | L26: 71757 | M26: - | R26: 0 | S26: 0 | W26: - | Y26: - | AA26: - | AC26: - | AD26: 25 | AE26: - | AG26: - | AH26: 1760 | AI26: - | AJ26: 764 | AK26: - | AL26: 54 | AM26: - | AN26: 2209 | AO26: - | AP26: 934 | AQ26: - | AR26: 111 | AS26: - | AT26: 0 | AU26: - | BI26: E | BJ26: 60 | BK26: 1152 | BL26: - | BM26: F | BN26: 293 | BO26: 445 | BP26: -
A27: 45130 | B27: 预售 | C27: 无 | F27: 0 | H27: =IFERROR(E27/G27-1,"") | I27: 0 | J27: =IFERROR(E27/I27,"") | K27: =IFERROR(E27/#REF!,"") | L27: 85972 | M27: - | R27: 8697 | S27: 0 | W27: - | Y27: - | AA27: - | AC27: - | AD27: 26 | AE27: - | AG27: - | AH27: 1940 | AI27: - | AJ27: 931 | AK27: - | AL27: 80 | AM27: - | AN27: 823 | AO27: - | AP27: 1140 | AQ27: - | AR27: 130 | AS27: - | AT27: 0 | AU27: - | BI27: E | BJ27: 58 | BK27: 1364 | BL27: - | BM27: F | BN27: 303 | BO27: 410 | BP27: -
A28: 45131 | B28: 预售 | C28: 无 | F28: 30.8233 | H28: =IFERROR(E28/G28-1,"") | I28: 23.4 | J28: =IFERROR(E28/I28,"") | K28: =IFERROR(E28/#REF!,"") | L28: 132042 | M28: - | R28: 22712 | S28: 0 | W28: - | Y28: - | AA28: - | AC28: - | AD28: 18 | AE28: - | AG28: - | AH28: 1812 | AI28: - | AJ28: 722 | AK28: - | AL28: 76 | AM28: - | AN28: 1842 | AO28: - | AP28: 937 | AQ28: - | AR28: 117 | AS28: - | AT28: 0.0258 | AU28: - | BH28: 1 | BI28: E | BJ28: 60 | BK28: 1233 | BL28: - | BM28: F | BN28: 345 | BO28: 342 | BP28: -
A29: 45132 | B29: S | C29: 无 | F29: 19.0114 | H29: =IFERROR(E29/G29-1,"") | I29: 18.2 | J29: =IFERROR(E29/I29,"") | K29: =IFERROR(E29/#REF!,"") | L29: 90986 | M29: - | R29: 8697 | S29: 0 | W29: - | Y29: - | AA29: - | AC29: - | AD29: 24 | AE29: - | AG29: - | AH29: 1662 | AI29: - | AJ29: 257 | AK29: - | AL29: 64 | AM29: - | AN29: 906 | AO29: - | AP29: 924 | AQ29: - | AR29: 96 | AS29: - | AT29: 0.0223 | AU29: - | BH29: 1 | BI29: D | BJ29: 48 | BK29: 1285 | BL29: - | BM29: F | BN29: 285 | BO29: 405 | BP29: - | BV29: 13QC05 | BW29: 16GD31 | BX29: 五星13QS04 | BY29: 13GD32 | BZ29: 16GD32 | CA29: 厂直16GD32 | CB29: 16QC05 | CC29: 13QD31 | CD29: 16QD06W | CE29: 厂直16QC05
A30: 45133 | B30: A | C30: 无 | F30: 18.5839 | H30: =IFERROR(E30/G30-1,"") | I30: 10.4 | J30: =IFERROR(E30/I30,"") | K30: =IFERROR(E30/#REF!,"") | L30: 72281 | M30: - | R30: 8697 | S30: 0 | W30: - | Y30: - | AA30: - | AC30: - | AD30: 18 | AE30: - | AG30: - | AH30: 1784 | AI30: - | AJ30: 414 | AK30: - | AL30: 52 | AM30: - | AN30: 1044 | AO30: - | AP30: 1036 | AQ30: - | AR30: 113 | AS30: - | AT30: 0.0173 | AU30: - | BI30: D | BJ30: 37 | BK30: 1538 | BL30: - | BM30: F | BN30: 229 | BO30: 518 | BP30: -
A31: 45134 | B31: A | C31: 无 | F31: 19.5434 | H31: =IFERROR(E31/G31-1,"") | I31: 13 | J31: =IFERROR(E31/I31,"") | K31: =IFERROR(E31/#REF!,"") | L31: 89573 | M31: - | R31: 8557 | S31: 0 | W31: - | Y31: - | AA31: - | AC31: - | AD31: 19 | AE31: - | AG31: - | AH31: 1747 | AI31: - | AJ31: 603 | AK31: - | AL31: 63 | AM31: - | AN31: 1569 | AO31: - | AP31: 998 | AQ31: - | AR31: 136 | AS31: - | AT31: 0.0138 | AU31: - | BH31: 1 | BI31: D | BJ31: 47 | BK31: 1233 | BL31: - | BM31: F | BN31: 252 | BO31: 480 | BP31: -
A32: 45135 | B32: A | C32: 无 | F32: 16.3886 | H32: =IFERROR(E32/G32-1,"") | I32: 13 | J32: =IFERROR(E32/I32,"") | K32: =IFERROR(E32/#REF!,"") | L32: 111514 | M32: - | R32: 8417 | S32: 0 | W32: - | Y32: - | AA32: - | AC32: - | AD32: 17 | AE32: - | AG32: - | AH32: 1902 | AI32: - | AJ32: 512 | AK32: - | AL32: 48 | AM32: - | AN32: 1345 | AO32: - | AP32: 1085 | AQ32: - | AR32: 128 | AS32: - | AT32: 0.0158 | AU32: - | BH32: 1 | BI32: D | BJ32: 42 | BK32: 1351 | BL32: - | BM32: F | BN32: 219 | BO32: 542 | BP32: -
A33: 45136 | B33: 预售 | C33: 无 | F33: 0.6234 | H33: =IFERROR(E33/G33-1,"") | I33: 0 | J33: =IFERROR(E33/I33,"") | K33: =IFERROR(E33/#REF!,"") | L33: 70469 | M33: - | R33: 0 | S33: 0 | W33: - | Y33: - | AA33: - | AC33: - | AD33: 32 | AE33: - | AG33: - | AH33: 2303 | AI33: - | AJ33: 593 | AK33: - | AL33: 85 | AM33: - | AN33: 1508 | AO33: - | AP33: 1355 | AQ33: - | AR33: 226 | AS33: - | AT33: 0.0002 | AU33: - | BI33: D | BJ33: 42 | BK33: 1666 | BL33: - | BM33: F | BN33: 198 | BO33: 616 | BP33: -
A34: 45137 | B34: 预售 | C34: 无 | F34: 0 | H34: =IFERROR(E34/G34-1,"") | I34: 0 | J34: =IFERROR(E34/I34,"") | K34: =IFERROR(E34/#REF!,"") | L34: 85772 | M34: - | O34: 25.8011 | P34: / | Q34: 0.2352 | R34: 0 | S34: 0 | W34: - | Y34: - | AA34: - | AC34: - | AD34: 20 | AE34: - | AG34: - | AH34: 1899 | AI34: - | AJ34: 703 | AK34: - | AL34: 42 | AM34: - | AN34: 32 | AO34: - | AP34: 2273 | AQ34: - | AR34: 459 | AS34: - | AT34: 0 | AU34: - | AV34: 490 | AW34: - | AY34: - | AZ34: 98 | BA34: - | BB34: 0.2 | BC34: - | BH34: 0.8 | BI34: D | BJ34: 35 | BK34: 2169 | BL34: - | BM34: F | BN34: 199 | BO34: 665 | BP34: -
A35: 45138 | B35: 限时 | C35: 无 | F35: =50.5609-3.2 -> 47.3609 | H35: =IFERROR(E35/G35-1,"") | I35: 33 | J35: =IFERROR(E35/I35,"") | K35: =IFERROR(E35/#REF!,"") | L35: 143553 | M35: - | R35: 25811 | S35: 0 | W35: - | Y35: - | AA35: - | AC35: - | AD35: 27 | AE35: - | AG35: - | AH35: 2932 | AI35: - | AJ35: 996 | AK35: - | AL35: 96 | AM35: - | AN35: 1034 | AO35: - | AP35: 1801 | AQ35: - | AR35: 279 | AS35: - | AT35: 0.0359 | AU35: - | BH35: 1 | BI35: D | BJ35: 31 | BK35: 2349 | BL35: - | BM35: F | BN35: 171 | BO35: 721 | BP35: -
A36: 45139 | B36: S级 | C36: 无 | F36: =E36-2.8 -> #VALUE! | I36: 16 | J36: =IFERROR(E36/I36,"") | K36: =IFERROR(E36/#REF!,"") | L36: 131255 | M36: - | O36: 9.566 | R36: 3299 | W36: - | Y36: - | AA36: - | AC36: - | AD36: 10 | AE36: - | AG36: - | AH36: 2416 | AI36: - | AJ36: 642 | AK36: - | AL36: 78 | AM36: - | AN36: 1399 | AO36: - | AP36: 1426 | AQ36: - | AR36: 156 | AS36: - | AT36: 0.01845 | AV36: 175 | AW36: - | AX36: 0.0414 | AY36: - | BH36: 0.8 | BI36: D | BJ36: 29 | BK36: 2116 | BL36: - | BM36: F | BN36: 170 | BO36: 739 | BP36: - | BV36: 16GD31 | BW36: 13QC05 | BX36: 13GD32 | BY36: 五星13QS04 | BZ36: 16QC05 | CA36: 13GD32 | CB36: 海尔锦绣 | CC36: 13QD31 | CD36: 13QD06W | CE36: 16QD31
A37: 45140 | B37: A级 | C37: 无 | F37: =E37-1.7 -> #VALUE! | I37: 10 | J37: =IFERROR(E37/I37,"") | K37: =IFERROR(E37/#REF!,"") | L37: 125161 | M37: - | W37: - | Y37: - | AA37: - | AC37: - | AD37: 12 | AE37: - | AG37: - | AH37: 2767 | AI37: - | AJ37: 635 | AK37: - | AL37: 78 | AM37: - | AN37: 1116 | AO37: - | AP37: 1753 | AQ37: - | AR37: 248 | AS37: - | AT37: 0.0138 | BH37: 1 | BI37: D | BJ37: 21 | BK37: 2881 | BL37: - | BM37: F | BN37: 152 | BO37: 799 | BP37: - | BY37: 五星13QS04
A38: 45141 | B38: A级 | C38: 无 | F38: =E38-1.7 -> #VALUE! | I38: 9 | J38: =IFERROR(E38/I38,"") | K38: =IFERROR(E38/#REF!,"") | L38: 113436 | M38: - | W38: - | Y38: - | AA38: - | AC38: - | AD38: 17 | AE38: - | AG38: - | AH38: 2657 | AI38: - | AJ38: 620 | AK38: - | AL38: 80 | AM38: - | AN38: 4352 | AO38: - | AP38: 1504 | AQ38: - | AR38: 208 | AS38: - | AT38: 0.0058 | BH38: 1 | BI38: D | BJ38: 30 | BK38: 2206 | BL38: - | BM38: F | BN38: 187 | BO38: 674 | BP38: - | BY38: 五星13QS04
A39: 45142 | B39: A级 | C39: 无 | F39: =E39-1.9 -> #VALUE! | I39: 11 | J39: =IFERROR(E39/I39,"") | K39: =IFERROR(E39/#REF!,"") | L39: 70027 | M39: - | W39: - | Y39: - | AA39: - | AC39: - | AD39: 18 | AE39: - | AG39: - | AH39: 3037 | AI39: - | AJ39: 665 | AK39: - | AL39: 90 | AM39: - | AN39: 1181 | AO39: - | AP39: 1806 | AQ39: - | AR39: 249 | AS39: - | BH39: 0.95 | BI39: D | BJ39: 26 | BK39: 2383 | BL39: - | BM39: F | BN39: 144 | BO39: 837 | BP39: - | BY39: 五星13QS04
A40: 45143 | B40: 预售 | C40: 无 | F40: =E40 | I40: 0 | J40: =IFERROR(E40/I40,"") | K40: =IFERROR(E40/#REF!,"") | L40: 55948 | M40: - | W40: - | Y40: - | AA40: - | AC40: - | AD40: 19 | AE40: - | AG40: - | AH40: 3019 | AI40: - | AJ40: 865 | AK40: - | AL40: 105 | AM40: - | AN40: 861 | AO40: - | AP40: 1786 | AQ40: - | AR40: 327 | AS40: - | BH40: 0.85 | BI40: D | BJ40: 27 | BK40: 2433 | BL40: - | BM40: F | BN40: 139 | BO40: 938 | BP40: - | BY40: 五星13QS04
A41: 45144 | B41: 预售 | C41: 无 | F41: =E41 | I41: 0 | J41: =IFERROR(E41/I41,"") | K41: =IFERROR(E41/#REF!,"") | L41: 32472 | M41: - | W41: - | Y41: - | AA41: - | AC41: - | AD41: 33 | AE41: - | AG41: - | AH41: 3418 | AI41: - | AJ41: 994 | AK41: - | AL41: 100 | AM41: - | AN41: 2723 | AO41: - | AP41: 2051 | AQ41: - | AR41: 413 | AS41: - | BH41: 0.9 | BI41: D | BJ41: 24 | BK41: 2956 | BL41: - | BM41: F | BN41: 104 | BO41: 1156 | BP41: - | BY41: 五星13QS04
A42: 45145 | B42: S级 | C42: 无 | F42: =E42-0.8 -> #VALUE! | I42: 38 | J42: =IFERROR(E42/I42,"") | K42: =IFERROR(E42/#REF!,"") | L42: 181522 | M42: - | W42: - | Y42: - | AA42: - | AC42: - | AD42: 20 | AE42: - | AG42: - | AH42: 3690 | AI42: - | AJ42: 1057 | AK42: - | AL42: 126 | AM42: - | AN42: 2722 | AO42: - | AP42: 2100 | AQ42: - | AR42: 392 | AS42: - | BH42: 0.9 | BI42: D | BJ42: 26 | BK42: 2682 | BL42: - | BM42: F | BN42: 107 | BO42: 1098 | BP42: - | BY42: 五星13QS04
A43: 45146 | B43: S级 | C43: 无 | F43: =E43-3 -> #VALUE! | I43: 16 | J43: =IFERROR(E43/I43,"") | K43: =IFERROR(E43/#REF!,"") | L43: 131539 | M43: - | W43: - | Y43: - | AA43: - | AC43: - | AD43: 17 | AE43: - | AG43: - | AH43: 3603 | AI43: - | AJ43: 903 | AK43: - | AL43: 97 | AM43: - | AN43: 2610 | AO43: - | AP43: 1979 | AQ43: - | AR43: 405 | AS43: - | BH43: 1 | BI43: D | BJ43: 24 | BK43: 2602 | BL43: - | BM43: F | BN43: 117 | BO43: 982 | BP43: - | BV43: 16GD31 | BW43: 13QC05 | BX43: 16GD32 | BY43: 13GD32 | BZ43: 海尔锦绣 | CA43: POP13QS04 | CB43: 16QC05 | CC43: 能率13EA2 | CD43: 海尔KL3U1 | CE43: 16QD06W
A44: 45147 | B44: A级 | C44: 无 | F44: =E44-1.4 -> #VALUE! | I44: 9 | J44: =IFERROR(E44/I44,"") | K44: =IFERROR(E44/#REF!,"") | L44: 130187 | M44: - | W44: - | Y44: - | AA44: - | AC44: - | AE44: - | AG44: - | AH44: 3452 | AI44: - | AJ44: 741 | AK44: - | AL44: 101 | AM44: - | AN44: 2664 | AO44: - | AP44: 2039 | AQ44: - | AR44: 326 | AS44: - | BH44: 1 | BI44: C | BJ44: 19 | BK44: 3344 | BL44: - | BM44: F | BN44: 104 | BO44: 1112 | BP44: -
A45: 45148 | B45: A级 | C45: 无 | F45: =E45-1.1 -> #VALUE! | I45: 10 | J45: =IFERROR(E45/I45,"") | K45: =IFERROR(E45/#REF!,"") | L45: 200234 | M45: - | P45: - | Q45: =O45/E45 -> #VALUE! | W45: - | Y45: - | AA45: - | AC45: - | AE45: - | AG45: - | AH45: 3255 | AI45: - | AJ45: 725 | AK45: - | AL45: 91 | AM45: - | AN45: 3056 | AO45: - | AP45: 1832 | AQ45: - | AR45: 353 | AS45: - | AW45: - | AX45: 0 | AY45: - | BA45: - | BB45: #DIV/0! | BH45: 1 | BI45: D | BJ45: 26 | BK45: 2328 | BL45: - | BM45: F | BN45: 138 | BO45: 862 | BP45: -
A46: 45149 | B46: 预售 | C46: 无 | F46: =E46 | I46: 0 | J46: =IFERROR(E46/I46,"") | K46: =IFERROR(E46/#REF!,"") | L46: 34788 | M46: - | O46: 3.18 | P46: - | Q46: =O46/E46 -> #VALUE! | W46: - | Y46: - | AA46: - | AC46: - | AE46: - | AG46: - | AH46: 3269 | AI46: - | AJ46: 957 | AK46: - | AL46: 96 | AM46: - | AN46: 2695 | AO46: - | AP46: 1771 | AQ46: - | AR46: 452 | AS46: - | AV46: 248 | AW46: - | AX46: 0.038780297 | AY46: - | AZ46: 21 | BA46: - | BB46: 0.084677419 | BH46: 1 | BI46: D | BJ46: 24 | BK46: 2225 | BL46: - | BM46: F | BN46: 160 | BO46: 813 | BP46: -
A47: 45150 | B47: 预售 | C47: 无 | F47: =E47 | I47: 0 | J47: =IFERROR(E47/I47,"") | K47: =IFERROR(E47/#REF!,"") | L47: 15912 | M47: - | O47: 7.64 | P47: - | Q47: =O47/E47 -> #VALUE! | W47: - | Y47: - | AA47: - | AC47: - | AE47: - | AG47: - | AH47: 3563 | AI47: - | AJ47: 1110 | AK47: - | AL47: 89 | AM47: - | AN47: 3136 | AO47: - | AP47: 2031 | AQ47: - | AR47: 469 | AS47: - | AV47: 198 | AW47: - | AX47: 0.027469478 | AY47: - | AZ47: 15 | BA47: - | BB47: 0.075757576 | BH47: 0.96 | BI47: C | BJ47: 18 | BK47: 3221 | BL47: - | BM47: F | BN47: 105 | BO47: 1299 | BP47: -
A48: 45151 | B48: 预售 | C48: 无 | F48: =E48 | I48: 0 | J48: =IFERROR(E48/I48,"") | K48: =IFERROR(E48/#REF!,"") | L48: 2599 | M48: - | O48: 3.59 | P48: - | Q48: =O48/E48 -> #VALUE! | W48: - | Y48: - | AA48: - | AC48: - | AE48: - | AG48: - | AH48: 3625 | AI48: - | AJ48: 1199 | AK48: - | AL48: 76 | AM48: - | AN48: 3126 | AO48: - | AP48: 2104 | AQ48: - | AR48: 457 | AS48: - | AV48: 222 | AW48: - | AX48: 0.030523855 | AY48: - | AZ48: 17 | BA48: - | BB48: 0.076576577 | BH48: 0.96 | BI48: C | BJ48: 20 | BK48: 3399 | BL48: - | BM48: F | BN48: 101 | BO48: 1427 | BP48: -
A49: 45152 | B49: 预售+S级 | C49: 无 | F49: =E49 | I49: 50 | J49: =IFERROR(E49/I49,"") | K49: =IFERROR(E49/#REF!,"") | L49: 277544 | M49: - | O49: 24.64 | P49: - | Q49: =O49/E49 -> #VALUE! | W49: - | Y49: - | AA49: - | AC49: - | AE49: - | AG49: - | AH49: 4415 | AI49: - | AJ49: 1422 | AK49: - | AL49: 151 | AM49: - | AN49: 2648 | AO49: - | AP49: 2532 | AQ49: - | AR49: 547 | AS49: - | AV49: 344 | AW49: - | AX49: 0.044347041 | AY49: - | AZ49: 78 | BA49: - | BB49: 0.22674419 | BH49: 0.96 | BI49: C | BJ49: 15 | BK49: 4055 | BL49: - | BM49: E | BN49: 78 | BO49: 1613 | BP49: -
A50: 45153 | B50: S级 | C50: 无 | F50: =E50-3 -> #VALUE! | I50: 22 | J50: =IFERROR(E50/I50,"") | K50: =IFERROR(E50/#REF!,"") | L50: 183632 | M50: - | O50: 9.41 | P50: - | Q50: =O50/E50 -> #VALUE! | W50: - | Y50: - | AA50: - | AC50: - | AE50: - | AG50: - | AH50: 3694 | AI50: - | AJ50: 1106 | AK50: - | AL50: 101 | AM50: - | AN50: 2637 | AO50: - | AP50: 2075 | AQ50: - | AR50: 413 | AS50: - | AV50: 288 | AW50: - | AX50: 0.04219162 | AY50: - | AZ50: 32 | BA50: - | BB50: 0.11111111 | BH50: 0.93 | BI50: D | BJ50: 23 | BK50: 2648 | BL50: - | BM50: F | BN50: 117 | BO50: 1157 | BP50: - | BV50: 16GD31 | BW50: 13QC05 | BX50: 16GD32 | BY50: 海尔锦绣 | BZ50: 13GD32 | CA50: 能率13EA2 | CB50: 16QC05 | CC50: 16GD61R | CD50: 能率13E4 | CE50: 厂直16QD31+SG
A51: 45154 | B51: A级 | C51: 无 | F51: =E51-1.7 -> #VALUE! | I51: 0 | J51: =IFERROR(E51/I51,"") | K51: =IFERROR(E51/#REF!,"") | L51: 156930 | M51: - | O51: 4.36 | P51: - | Q51: =O51/E51 -> #VALUE! | W51: - | Y51: - | AA51: - | AC51: - | AE51: - | AG51: - | AH51: 3413 | AI51: - | AJ51: 1198 | AK51: - | AL51: 88 | AM51: - | AN51: 2524 | AO51: - | AP51: 2007 | AQ51: - | AR51: 353 | AS51: - | AV51: 250 | AW51: - | AX51: 0.038249694 | AY51: - | AZ51: 15 | BA51: - | BB51: 0.06 | BH51: 1 | BI51: D | BJ51: 22 | BK51: 2627 | BL51: - | BM51: F | BN51: 102 | BO51: 1260 | BP51: -
A52: 45155 | B52: 预售+S级 | C52: 无 | F52: =E52-0.5 -> #VALUE! | I52: 32 | J52: =IFERROR(E52/I52,"") | K52: =IFERROR(E52/#REF!,"") | L52: 122957 | M52: - | O52: 7.7 | P52: - | Q52: =O52/E52 -> #VALUE! | W52: - | Y52: - | AA52: - | AC52: - | AE52: - | AG52: - | AH52: 3357 | AI52: - | AJ52: 1288 | AK52: - | AL52: 115 | AM52: - | AN52: 2615 | AO52: - | AP52: 1828 | AQ52: - | AR52: 429 | AS52: - | AV52: 300 | AW52: - | AX52: 0.045669052 | AY52: - | AZ52: 22 | BA52: - | BB52: 0.073333333 | BH52: 1 | BI52: D | BJ52: 24 | BK52: 2503 | BL52: - | BM52: F | BN52: 112 | BO52: 1202 | BP52: -
A53: 45156 | B53: S级 | C53: 无 | F53: =E53-0.8 -> #VALUE! | I53: 20 | J53: =IFERROR(E53/I53,"") | K53: =IFERROR(E53/#REF!,"") | L53: 161399 | M53: - | O53: 6.9 | P53: - | Q53: =O53/E53 -> #VALUE! | W53: - | Y53: - | AA53: - | AC53: - | AE53: - | AG53: - | AH53: 3584 | AI53: - | AJ53: 1260 | AK53: - | AL53: 83 | AM53: - | AN53: 2260 | AO53: - | AP53: 2024 | AQ53: - | AR53: 395 | AS53: - | AV53: 329 | AW53: - | AX53: 0.051039404 | AY53: - | AZ53: 24 | BA53: - | BB53: 0.072948328 | BH53: 1 | BI53: C | BJ53: 15 | BK53: 3085 | BL53: - | BM53: E | BN53: 83 | BO53: 1546 | BP53: -
A54: 45157 | B54: A级 | C54: 无 | F54: =E54 | I54: 9 | J54: =IFERROR(E54/I54,"") | K54: =IFERROR(E54/#REF!,"") | L54: 93061 | M54: - | O54: 3.8 | P54: - | Q54: =O54/E54 -> #VALUE! | W54: - | Y54: - | AA54: - | AC54: - | AE54: - | AG54: - | AH54: 3419 | AI54: - | AJ54: 832 | AK54: - | AL54: 94 | AM54: - | AN54: 2613 | AO54: - | AP54: 2003 | AQ54: - | AR54: 340 | AS54: - | AV54: 276 | AX54: 0.043064441 | AZ54: 13 | BB54: 0.047101449 | BH54: 1 | BI54: D | BJ54: 21 | BK54: 3012 | BL54: - | BM54: F | BN54: 101 | BO54: 1361 | BP54: -
A55: 45158 | B55: A级 | C55: 无 | F55: =E55 | I55: 10 | J55: =IFERROR(E55/I55,"") | K55: =IFERROR(E55/#REF!,"") | L55: 105257 | M55: - | O55: 5.9 | P55: - | Q55: =O55/E55 -> #VALUE! | W55: - | Y55: - | AA55: - | AC55: - | AE55: - | AG55: - | AH55: 3517 | AI55: - | AJ55: 900 | AK55: - | AL55: 85 | AM55: - | AN55: 2626 | AO55: - | AP55: 2167 | AQ55: - | AR55: 338 | AS55: - | AV55: 281 | AX55: 0.042986079 | AZ55: 22 | BB55: 0.078291815 | BI55: C | BJ55: 20 | BK55: 3346 | BL55: - | BM55: E | BN55: 86 | BO55: 1544 | BP55: -
A56: 45159 | B56: A级 | C56: 无 | F56: =E56-1 -> #VALUE! | I56: 11 | J56: =IFERROR(E56/I56,"") | K56: =IFERROR(E56/#REF!,"") | L56: 120193 | M56: - | O56: 4.65 | Q56: =O56/E56 -> #VALUE! | W56: - | Y56: - | AA56: - | AC56: - | AE56: - | AG56: - | AH56: 3419 | AI56: - | AJ56: 795 | AK56: - | AL56: 70 | AM56: - | AN56: 2657 | AO56: - | AP56: 2034 | AQ56: - | AR56: 316 | AS56: - | AV56: 265 | AX56: 0.041361011 | AZ56: 19 | BB56: 0.071698113 | BI56: D | BJ56: 24 | BK56: 3031 | BL56: - | BM56: E | BN56: 99 | BO56: 1346 | BP56: -
A57: 45160 | B57: A级 | C57: 无 | F57: =E57-1.4 -> #VALUE! | I57: 0 | J57: =IFERROR(E57/I57,"") | K57: =IFERROR(E57/#REF!,"") | L57: 121427 | M57: - | O57: 5.1 | Q57: =O57/E57 -> #VALUE! | W57: - | Y57: - | AA57: - | AC57: - | AE57: - | AG57: - | AH57: 2946 | AI57: - | AJ57: 726 | AK57: - | AL57: 78 | AM57: - | AN57: 2645 | AO57: - | AP57: 1704 | AQ57: - | AR57: 274 | AS57: - | AV57: 216 | AX57: 0.036691014 | AZ57: 16 | BB57: 0.074074074 | BI57: D | BJ57: 22 | BK57: 2538 | BL57: - | BM57: F | BN57: 136 | BO57: 921 | BP57: - | BV57: 16GD31 | BW57: 13QC05 | BX57: 13GD32 | BY57: 16GD32 | BZ57: 海尔锦绣 | CA57: 13QD06W | CB57: POP13QS04 | CC57: 16QD31 | CD57: 能率13EA2 | CE57: 16QC05
A58: 45161 | B58: A级 | C58: 无 | F58: =E58-2 -> #VALUE! | I58: 0 | J58: =IFERROR(E58/I58,"") | K58: =IFERROR(E58/#REF!,"") | L58: 91884 | M58: - | O58: 5.4 | Q58: =O58/E58 -> #VALUE! | W58: - | Y58: - | AA58: - | AC58: - | AE58: - | AG58: - | AH58: 3018 | AI58: - | AJ58: 432 | AK58: - | AL58: 71 | AM58: - | AN58: 2340 | AO58: - | AP58: 1743 | AQ58: - | AR58: 302 | AS58: - | AV58: 247 | AX58: 0.045023697 | AZ58: 23 | BB58: 0.093117409 | BI58: D | BJ58: 25 | BK58: 2601 | BL58: - | BM58: F | BN58: 138 | BO58: 1032 | BP58: -
A59: 45162 | B59: A级 | C59: 无 | F59: =E59-0.5 -> #VALUE! | I59: 33 | J59: =IFERROR(E59/I59,"") | K59: =IFERROR(E59/#REF!,"") | L59: 100601 | M59: - | O59: 4.2 | Q59: =O59/E59 -> #VALUE! | W59: - | Y59: - | AA59: - | AC59: - | AE59: - | AG59: - | AH59: 2871 | AI59: - | AJ59: 881 | AK59: - | AL59: 62 | AM59: - | AN59: 1692 | AO59: - | AP59: 1565 | AQ59: - | AR59: 291 | AS59: - | AV59: 196 | AX59: 0.0397808 | AZ59: 14 | BB59: 0.071428571 | BI59: D | BJ59: 25 | BK59: 2673 | BL59: - | BM59: F | BN59: 140 | BO59: 932 | BP59: -
A60: 45163 | B60: A级 | C60: 无 | F60: =E60-1 -> #VALUE! | I60: 17 | J60: =IFERROR(E60/I60,"") | K60: =IFERROR(E60/#REF!,"") | L60: 138363 | M60: - | O60: 5.12 | Q60: =O60/E60 -> #VALUE! | W60: - | Y60: - | AA60: - | AC60: - | AE60: - | AG60: - | AH60: 2741 | AI60: - | AJ60: 1031 | AK60: - | AL60: 60 | AM60: - | AN60: 1721 | AO60: - | AP60: 1604 | AQ60: - | AR60: 289 | AS60: - | AV60: 209 | AX60: 0.042086186 | AZ60: 20 | BB60: 0.09569378 | BI60: D | BJ60: 26 | BK60: 2787 | BL60: - | BM60: F | BN60: 139 | BO60: 948 | BP60: -
A61: 45164 | B61: A级 | C61: 无 | F61: =E61 | I61: 9 | J61: =IFERROR(E61/I61,"") | K61: =IFERROR(E61/#REF!,"") | L61: 112689 | M61: - | O61: 3.93 | Q61: =O61/E61 -> #VALUE! | W61: - | Y61: - | AA61: - | AC61: - | AE61: - | AG61: - | AH61: 2906 | AI61: - | AJ61: 906 | AK61: - | AL61: 88 | AM61: - | AN61: 1993 | AO61: - | AP61: 1711 | AQ61: - | AR61: 293 | AS61: - | AV61: 236 | AX61: 0.044013428 | AZ61: 14 | BB61: 0.059322034 | BI61: D | BJ61: 28 | BK61: 2685 | BL61: - | BM61: F | BN61: 155 | BO61: 949 | BP61: -
A62: 45165 | B62: A级 | C62: 无 | F62: =E62 | I62: 10 | J62: =IFERROR(E62/I62,"") | K62: =IFERROR(E62/#REF!,"") | L62: 123727 | M62: - | O62: 6.13 | Q62: =O62/E62 -> #VALUE! | W62: - | Y62: - | AA62: - | AC62: - | AE62: - | AG62: - | AH62: 3009 | AI62: - | AJ62: 367 | AK62: - | AL62: 93 | AM62: - | AN62: 1974 | AO62: - | AP62: 1797 | AQ62: - | AR62: 325 | AS62: - | AV62: 220 | AX62: 0.042985541 | AZ62: 17 | BB62: 0.077272727 | BI62: D | BJ62: 27 | BK62: 2604 | BL62: - | BM62: F | BN62: 164 | BO62: 1011 | BP62: -
A63: 45166 | B63: A级 | C63: 无 | F63: =E63 | I63: 11 | J63: =IFERROR(E63/I63,"") | K63: =IFERROR(E63/#REF!,"") | L63: 112425 | M63: - | O63: 5.53 | Q63: =O63/E63 -> #VALUE! | W63: - | Y63: - | AA63: - | AC63: - | AE63: - | AG63: - | AH63: 2984 | AI63: - | AJ63: 646 | AK63: - | AL63: 97 | AM63: - | AN63: 1854 | AO63: - | AP63: 1694 | AQ63: - | AR63: 320 | AS63: - | AV63: 207 | AX63: 0.040295893 | AZ63: 12 | BB63: 0.057971014 | BI63: D | BJ63: 27 | BK63: 2310 | BL63: - | BM63: F | BN63: 171 | BO63: 899 | BP63: -
A64: 45167 | B64: 预售 | C64: 无 | F64: =E64 | I64: 0 | J64: =IFERROR(E64/I64,"") | K64: =IFERROR(E64/#REF!,"") | L64: 10896 | M64: - | O64: 10.41 | Q64: =O64/E64 -> #VALUE! | W64: - | Y64: - | AA64: - | AC64: - | AE64: - | AG64: - | AH64: 3000 | AI64: - | AJ64: 660 | AK64: - | AL64: 95 | AM64: - | AN64: 1832 | AO64: - | AP64: 1636 | AQ64: - | AR64: 330 | AS64: - | AV64: 253 | AX64: 0.049356223 | AZ64: 32 | BB64: 0.12648221 | BI64: D | BJ64: 29 | BK64: 2382 | BL64: - | BM64: F | BN64: 160 | BO64: 1020 | BP64: - | BV64: 13QC05 | BW64: 16GD31 | BX64: 13GD32 | BY64: 海尔锦绣 | BZ64: 能率13EA2 | CA64: 16GD32 | CB64: 16QC05 | CC64: 16QD31 | CD64: 16GD61R | CE64: 史密斯TC1
A65: 45168 | B65: 预售 | C65: 无 | F65: =E65 | I65: 0 | J65: =IFERROR(E65/I65,"") | K65: =IFERROR(E65/#REF!,"") | L65: 19683 | M65: - | O65: 6.26 | Q65: =O65/E65 -> #VALUE! | W65: - | Y65: - | AA65: - | AC65: - | AE65: - | AG65: - | AH65: 2912 | AI65: - | AJ65: 808 | AK65: - | AL65: 111 | AM65: - | AN65: 1664 | AO65: - | AP65: 1557 | AQ65: - | AR65: 354 | AS65: - | AV65: 214 | AX65: 0.043206138 | AZ65: 21 | BB65: 0.098130841 | BI65: D | BJ65: 31 | BK65: 2211 | BL65: - | BM65: F | BN65: 158 | BO65: 1034 | BP65: -
A66: 45169 | B66: 31号晚8开门红 | C66: 无 | F66: =E66 | I66: 43 | J66: =IFERROR(E66/I66,"") | K66: =IFERROR(E66/#REF!,"") | L66: 246600 | M66: - | O66: 8.4 | Q66: =O66/E66 -> #VALUE! | W66: - | Y66: - | AA66: - | AC66: - | AE66: - | AG66: - | AH66: 3194 | AI66: - | AJ66: 1004 | AK66: - | AL66: 82 | AM66: - | AN66: 1207 | AO66: - | AP66: 1772 | AQ66: - | AR66: 372 | AS66: - | AV66: 210 | AX66: 0.043192102 | AZ66: 27 | BB66: 0.12857143 | BI66: D | BJ66: 27 | BK66: 2306 | BL66: - | BM66: F | BN66: 144 | BO66: 1094 | BP66: -
A67: 45170 | F67: =E67 | J67: =IFERROR(E67/I67,"") | K67: =IFERROR(E67/#REF!,"") | L67: 155762 | M67: - | O67: 7.24 | Q67: =O67/E67 -> #VALUE! | W67: - | Y67: - | AA67: - | AC67: - | AE67: - | AG67: - | AH67: 2719 | AI67: - | AJ67: 802 | AK67: - | AL67: 80 | AM67: - | AN67: 1500 | AO67: - | AP67: 1488 | AQ67: - | AR67: 276 | AS67: - | AV67: 262 | AX67: 0.056857639 | AZ67: 19 | BB67: 0.072519084 | BI67: D | BJ67: 29 | BK67: 1810 | BL67: - | BM67: F | BN67: 170 | BO67: 903 | BP67: -
A68: 45171 | B68: 日销 | F68: =E68 | J68: =IFERROR(E68/I68,"") | K68: =IFERROR(E68/#REF!,"") | L68: 113042 | M68: - | O68: 8.77 | Q68: =O68/E68 -> #VALUE! | W68: - | Y68: - | AA68: - | AC68: - | AE68: - | AG68: - | AH68: 2995 | AI68: - | AJ68: 776 | AK68: - | AL68: 65 | AM68: - | AN68: 1582 | AO68: - | AP68: 1689 | AQ68: - | AR68: 324 | AS68: - | AV68: 241 | AX68: 0.048500704 | AZ68: 22 | BB68: 0.091286307 | BI68: D | BJ68: 28 | BK68: 2242 | BL68: - | BM68: F | BN68: 163 | BO68: 1028 | BP68: -
A69: 45172 | B69: 预售 | F69: =E69 | J69: =IFERROR(E69/I69,"") | K69: =IFERROR(E69/#REF!,"") | L69: 31469 | M69: - | O69: 1.81 | Q69: =O69/E69 -> #VALUE! | W69: - | Y69: - | AA69: - | AC69: - | AE69: - | AG69: - | AH69: 2696 | AI69: - | AJ69: 767 | AK69: - | AL69: 65 | AM69: - | AN69: 1542 | AO69: - | AP69: 1190 | AQ69: - | AR69: 365 | AS69: - | AV69: 171 | AX69: 0.037222464 | AZ69: 5 | BB69: 0.029239766 | BI69: E | BJ69: 62 | BK69: 1251 | BL69: - | BM69: F | BN69: 265 | BO69: 634 | BP69: -
A70: 45173 | B70: 晚8点 | F70: =E70 | J70: =IFERROR(E70/I70,"") | K70: =IFERROR(E70/#REF!,"") | L70: 221679 | M70: - | O70: 8.02 | Q70: =O70/E70 -> #VALUE! | W70: - | Y70: - | AA70: - | AC70: - | AE70: - | AG70: - | AH70: 2686 | AI70: - | AJ70: 734 | AK70: - | AL70: 94 | AM70: - | AN70: 1379 | AO70: - | AP70: 1262 | AQ70: - | AR70: 354 | AS70: - | AV70: 217 | AX70: 0.049206349 | AZ70: 26 | BB70: 0.11981567 | BI70: D | BJ70: 49 | BK70: 1368 | BL70: - | BM70: F | BN70: 269 | BO70: 567 | BP70: -
A71: 45174 | B71: 预售 | F71: =E71 | J71: =IFERROR(E71/I71,"") | K71: =IFERROR(E71/#REF!,"") | L71: 25752 | M71: - | O71: 3.04 | Q71: =O71/E71 -> #VALUE! | W71: - | Y71: - | AA71: - | AC71: - | AE71: - | AG71: - | AH71: 2981 | AI71: - | AJ71: 665 | AK71: - | AL71: 125 | AM71: - | AN71: 1328 | AO71: - | AP71: 1642 | AQ71: - | AR71: 346 | AS71: - | AV71: 235 | AX71: 0.050245884 | AZ71: 13 | BB71: 0.055319149 | BI71: D | BJ71: 23 | BK71: 2513 | BL71: - | BM71: F | BN71: 121 | BO71: 1048 | BP71: - | BV71: 16GD31 | BW71: 13QC05 | BX71: 16GD32 | BY71: 海尔锦绣 | BZ71: POP13QS04 | CA71: 16QC05 | CB71: 16GD61R | CC71: POP13GD31 | CD71: 厂直16QD31+SG | CE71: 厂直16QC05+SG
A72: 45175 | B72: 预售 | F72: =E72 | J72: =IFERROR(E72/I72,"") | K72: =IFERROR(E72/#REF!,"") | L72: 40157 | M72: - | O72: 7.22 | Q72: =O72/E72 -> #VALUE! | W72: - | Y72: - | AA72: - | AC72: - | AE72: - | AG72: - | AH72: 2883 | AI72: - | AJ72: 727 | AK72: - | AL72: 108 | AM72: - | AN72: 1252 | AO72: - | AP72: 1546 | AQ72: - | AR72: 376 | AS72: - | AV72: 206 | AX72: 0.045879733 | AZ72: 23 | BB72: 0.11165049 | BI72: D | BJ72: 27 | BK72: 2284 | BL72: - | BM72: F | BN72: 140 | BO72: 945 | BP72: -
A73: 45176 | B73: 7号晚8 | F73: =E73 | J73: =IFERROR(E73/I73,"") | K73: =IFERROR(E73/#REF!,"") | L73: 171524 | M73: - | O73: 14.33 | Q73: =O73/E73 -> #VALUE! | W73: - | Y73: - | AA73: - | AC73: - | AE73: - | AG73: - | AH73: 3140 | AI73: - | AJ73: 835 | AK73: - | AL73: 117 | AM73: - | AN73: 1355 | AO73: - | AP73: 1668 | AQ73: - | AR73: 422 | AS73: - | AV73: 300 | AX73: 0.061626952 | AZ73: 49 | BB73: 0.16333333 | BI73: D | BJ73: 28 | BK73: 2420 | BL73: - | BM73: F | BN73: 137 | BO73: 929 | BP73: -
A74: 45177 | F74: =E74 | J74: =IFERROR(E74/I74,"") | K74: =IFERROR(E74/#REF!,"") | L74: 112426 | M74: - | O74: 4.74 | Q74: =O74/E74 -> #VALUE! | W74: - | Y74: - | AA74: - | AC74: - | AE74: - | AG74: - | AH74: 3972 | AI74: - | AJ74: 713 | AK74: - | AL74: 118 | AM74: - | AN74: 1378 | AO74: - | AP74: 1617 | AQ74: - | AR74: 323 | AS74: - | AV74: 233 | AX74: 0.050873362 | AZ74: 15 | BB74: 0.064377682 | BI74: D | BJ74: 30 | BK74: 2055 | BL74: - | BM74: F | BN74: 151 | BO74: 847 | BP74: -
A75: 45178 | F75: =E75 | J75: =IFERROR(E75/I75,"") | K75: =IFERROR(E75/#REF!,"") | L75: 116904 | M75: - | O75: 5.35 | Q75: =O75/E75 -> #VALUE! | W75: - | Y75: - | AA75: - | AC75: - | AE75: - | AG75: - | AH75: 4363 | AI75: - | AJ75: 707 | AK75: - | AL75: 75 | AM75: - | AN75: 1436 | AO75: - | AP75: 1912 | AQ75: - | AR75: 333 | AS75: - | AV75: 204 | AX75: 0.042087889 | AZ75: 17 | BB75: 0.083333333 | BI75: D | BJ75: 30 | BK75: 2481 | BL75: - | BM75: F | BN75: 133 | BO75: 1053 | BP75: -
A76: 45179 | B76: 预售 | F76: =E76 | J76: =IFERROR(E76/I76,"") | K76: =IFERROR(E76/#REF!,"") | L76: 97734 | M76: - | O76: 2.78 | Q76: =O76/E76 -> #VALUE! | W76: - | Y76: - | AA76: - | AC76: - | AE76: - | AG76: - | AH76: 4282 | AI76: - | AJ76: 580 | AK76: - | AL76: 69 | AM76: - | AN76: 1684 | AO76: - | AP76: 1839 | AQ76: - | AR76: 330 | AS76: - | AV76: 211 | AX76: 0.042267628 | AZ76: 10 | BB76: 0.047393365 | BI76: D | BJ76: 33 | BK76: 2321 | BL76: - | BM76: F | BN76: 146 | BO76: 1011 | BP76: -
A77: 45180 | B77: 预售 | F77: =E77 | J77: =IFERROR(E77/I77,"") | K77: =IFERROR(E77/#REF!,"") | L77: 172089 | M77: - | O77: 6.34 | Q77: =O77/E77 -> #VALUE! | W77: - | Y77: - | AA77: - | AC77: - | AE77: - | AG77: - | AH77: 2914 | AI77: - | AJ77: 625 | AK77: - | AL77: 67 | AM77: - | AN77: 1366 | AO77: - | AP77: 1605 | AQ77: - | AR77: 313 | AS77: - | AV77: 255 | AX77: 0.056056276 | AZ77: 21 | BB77: 0.082352941 | BI77: D | BJ77: 35 | BK77: 2106 | BL77: - | BM77: F | BN77: 161 | BO77: 870 | BP77: -
A78: 45181 | B78: 预售 | F78: =E78 | J78: =IFERROR(E78/I78,"") | K78: =IFERROR(E78/#REF!,"") | L78: 102321 | M78: - | O78: 6.2 | Q78: =O78/E78 -> #VALUE! | W78: - | Y78: - | AA78: - | AC78: - | AE78: - | AG78: - | AH78: 2911 | AI78: - | AJ78: 698 | AK78: - | AL78: 104 | AM78: - | AN78: 1398 | AO78: - | AP78: 1635 | AQ78: - | AR78: 337 | AS78: - | AV78: 233 | AX78: 0.050215517 | AZ78: 18 | BB78: 0.077253219 | BI78: D | BJ78: 34 | BK78: 2443 | BL78: - | BM78: F | BN78: 145 | BO78: 926 | BP78: - | BV78: 13QC05 | BW78: 16GD31 | BX78: 16QC05 | BY78: POP13QS04 | BZ78: 能率13EA2 | CA78: 16GD61R | CB78: 13GD32 | CC78: 厂直16QC05+SG | CD78: 海尔13KL3U1 | CE78: 厂直16QD31+SG
A79: 45182 | B79: 预售 | F79: =E79 | J79: =IFERROR(E79/I79,"") | K79: =IFERROR(E79/#REF!,"") | L79: 257156 | M79: - | O79: 7.15 | Q79: =O79/E79 -> #VALUE! | W79: - | Y79: - | AA79: - | AC79: - | AE79: - | AG79: - | AH79: 2986 | AI79: - | AJ79: 676 | AK79: - | AL79: 89 | AM79: - | AN79: 1576 | AO79: - | AP79: 1704 | AQ79: - | AR79: 360 | AS79: - | AV79: 231 | AX79: 0.047570016 | AZ79: 19 | BB79: 0.082251082 | BI79: D | BJ79: 22 | BK79: 3062 | BL79: - | BM79: E | BN79: 98 | BO79: 1316 | BP79: -
A80: 45183 | B80: 晚8点 | F80: =E80 | J80: =IFERROR(E80/I80,"") | K80: =IFERROR(E80/#REF!,"") | L80: 334356 | M80: - | Q80: =O80/E80 -> #VALUE! | W80: - | Y80: - | AA80: - | AC80: - | AE80: - | AG80: - | AH80: 3118 | AI80: - | AJ80: 583 | AK80: - | AL80: 115 | AM80: - | AN80: 1498 | AO80: - | AP80: 1695 | AQ80: - | AR80: 359 | AS80: - | AV80: 253 | AX80: 0.052240347 | AZ80: 29 | BB80: 0.11462451 | BI80: D | BJ80: 23 | BK80: 2889 | BL80: - | BM80: F | BN80: 115 | BO80: 1127 | BP80: -
A81: 45184 | F81: =E81 | J81: =IFERROR(E81/I81,"") | K81: =IFERROR(E81/#REF!,"") | L81: 108665 | M81: - | Q81: =O81/E81 -> #VALUE! | W81: - | Y81: - | AA81: - | AC81: - | AE81: - | AG81: - | AH81: 2853 | AI81: - | AJ81: 607 | AK81: - | AL81: 88 | AM81: - | AN81: 1527 | AO81: - | AP81: 1566 | AQ81: - | AR81: 286 | AS81: - | AV81: 288 | AX81: 0.062095731 | AZ81: 34 | BB81: 0.11805556 | BI81: D | BJ81: 27 | BK81: 2412 | BL81: - | BM81: F | BN81: 140 | BO81: 964 | BP81: -
A82: 45185 | B82: 预售 | F82: =E82 | J82: =IFERROR(E82/I82,"") | K82: =IFERROR(E82/#REF!,"") | L82: 26602 | M82: - | Q82: =O82/E82 -> #VALUE! | W82: - | Y82: - | AA82: - | AC82: - | AE82: - | AG82: - | AH82: 3285 | AI82: - | AJ82: 605 | AK82: - | AL82: 119 | AM82: - | AN82: 1523 | AO82: - | AP82: 1847 | AQ82: - | AR82: 424 | AS82: - | AV82: 331 | AX82: 0.065273122 | AZ82: 46 | BB82: 0.13897281 | BI82: D | BJ82: 21 | BK82: 3575 | BL82: - | BM82: E | BN82: 89 | BO82: 1503 | BP82: -
A83: 45186 | B83: 预售 | F83: =E83 | J83: =IFERROR(E83/I83,"") | K83: =IFERROR(E83/#REF!,"") | L83: 49458 | M83: - | Q83: =O83/E83 -> #VALUE! | W83: - | Y83: - | AA83: - | AC83: - | AE83: - | AG83: - | AH83: 3509 | AI83: - | AJ83: 734 | AK83: - | AL83: 105 | AM83: - | AN83: 1527 | AO83: - | AP83: 2028 | AQ83: - | AR83: 427 | AS83: - | AV83: 306 | AX83: 0.057057617 | AZ83: 49 | BB83: 0.16013072 | BI83: C | BJ83: 20 | BK83: 4041 | BL83: - | BM83: E | BN83: 92 | BO83: 1570 | BP83: -
A84: 45187 | B84: 预售 | F84: =E84 | J84: =IFERROR(E84/I84,"") | K84: =IFERROR(E84/#REF!,"") | L84: 17117 | M84: - | Q84: =O84/E84 -> #VALUE! | W84: - | Y84: - | AA84: - | AC84: - | AE84: - | AG84: - | AH84: 3381 | AI84: - | AJ84: 739 | AK84: - | AL84: 133 | AM84: - | AN84: 1369 | AO84: - | AP84: 1900 | AQ84: - | AR84: 442 | AS84: - | AV84: 319 | AX84: 0.062610402 | AZ84: 51 | BB84: 0.15987461 | BI84: C | BJ84: 21 | BK84: 3651 | BL84: - | BM84: E | BN84: 81 | BO84: 1646 | BP84: -
A85: 45188 | B85: 晚8点 | F85: =E85 | J85: =IFERROR(E85/I85,"") | K85: =IFERROR(E85/#REF!,"") | L85: 247956 | M85: - | Q85: =O85/E85 -> #VALUE! | W85: - | Y85: - | AA85: - | AC85: - | AE85: - | AG85: - | AH85: 3626 | AI85: - | AJ85: 716 | AK85: - | AL85: 161 | AM85: - | AN85: 1405 | AO85: - | AP85: 1838 | AQ85: - | AR85: 503 | AS85: - | AV85: 363 | AX85: 0.067799776 | AZ85: 51 | BB85: 0.14049587 | BI85: C | BJ85: 20 | BK85: 3498 | BL85: - | BM85: E | BN85: 80 | BO85: 1641 | BP85: -
A86: 45189 | B86: 日销 | F86: =E86 | J86: =IFERROR(E86/I86,"") | K86: =IFERROR(E86/#REF!,"") | L86: 155604 | M86: - | Q86: =O86/E86 -> #VALUE! | W86: - | Y86: - | AA86: - | AC86: - | AE86: - | AG86: - | AH86: 3453 | AI86: - | AJ86: 662 | AK86: - | AL86: 128 | AM86: - | AN86: 1290 | AO86: - | AP86: 1738 | AQ86: - | AR86: 337 | AS86: - | AV86: 385 | AX86: 0.076373735 | AZ86: 48 | BB86: 0.12467532 | BI86: C | BJ86: 24 | BK86: 2418 | BL86: - | BM86: F | BN86: 122 | BO86: 1024 | BP86: -
A87: 45190 | B87: 预售 | F87: =E87 | J87: =IFERROR(E87/I87,"") | K87: =IFERROR(E87/#REF!,"") | L87: 121800 | M87: - | Q87: =O87/E87 -> #VALUE! | W87: - | Y87: - | AA87: - | AC87: - | AE87: - | AG87: - | AH87: 3450 | AI87: - | AJ87: 542 | AK87: - | AL87: 94 | AM87: - | AN87: 1480 | AO87: - | AP87: 1859 | AQ87: - | AR87: 384 | AS87: - | AV87: 346 | AX87: 0.067485859 | AZ87: 36 | BB87: 0.10404624 | BI87: C | BJ87: 19 | BK87: 3195 | BL87: - | BM87: F | BN87: 139 | BO87: 958 | BP87: -
A88: 45191 | B88: 预售 | F88: =E88 | J88: =IFERROR(E88/I88,"") | K88: =IFERROR(E88/#REF!,"") | L88: 123389 | M88: - | Q88: =O88/E88 -> #VALUE! | W88: - | Y88: - | AA88: - | AC88: - | AE88: - | AG88: - | AH88: 2876 | AI88: - | AJ88: 616 | AK88: - | AL88: 113 | AM88: - | AN88: 1262 | AO88: - | AP88: 1471 | AQ88: - | AR88: 256 | AS88: - | AV88: 294 | AX88: 0.066500792 | AZ88: 24 | BB88: 0.081632653 | BI88: D | BJ88: 26 | BK88: 2792 | BL88: - | BM88: F | BN88: 157 | BO88: 797 | BP88: -
A89: 45192 | B89: 预售 | F89: =E89 | J89: =IFERROR(E89/I89,"") | K89: =IFERROR(E89/#REF!,"") | L89: 121627.97 | M89: - | Q89: =O89/E89 -> #VALUE! | W89: - | Y89: - | AA89: - | AC89: - | AE89: - | AG89: - | AH89: 3334 | AI89: - | AJ89: 826 | AK89: - | AL89: 112 | AM89: - | AN89: 1579 | AO89: - | AP89: 1881 | AQ89: - | AR89: 358 | AS89: - | AV89: 312 | AX89: 0.059046177 | AZ89: 42 | BB89: 0.13461538 | BI89: D | BJ89: 22 | BK89: 3267 | BL89: - | BM89: E | BN89: 100 | BO89: 1291 | BP89: -
A90: 45193 | B90: 晚8点 | F90: =E90 | J90: =IFERROR(E90/I90,"") | K90: =IFERROR(E90/#REF!,"") | L90: 410188 | M90: - | Q90: =O90/E90 -> #VALUE! | W90: - | Y90: - | AA90: - | AC90: - | AE90: - | AG90: - | AH90: 3968 | AI90: - | AJ90: 852 | AK90: - | AL90: 151 | AM90: - | AN90: 1482 | AO90: - | AP90: 2212 | AQ90: - | AR90: 428 | AS90: - | AV90: 344 | AX90: 0.059045657 | AZ90: 49 | BB90: 0.14244186 | BI90: C | BJ90: 17 | BK90: 4335 | BL90: - | BM90: E | BN90: 82 | BO90: 1750 | BP90: -
A91: 45194 | B91: 日销 | F91: =E91 | J91: =IFERROR(E91/I91,"") | K91: =IFERROR(E91/#REF!,"") | L91: 134949.05 | M91: - | Q91: =O91/E91 -> #VALUE! | W91: - | Y91: - | AA91: - | AC91: - | AE91: - | AG91: - | AH91: 3752 | AI91: - | AJ91: 687 | AK91: - | AL91: 126 | AM91: - | AN91: 1314 | AO91: - | AP91: 2148 | AQ91: - | AR91: 362 | AS91: - | AV91: 366 | AX91: 0.068283582 | AZ91: 54 | BB91: 0.14754098 | BI91: C | BJ91: 18 | BK91: 3934 | BL91: - | BM91: E | BN91: 86 | BO91: 1549 | BP91: -
A92: 45195 | B92: 预售 | F92: =E92 | J92: =IFERROR(E92/I92,"") | K92: =IFERROR(E92/#REF!,"") | L92: 48281 | M92: - | Q92: =O92/E92 -> #VALUE! | W92: - | Y92: - | AA92: - | AC92: - | AE92: - | AG92: - | AH92: 3285 | AI92: - | AJ92: 796 | AK92: - | AL92: 100 | AM92: - | AN92: 1411 | AO92: - | AP92: 1918 | AQ92: - | AR92: 298 | AS92: - | AV92: 298 | AX92: 0.058431373 | AZ92: 0 | BB92: 0 | BI92: D | BJ92: 25 | BK92: 2978 | BL92: - | BM92: F | BN92: 128 | BO92: 1054 | BP92: -
A93: 45196 | B93: 预售 | F93: =E93 | J93: =IFERROR(E93/I93,"") | K93: =IFERROR(E93/#REF!,"") | L93: 160175 | M93: - | Q93: =O93/E93 -> #VALUE! | W93: - | Y93: - | AA93: - | AC93: - | AE93: - | AG93: - | AH93: 3062 | AI93: - | AJ93: 912 | AK93: - | AL93: 132 | AM93: - | AN93: 1595 | AO93: - | AP93: 1695 | AQ93: - | AR93: 277 | AS93: - | AV93: 314 | AX93: #DIV/0! | AZ93: 27 | BB93: 0.085987261 | BI93: D | BJ93: 25 | BK93: 2718 | BL93: - | BM93: F | BN93: 134 | BO93: 1023 | BP93: -
A94: 45197 | B94: 晚8点 | F94: =E94 | J94: =IFERROR(E94/I94,"") | K94: =IFERROR(E94/#REF!,"") | L94: 190161 | M94: - | Q94: =O94/E94 -> #VALUE! | W94: - | Y94: - | AA94: - | AC94: - | AE94: - | AG94: - | AH94: 2876 | AI94: - | AJ94: 859 | AK94: - | AL94: 98 | AM94: - | AN94: 1447 | AO94: - | AP94: 1562 | AQ94: - | AR94: 321 | AS94: - | AV94: 279 | AX94: 0.058724479 | AZ94: 39 | BB94: 0.13978495 | BI94: D | BJ94: 25 | BK94: 2593 | BL94: - | BM94: F | BN94: 143 | BO94: 958 | BP94: -
A95: 45198 | B95: 日销 | F95: =E95 | J95: =IFERROR(E95/I95,"") | K95: =IFERROR(E95/#REF!,"") | L95: 130013 | M95: - | Q95: =O95/E95 -> #VALUE! | W95: - | Y95: - | AA95: - | AC95: - | AE95: - | AG95: - | AH95: 2765 | AI95: - | AJ95: 891 | AK95: - | AL95: 58 | AM95: - | AN95: 1467 | AO95: - | AP95: 1489 | AQ95: - | AR95: 268 | AS95: - | AV95: 249 | AX95: 0.053137004 | AZ95: 51 | BB95: 0.20481928 | BI95: D | BJ95: 28 | BK95: 2215 | BL95: - | BM95: F | BN95: 167 | BO95: 992 | BP95: -
A96: 45199 | B96: 日销 | F96: =E96 | J96: =IFERROR(E96/I96,"") | K96: =IFERROR(E96/#REF!,"") | L96: 140178 | M96: - | Q96: =O96/E96 -> #VALUE! | W96: - | Y96: - | AA96: - | AC96: - | AE96: - | AG96: - | AH96: 3146 | AI96: - | AJ96: 1114 | AK96: - | AL96: 78 | AM96: - | AN96: 1567 | AO96: - | AP96: 1685 | AQ96: - | AR96: 265 | AS96: - | AV96: 265 | AX96: 0.050389808 | AZ96: 35 | BB96: 0.13207547 | BI96: D | BJ96: 31 | BK96: 2738 | BL96: - | BM96: F | BN96: 148 | BO96: 1222 | BP96: -
A97: 45200 | B97: 日销 | F97: =E97 | K97: =IFERROR(E97/#REF!,"") | L97: 140728 | M97: - | Q97: =O97/E97 -> #VALUE! | W97: - | Y97: - | AA97: - | AC97: - | AE97: - | AG97: - | AH97: 3230 | AI97: - | AJ97: 755 | AK97: - | AL97: 81 | AM97: - | AN97: 1591 | AO97: - | AP97: 1786 | AQ97: - | AR97: 254 | AS97: - | AV97: 0 | AX97: 0 | AZ97: 0 | BB97: #DIV/0! | BI97: D | BJ97: 31 | BK97: 2603 | BL97: - | BM97: F | BN97: 149 | BO97: 1175 | BP97: -
A98: 45201 | B98: 日销 | F98: =E98 | K98: =IFERROR(E98/#REF!,"") | L98: 109705 | M98: - | Q98: =O98/E98 -> #VALUE! | W98: - | Y98: - | AA98: - | AC98: - | AE98: - | AG98: - | AH98: 3122 | AI98: - | AJ98: 798 | AK98: - | AL98: 62 | AM98: - | AN98: 1668 | AO98: - | AP98: 1771 | AQ98: - | AR98: 285 | AS98: - | AV98: 0 | AX98: 0 | AZ98: 0 | BB98: #DIV/0! | BI98: D | BJ98: 26 | BK98: 2826 | BL98: - | BM98: F | BN98: 128 | BO98: 1195 | BP98: -
A99: 45202 | B99: 日销 | F99: =E99 | K99: =IFERROR(E99/#REF!,"") | L99: 151264 | M99: - | Q99: =O99/E99 -> #VALUE! | W99: - | Y99: - | AA99: - | AC99: - | AE99: - | AG99: - | AH99: 3219 | AI99: - | AJ99: 772 | AK99: - | AL99: 66 | AM99: - | AN99: 1591 | AO99: - | AP99: 1821 | AQ99: - | AR99: 312 | AS99: - | AV99: 0 | AX99: 0 | AZ99: 0 | BB99: #DIV/0! | BI99: D | BJ99: 30 | BK99: 2730 | BL99: - | BM99: F | BN99: 134 | BO99: 1140 | BP99: -
A100: 45203 | B100: 日销 | F100: =E100 | K100: =IFERROR(E100/#REF!,"") | L100: 124269 | M100: - | Q100: =O100/E100 -> #VALUE! | W100: - | Y100: - | AA100: - | AC100: - | AE100: - | AG100: - | AH100: 3396 | AI100: - | AJ100: 648 | AK100: - | AL100: 64 | AM100: - | AN100: 1703 | AO100: - | AP100: 1954 | AQ100: - | AR100: 275 | AS100: - | AV100: 0 | AX100: 0 | AZ100: 0 | BB100: #DIV/0! | BI100: D | BJ100: 36 | BK100: 2642 | BL100: - | BM100: F | BN100: 141 | BO100: 1131 | BP100: -
...

Sheet 单品16GD31 
A1: 7月 sku:100039707007 | D1: 销售出库 | V1: 流量 | AT1: 转化 | BH1: 京仓现货率 | BI1: 关键词排名 | BQ1: 流失分析 | CF1: 负同比每日分析
A2: 日期 | B2: 价格政策 | D2: 销售额 | L2: 模块销售占比 | V2: PV | X2: UV | Z2: 人均浏览量 | AB2: 平均停留时间 | AD2: 关注人数 | AF2: 加购人数 | AH2: 站内免费 | AJ2: 站内付费 | AL2: 站外免费 | AN2: 站外付费 | AP2: 搜索 | AR2: 内容 | AT2: 店铺转化率 | AV2: 询单 数 | AX2: 询单 率 | AZ2: 询单 成交数 | BB2: 询单 转化 | BD2: 静默成交数 | BF2: 静默转化 | BI2: 燃气热水器 | BM2: 热水器 | BQ2: 流量流失 | BV2: 销售流失
B3: Y-23 | C3: Y-22 | D3: Y-23 数量 | E3: Y-23 金额 | F3: 实际销售 | G3: Y-22 金额 | H3: 同比 | I3: 目标 | J3: 达成率 | K3: 类目占比 | L3: 推广成交金额 | M3: 同比 | N3: 占比 | O3: 客服成交金额 | P3: 同比 | Q3: 占比 | R3: Y-23 | S3: Y-22 | T3: 同比 | U3: 占比 | V3: Y-23 | W3: Y-22 | X3: Y-23 | Y3: Y-22 | Z3: Y-23 | AA3: Y-22 | AB3: Y-23 | AC3: Y-22 | AD3: Y-23 | AE3: Y-22 | AF3: Y-23 | AG3: Y-22 | AH3: Y-23 | AI3: Y-22 | AJ3: Y-23 | AK3: Y-22 | AL3: Y-23 | AM3: Y-22 | AN3: Y-23 | AO3: Y-22 | AP3: Y-23 | AQ3: Y-22 | AR3: Y-23 | AS3: Y-22 | AT3: Y-23 | AU3: Y-22 | AV3: Y-23 | AW3: Y-22 | AX3: Y-23 | AY3: Y-22 | AZ3: Y-23 | BA3: Y-22 | BB3: Y-23 | BC3: Y-22 | BD3: Y-23 | BE3: Y-22 | BF3: Y-23 | BG3: Y-22 | BI3: 层级 | BJ3: 排名 | BK3: 搜索曝光 | BL3: Y-22搜索曝光 | BM3: 层级 | BN3: 排名 | BO3: 搜索曝光 | BP3: Y-22搜索曝光 | BQ3: TOP 1 | BR3: TOP 2 | BS3: TOP 3 | BT3: TOP 4 | BU3: TOP 5 | BV3: TOP 1 | BW3: TOP 2 | BX3: TOP 3 | BY3: TOP 4 | BZ3: TOP 5 | CA3: TOP 6 | CB3: TOP 7 | CC3: TOP 8 | CD3: TOP 9 | CE3: TOP 10
A4: 填写人员 | B4: 运营 | C4: 运营 | D4: 张超 | E4: 张超 | F4: 运营 | G4: 张超 | H4: 张超 | I4: 张超 | J4: 张超 | K4: 张超 | L4: 推广 | M4: 推广 | N4: 推广 | O4: 客服 | P4: 客服 | Q4: 客服 | R4: 直播 | S4: 直播 | T4: 直播 | U4: 直播 | V4: 运营 | W4: 运营 | X4: 运营 | Y4: 运营 | Z4: 运营 | AA4: 运营 | AB4: 运营 | AC4: 运营 | AD4: 运营 | AE4: 运营 | AF4: 运营 | AG4: 运营 | AH4: 运营 | AI4: 运营 | AJ4: 运营 | AK4: 运营 | AL4: 运营 | AM4: 运营 | AN4: 运营 | AO4: 运营 | AP4: 运营 | AQ4: 运营 | AR4: 运营 | AS4: 运营 | AT4: 客服 | AU4: 客服 | AV4: 客服 | AW4: 客服 | AX4: 客服 | AY4: 客服 | AZ4: 客服 | BA4: 客服 | BB4: 客服 | BC4: 客服 | BD4: 客服 | BE4: 客服 | BF4: 客服 | BG4: 客服 | BH4: 供应链 | BI4: 运营 | BJ4: 运营 | BK4: 运营 | BL4: 运营 | BM4: 运营 | BN4: 运营 | BO4: 运营 | BP4: 运营 | BQ4: 运营 | BR4: 运营 | BS4: 运营 | BT4: 运营 | BU4: 运营 | BV4: 运营 | BW4: 运营 | BX4: 运营 | BY4: 运营 | BZ4: 运营 | CA4: 运营 | CB4: 运营 | CC4: 运营 | CD4: 运营 | CE4: 运营 | CF4: 运营
A5: 45108 | B5: A | C5: 无 | F5: 5.5983 | H5: =IFERROR(E5/G5-1,"") | I5: 5.2784 | J5: =IFERROR(E5/I5,"") | K5: =IFERROR(E5/#REF!,"") | L5: 44368 | M5: - | R5: 6598 | S5: 0 | W5: - | Y5: - | AA5: - | AC5: - | AD5: 8 | AE5: - | AG5: - | AH5: 1344 | AI5: - | AJ5: 528 | AK5: - | AL5: 44 | AM5: - | AN5: 32 | AO5: - | AP5: 644 | AQ5: - | AR5: 85 | AS5: - | AT5: 0.0086 | AU5: - | BH5: 1 | BI5: E | BJ5: 100 | BK5: 735 | BL5: - | BM5: F | BN5: 451 | BO5: 281 | BP5: -
A6: 45109 | B6: A | C6: 无 | F6: 5.9285 | H6: =IFERROR(E6/G6-1,"") | I6: 5.6086 | J6: =IFERROR(E6/I6,"") | K6: =IFERROR(E6/#REF!,"") | L6: 28923 | M6: - | R6: 3299 | S6: 0 | W6: - | Y6: - | AA6: - | AC6: - | AD6: 13 | AE6: - | AG6: - | AH6: 1424 | AI6: - | AJ6: 749 | AK6: - | AL6: 39 | AM6: - | AN6: 42 | AO6: - | AP6: 679 | AQ6: - | AR6: 103 | AS6: - | AT6: 0.0086 | AU6: - | BH6: 1 | BI6: E | BJ6: 82 | BK6: 1020 | BL6: - | BM6: F | BN6: 525 | BO6: 229 | BP6: -
A7: 45110 | B7: 预约 | C7: 无 | F7: 0.9597 | H7: =IFERROR(E7/G7-1,"") | I7: 0 | J7: =IFERROR(E7/I7,"") | K7: =IFERROR(E7/#REF!,"") | L7: 22490 | M7: - | R7: 0 | S7: 0 | W7: - | Y7: - | AA7: - | AC7: - | AD7: 16 | AE7: - | AG7: - | AH7: 1525 | AI7: - | AJ7: 785 | AK7: - | AL7: 59 | AM7: - | AN7: 36 | AO7: - | AP7: 635 | AQ7: - | AR7: 135 | AS7: - | AT7: 0 | AU7: - | BH7: 1 | BI7: E | BJ7: 90 | BK7: 776 | BL7: - | BM7: F | BN7: 567 | BO7: 191 | BP7: - | BV7: 16QD31 | BW7: 16GD32 | BX7: 海尔锦绣 | BY7: POP16GD32 | BZ7: 16QD06W | CA7: 13GD31 | CB7: 16QC05 | CC7: POP16QS04 | CD7: 16QD06 | CE7: 能率16EA2
A8: 45111 | B8: A | C8: 无 | F8: 6.9279 | H8: =IFERROR(E8/G8-1,"") | I8: 6.9279 | J8: =IFERROR(E8/I8,"") | K8: =IFERROR(E8/#REF!,"") | L8: 65680 | M8: - | R8: 9897 | S8: 0 | W8: - | Y8: - | AA8: - | AC8: - | AD8: 21 | AE8: - | AG8: - | AH8: 1595 | AI8: - | AJ8: 815 | AK8: - | AL8: 45 | AM8: - | AN8: 36 | AO8: - | AP8: 614 | AQ8: - | AR8: 151 | AS8: - | AT8: 0.0096 | AU8: - | BH8: 1 | BI8: E | BJ8: 90 | BK8: 767 | BL8: - | BM8: F | BN8: 519 | BO8: 207 | BP8: -
A9: 45112 | B9: A | C9: 无 | F9: 11.1969 | H9: =IFERROR(E9/G9-1,"") | I9: 10.5571 | J9: =IFERROR(E9/I9,"") | K9: =IFERROR(E9/#REF!,"") | L9: 59987 | M9: - | R9: 3299 | S9: 0 | W9: - | Y9: - | AA9: - | AC9: - | AD9: 7 | AE9: - | AG9: - | AH9: 1735 | AI9: - | AJ9: 498 | AK9: - | AL9: 53 | AM9: - | AN9: 29 | AO9: - | AP9: 769 | AQ9: - | AR9: 151 | AS9: - | AT9: 0.0147 | AU9: - | BH9: 1 | BI9: E | BJ9: 64 | BK9: 1031 | BL9: - | BM9: F | BN9: 335 | BO9: 340 | BP9: -
A10: 45113 | B10: 预约 | C10: 无 | F10: 1.2197 | H10: =IFERROR(E10/G10-1,"") | I10: 0.8998 | J10: =IFERROR(E10/I10,"") | K10: =IFERROR(E10/#REF!,"") | L10: 6158 | M10: - | R10: 0 | S10: 0 | W10: - | Y10: - | AA10: - | AC10: - | AD10: 7 | AE10: - | AG10: - | AH10: 1310 | AI10: - | AJ10: 649 | AK10: - | AL10: 72 | AM10: - | AN10: 39 | AO10: - | AP10: 468 | AQ10: - | AR10: 103 | AS10: - | AT10: 0.0011 | AU10: - | BH10: 1 | BI10: E | BJ10: 94 | BK10: 632 | BL10: - | BM10: F | BN10: 328 | BO10: 362 | BP10: -
A11: 45114 | B11: A | C11: 无 | F11: 9.2272 | H11: =IFERROR(E11/G11-1,"") | I11: 8.9073 | J11: =IFERROR(E11/I11,"") | K11: =IFERROR(E11/#REF!,"") | L11: 15695 | M11: - | R11: 3299 | S11: 0 | W11: - | Y11: - | AA11: - | AC11: - | AD11: 14 | AE11: - | AG11: - | AH11: 1575 | AI11: - | AJ11: 711 | AK11: - | AL11: 64 | AM11: - | AN11: 32 | AO11: - | AP11: 708 | AQ11: - | AR11: 105 | AS11: - | AT11: 0.0129 | AU11: - | BH11: 1 | BI11: E | BJ11: 77 | BK11: 882 | BL11: - | BM11: F | BN11: 418 | BO11: 240 | BP11: -
A12: 45115 | B12: A | C12: 无 | F12: 6.5783 | H12: =IFERROR(E12/G12-1,"") | I12: 5.9385 | J12: =IFERROR(E12/I12,"") | K12: =IFERROR(E12/#REF!,"") | L12: 16295 | M12: - | R12: 0 | S12: 0 | W12: - | Y12: - | AA12: - | AC12: - | AD12: 11 | AE12: - | AG12: - | AH12: 1701 | AI12: - | AJ12: 295 | AK12: - | AL12: 57 | AM12: - | AN12: 47 | AO12: - | AP12: 764 | AQ12: - | AR12: 109 | AS12: - | AT12: 0.0093 | AU12: - | BH12: 1 | BI12: E | BJ12: 69 | BK12: 1040 | BL12: - | BM12: F | BN12: 331 | BO12: 352 | BP12: -
A13: 45116 | B13: 预约 | C13: 无 | F13: 0.3199 | H13: =IFERROR(E13/G13-1,"") | I13: 0 | J13: =IFERROR(E13/I13,"") | K13: =IFERROR(E13/#REF!,"") | L13: 5467 | M13: - | R13: 0 | S13: 0 | W13: - | Y13: - | AA13: - | AC13: - | AD13: 24 | AE13: - | AG13: - | AH13: 1694 | AI13: - | AJ13: 701 | AK13: - | AL13: 76 | AM13: - | AN13: 49 | AO13: - | AP13: 721 | AQ13: - | AR13: 134 | AS13: - | AT13: 0 | AU13: - | BH13: 1 | BI13: E | BJ13: 97 | BK13: 755 | BL13: - | BM13: F | BN13: 594 | BO13: 185 | BP13: -
A14: 45117 | B14: 预约 | C14: 无 | F14: 0 | H14: =IFERROR(E14/G14-1,"") | I14: 0 | J14: =IFERROR(E14/I14,"") | K14: =IFERROR(E14/#REF!,"") | L14: 13519 | M14: - | R14: 0 | S14: 0 | W14: - | Y14: - | AA14: - | AC14: - | AD14: 23 | AE14: - | AG14: - | AH14: 1536 | AI14: - | AJ14: 787 | AK14: - | AL14: 49 | AM14: - | AN14: 44 | AO14: - | AP14: 530 | AQ14: - | AR14: 127 | AS14: - | AT14: 0 | AU14: - | BH14: 1 | BI14: F | BJ14: 117 | BK14: 538 | BL14: - | BM14: F | BN14: 747 | BO14: 128 | BP14: -
A15: 45118 | B15: A | C15: 无 | F15: 10.5568 | H15: =IFERROR(E15/G15-1,"") | I15: 10.5568 | J15: =IFERROR(E15/I15,"") | K15: =IFERROR(E15/#REF!,"") | L15: 78675 | M15: - | R15: 16495 | S15: 0 | W15: - | Y15: - | AA15: - | AC15: - | AD15: 22 | AE15: - | AG15: - | AH15: 1897 | AI15: - | AJ15: 759 | AK15: - | AL15: 56 | AM15: - | AN15: 58 | AO15: - | AP15: 690 | AQ15: - | AR15: 158 | AS15: - | AT15: 0.013 | AU15: - | BH15: 1 | BI15: E | BJ15: 83 | BK15: 764 | BL15: - | BM15: F | BN15: 443 | BO15: 246 | BP15: - | BV15: 16QD31 | BW15: 16QC05 | BX15: 16GD32 | BY15: 13GD31 | BZ15: 16QD06W | CA15: 海尔锦绣 | CB15: 16GD32 | CC15: 13QC05 | CD15: 海尔云程 | CE15: 13GD32
A16: 45119 | B16: A | C16: 无 | F16: 7.9179 | H16: =IFERROR(E16/G16-1,"") | I16: 14.3 | J16: =IFERROR(E16/I16,"") | K16: =IFERROR(E16/#REF!,"") | L16: 36089 | M16: - | R16: 0 | S16: 0 | W16: - | Y16: - | AA16: - | AC16: - | AD16: 20 | AE16: - | AG16: - | AH16: 1753 | AI16: - | AJ16: 791 | AK16: - | AL16: 94 | AM16: - | AN16: 30 | AO16: - | AP16: 804 | AQ16: - | AR16: 113 | AS16: - | AT16: 0.0102 | AU16: - | BH16: 1 | BI16: E | BJ16: 64 | BK16: 1054 | BL16: - | BM16: F | BN16: 402 | BO16: 282 | BP16: -
A17: 45120 | B17: A | C17: 无 | F17: 8.5777 | H17: =IFERROR(E17/G17-1,"") | I17: 11.7 | J17: =IFERROR(E17/I17,"") | K17: =IFERROR(E17/#REF!,"") | L17: 29447 | M17: - | R17: 6601 | S17: 0 | W17: - | Y17: - | AA17: - | AC17: - | AD17: 15 | AE17: - | AG17: - | AH17: 1879 | AI17: - | AJ17: 640 | AK17: - | AL17: 75 | AM17: - | AN17: 48 | AO17: - | AP17: 932 | AQ17: - | AR17: 123 | AS17: - | AT17: 0.0111 | AU17: - | BH17: 1 | BI17: E | BJ17: 55 | BK17: 1178 | BL17: - | BM17: F | BN17: 381 | BO17: 296 | BP17: -
A18: 45121 | B18: 预售 | C18: 无 | F18: 0.3199 | H18: =IFERROR(E18/G18-1,"") | I18: 0 | J18: =IFERROR(E18/I18,"") | K18: =IFERROR(E18/#REF!,"") | L18: 40655 | M18: - | R18: ？ | S18: 0 | W18: - | Y18: - | AA18: - | AC18: - | AD18: 22 | AE18: - | AG18: - | AH18: 2194 | AI18: - | AJ18: 783 | AK18: - | AL18: 73 | AM18: - | AN18: 45 | AO18: - | AP18: 1184 | AQ18: - | AR18: 168 | AS18: - | AT18: 0 | AU18: - | BH18: 1 | BI18: D | BJ18: 49 | BK18: 1328 | BL18: - | BM18: F | BN18: 273 | BO18: 431 | BP18: -
A19: 45122 | B19: 预售 | C19: 无 | F19: 0.3199 | H19: =IFERROR(E19/G19-1,"") | I19: 0 | J19: =IFERROR(E19/I19,"") | K19: =IFERROR(E19/#REF!,"") | L19: 31900 | M19: - | R19: 0 | S19: 0 | W19: - | Y19: - | AA19: - | AC19: - | AD19: 21 | AE19: - | AG19: - | AH19: 2138 | AI19: - | AJ19: 774 | AK19: - | AL19: 65 | AM19: - | AN19: 39 | AO19: - | AP19: 1215 | AQ19: - | AR19: 152 | AS19: - | AT19: 0 | AU19: - | BH19: 1 | BI19: D | BJ19: 49 | BK19: 1428 | BL19: - | BM19: F | BN19: 307 | BO19: 406 | BP19: -
A20: 45123 | B20: S | C20: 无 | F20: 30.5408 | H20: =IFERROR(E20/G20-1,"") | I20: 36.4 | J20: =IFERROR(E20/I20,"") | K20: =IFERROR(E20/#REF!,"") | L20: 102488 | M20: - | R20: 19794 | S20: 0 | W20: - | Y20: - | AA20: - | AC20: - | AD20: 26 | AE20: - | AG20: - | AH20: 2614 | AI20: - | AJ20: 795 | AK20: - | AL20: 75 | AM20: - | AN20: 46 | AO20: - | AP20: 1420 | AQ20: - | AR20: 187 | AS20: - | AT20: 0.029 | AU20: - | BH20: 1 | BI20: D | BJ20: 49 | BK20: 1577 | BL20: - | BM20: F | BN20: 327 | BO20: 433 | BP20: -
A21: 45124 | B21: S | C21: 无 | F21: 13.8558 | H21: =IFERROR(E21/G21-1,"") | I21: 23.4 | J21: =IFERROR(E21/I21,"") | K21: =IFERROR(E21/#REF!,"") | L21: 63421 | M21: - | R21: 13196 | S21: 0 | W21: - | Y21: - | AA21: - | AC21: - | AD21: 14 | AE21: - | AG21: - | AH21: 2371 | AI21: - | AJ21: 839 | AK21: - | AL21: 86 | AM21: - | AN21: 70 | AO21: - | AP21: 1267 | AQ21: - | AR21: 149 | AS21: - | AT21: 0.0138 | AU21: - | BH21: 1 | BI21: D | BJ21: 40 | BK21: 1256 | BL21: - | BM21: F | BN21: 320 | BO21: 418 | BP21: -
A22: 45125 | B22: A | C22: 无 | F22: 11.5825 | H22: =IFERROR(E22/G22-1,"") | I22: 11.7 | J22: =IFERROR(E22/I22,"") | K22: =IFERROR(E22/#REF!,"") | L22: 217755 | M22: - | R22: 0 | S22: 0 | W22: - | Y22: - | AA22: - | AC22: - | AD22: 18 | AE22: - | AG22: - | AH22: 2106 | AI22: - | AJ22: 205 | AK22: - | AL22: 77 | AM22: - | AN22: 59 | AO22: - | AP22: 1127 | AQ22: - | AR22: 144 | AS22: - | AT22: 0.0144 | AU22: - | BH22: 1 | BI22: D | BJ22: 50 | BK22: 1279 | BL22: - | BM22: F | BN22: 371 | BO22: 334 | BP22: - | BV22: 16QD06* | BW22: 16QD31 | BX22: 16GD32 | BY22: 16QC05 | BZ22: 海尔锦绣 | CA22: 13GD31 | CB22: 16QD06W | CC22: 16QD03* | CD22: 16QD06* | CE22: 13GD32
A23: 45126 | B23: A | C23: 无 | F23: 10.1789 | H23: =IFERROR(E23/G23-1,"") | I23: 0 | J23: =IFERROR(E23/I23,"") | K23: =IFERROR(E23/#REF!,"") | L23: 107294 | M23: - | R23: 6438 | S23: 0 | W23: - | Y23: - | AA23: - | AC23: - | AD23: 23 | AE23: - | AG23: - | AH23: 2272 | AI23: - | AJ23: 996 | AK23: - | AL23: 83 | AM23: - | AN23: 60 | AO23: - | AP23: 1203 | AQ23: - | AR23: 144 | AS23: - | AT23: 0.0104 | AU23: - | BH23: 1 | BI23: E | BJ23: 54 | BK23: 1289 | BL23: - | BM23: F | BN23: 331 | BO23: 357 | BP23: -
A24: 45127 | B24: A | C24: 无 | F24: 14.6096 | H24: =IFERROR(E24/G24-1,"") | I24: 22.1 | J24: =IFERROR(E24/I24,"") | K24: =IFERROR(E24/#REF!,"") | L24: 1342791 | M24: - | R24: 9897 | S24: 0 | W24: - | Y24: - | AA24: - | AC24: - | AD24: 22 | AE24: - | AG24: - | AH24: 2427 | AI24: - | AJ24: 1040 | AK24: - | AL24: 78 | AM24: - | AN24: 70 | AO24: - | AP24: 1322 | AQ24: - | AR24: 153 | AS24: - | AT24: 0.0136 | AU24: - | BH24: 1 | BI24: D | BJ24: 41 | BK24: 1558 | BL24: - | BM24: F | BN24: 252 | BO24: 478 | BP24: -
A25: 45128 | B25: A | C25: 无 | F25: 9.5191 | H25: =IFERROR(E25/G25-1,"") | I25: 16.9 | J25: =IFERROR(E25/I25,"") | K25: =IFERROR(E25/#REF!,"") | L25: 65063 | M25: - | R25: 3299 | S25: 0 | W25: - | Y25: - | AA25: - | AC25: - | AD25: 24 | AE25: - | AG25: - | AH25: 2069 | AI25: - | AJ25: 746 | AK25: - | AL25: 82 | AM25: - | AN25: 963 | AO25: - | AP25: 1081 | AQ25: - | AR25: 119 | AS25: - | AT25: 0.008 | AU25: - | BH25: 1 | BI25: E | BJ25: 54 | BK25: 1214 | BL25: - | BM25: F | BN25: 272 | BO25: 437 | BP25: -
A26: 45129 | B26: 预售 | C26: 无 | F26: 0.9797 | H26: =IFERROR(E26/G26-1,"") | I26: 11.7 | J26: =IFERROR(E26/I26,"") | K26: =IFERROR(E26/#REF!,"") | L26: 26992 | M26: - | R26: 0 | S26: 0 | W26: - | Y26: - | AA26: - | AC26: - | AD26: 28 | AE26: - | AG26: - | AH26: 2570 | AI26: - | AJ26: 926 | AK26: - | AL26: 71 | AM26: - | AN26: 2884 | AO26: - | AP26: 1350 | AQ26: - | AR26: 198 | AS26: - | AT26: 0.0003 | AU26: - | BH26: 1 | BI26: D | BJ26: 48 | BK26: 1389 | BL26: - | BM26: F | BN26: 295 | BO26: 443 | BP26: -
A27: 45130 | B27: 预售 | C27: 无 | F27: 0 | H27: =IFERROR(E27/G27-1,"") | I27: 0 | J27: =IFERROR(E27/I27,"") | K27: =IFERROR(E27/#REF!,"") | L27: 16696 | M27: - | R27: 0 | S27: 0 | W27: - | Y27: - | AA27: - | AC27: - | AD27: 21 | AE27: - | AG27: - | AH27: 2437 | AI27: - | AJ27: 126 | AK27: - | AL27: 89 | AM27: - | AN27: 1169 | AO27: - | AP27: 1310 | AQ27: - | AR27: 202 | AS27: - | AT27: 0 | AU27: - | BH27: 1 | BI27: D | BJ27: 44 | BK27: 1587 | BL27: - | BM27: F | BN27: 264 | BO27: 484 | BP27: -
A28: 45131 | B28: 预售 | C28: 无 | F28: 29.2171 | H28: =IFERROR(E28/G28-1,"") | I28: 23.4 | J28: =IFERROR(E28/I28,"") | K28: =IFERROR(E28/#REF!,"") | L28: 73807 | M28: - | R28: 26392 | S28: 0 | W28: - | Y28: - | AA28: - | AC28: - | AD28: 24 | AE28: - | AG28: - | AH28: 2870 | AI28: - | AJ28: 1009 | AK28: - | AL28: 120 | AM28: - | AN28: 3200 | AO28: - | AP28: 1582 | AQ28: - | AR28: 211 | AS28: - | AT28: 0.0134 | AU28: - | BH28: 1 | BI28: D | BJ28: 35 | BK28: 1778 | BL28: - | BM28: F | BN28: 243 | BO28: 496 | BP28: -
A29: 45132 | B29: S | C29: 无 | F29: 31.5665 | H29: =IFERROR(E29/G29-1,"") | I29: 18.2 | J29: =IFERROR(E29/I29,"") | K29: =IFERROR(E29/#REF!,"") | L29: 64783 | M29: - | R29: 91973 | S29: 0 | W29: - | Y29: - | AA29: - | AC29: - | AD29: 20 | AE29: - | AG29: - | AH29: 2692 | AI29: - | AJ29: 680 | AK29: - | AL29: 134 | AM29: - | AN29: 3296 | AO29: - | AP29: 1301 | AQ29: - | AR29: 152 | AS29: - | AT29: 0.0111 | AU29: - | BH29: 1 | BI29: D | BJ29: 39 | BK29: 1479 | BL29: - | BM29: F | BN29: 245 | BO29: 476 | BP29: - | BV29: 16GD32 | BW29: 16QD31 | BX29: 13GD31 | BY29: 16QD06W | BZ29: 16QC05 | CA29: 海尔锦绣 | CB29: 五星16GD32 | CC29: 五星16QC06 | CD29: 海尔云程 | CE29: 13GD32
A30: 45133 | B30: A | C30: 无 | F30: 14.9135 | H30: =IFERROR(E30/G30-1,"") | I30: 10.4 | J30: =IFERROR(E30/I30,"") | K30: =IFERROR(E30/#REF!,"") | L30: 103749 | M30: - | R30: 9897 | S30: 0 | W30: - | Y30: - | AA30: - | AC30: - | AD30: 18 | AE30: - | AG30: - | AH30: 2494 | AI30: - | AJ30: 767 | AK30: - | AL30: 74 | AM30: - | AN30: 2854 | AO30: - | AP30: 1195 | AQ30: - | AR30: 160 | AS30: - | AT30: 0.0075 | AU30: - | BH30: 1 | BI30: D | BJ30: 38 | BK30: 1451 | BL30: - | BM30: F | BN30: 240 | BO30: 483 | BP30: -
A31: 45134 | B31: A | C31: 无 | F31: 17.8236 | H31: =IFERROR(E31/G31-1,"") | I31: 13 | J31: =IFERROR(E31/I31,"") | K31: =IFERROR(E31/#REF!,"") | L31: 40088 | M31: - | R31: 3299 | S31: 0 | W31: - | Y31: - | AA31: - | AC31: - | AD31: 12 | AE31: - | AG31: - | AH31: 2499 | AI31: - | AJ31: 225 | AK31: - | AL31: 77 | AM31: - | AN31: 5601 | AO31: - | AP31: 1196 | AQ31: - | AR31: 181 | AS31: - | AT31: 0.0064 | AU31: - | BH31: 1 | BI31: D | BJ31: 44 | BK31: 1273 | BL31: - | BM31: F | BN31: 269 | BO31: 446 | BP31: -
A32: 45135 | B32: A | C32: 无 | F32: 11.4668 | H32: =IFERROR(E32/G32-1,"") | I32: 13 | J32: =IFERROR(E32/I32,"") | K32: =IFERROR(E32/#REF!,"") | L32: 38898 | M32: - | R32: 6598 | S32: 0 | W32: - | Y32: - | AA32: - | AC32: - | AD32: 24 | AE32: - | AG32: - | AH32: 2412 | AI32: - | AJ32: 636 | AK32: - | AL32: 57 | AM32: - | AN32: 3357 | AO32: - | AP32: 1163 | AQ32: - | AR32: 149 | AS32: - | AT32: 0.0058 | AU32: - | BH32: 1 | BI32: E | BJ32: 51 | BK32: 1119 | BL32: - | BM32: F | BN32: 306 | BO32: 368 | BP32: -
A33: 45136 | B33: 预售 | C33: 无 | F33: 0 | H33: =IFERROR(E33/G33-1,"") | I33: 0 | J33: =IFERROR(E33/I33,"") | K33: =IFERROR(E33/#REF!,"") | L33: 47101 | M33: - | R33: 0 | S33: 0 | W33: - | Y33: - | AA33: - | AC33: - | AD33: 24 | AE33: - | AG33: - | AH33: 3016 | AI33: - | AJ33: 599 | AK33: - | AL33: 98 | AM33: - | AN33: 4056 | AO33: - | AP33: 1580 | AQ33: - | AR33: 270 | AS33: - | AT33: 0 | AU33: - | BH33: 1 | BI33: D | BJ33: 43 | BK33: 1521 | BL33: - | BM33: F | BN33: 258 | BO33: 479 | BP33: -
A34: 45137 | B34: 预售 | C34: 无 | F34: 0 | H34: =IFERROR(E34/G34-1,"") | I34: 0 | J34: =IFERROR(E34/I34,"") | K34: =IFERROR(E34/#REF!,"") | L34: 36289 | M34: - | O34: 23.8327 | P34: 0 | Q34: 0.2173 | R34: 0 | S34: 0 | W34: - | Y34: - | AA34: - | AC34: - | AD34: 27 | AE34: - | AG34: - | AH34: 3504 | AI34: - | AJ34: 754 | AK34: - | AL34: 86 | AM34: - | AN34: 1873 | AO34: - | AP34: 2108 | AQ34: - | AR34: 328 | AS34: - | AT34: 0 | AU34: - | AV34: 249 | AW34: - | AX34: 50 | AY34: - | AZ34: 0.20080321 | BA34: - | BC34: - | BH34: 1 | BI34: D | BJ34: 41 | BK34: 2013 | BL34: - | BM34: F | BN34: 216 | BO34: 613 | BP34: -
A35: 45138 | B35: 限时 | C35: 无 | F35: 42.2 | H35: =IFERROR(E35/G35-1,"") | I35: 39 | J35: =IFERROR(E35/I35,"") | K35: =IFERROR(E35/#REF!,"") | L35: 119465 | M35: - | R35: 29531 | S35: 0 | W35: - | Y35: - | AA35: - | AC35: - | AD35: 36 | AE35: - | AG35: - | AH35: 3981 | AI35: - | AJ35: 896 | AK35: - | AL35: 136 | AM35: - | AN35: 5178 | AO35: - | AP35: 2214 | AQ35: - | AR35: 326 | AS35: - | AT35: 0.0136 | AU35: - | BH35: 1 | BI35: D | BJ35: 34 | BK35: 2235 | BL35: - | BM35: F | BN35: 199 | BO35: 628 | BP35: -
A36: 45139 | B36: S级 | C36: 无 | F36: =E36-3.2 -> #VALUE! | I36: 19 | J36: =IFERROR(E36/I36,"") | K36: =IFERROR(E36/#REF!,"") | L36: 151183 | M36: - | O36: 13.186 | W36: - | Y36: - | AA36: - | AC36: - | AD36: 29 | AE36: - | AG36: - | AH36: 4932 | AI36: - | AJ36: 1019 | AK36: - | AL36: 131 | AM36: - | AN36: 4083 | AO36: - | AP36: 1983 | AQ36: - | AR36: 255 | AS36: - | AT36: 0.0083 | AV36: 225 | AW36: - | AX36: 0.0277 | AY36: - | BH36: 1 | BI36: D | BJ36: 32 | BK36: 2052 | BL36: - | BM36: F | BN36: 199 | BO36: 635 | BP36: - | BV36: 16GD32 | BW36: 13GD31 | BX36: 16QC05 | BY36: 16QD31 | BZ36: 海尔锦绣 | CA36: 16QD06W | CB36: 海尔云程 | CC36: 能率16E4 | CD36: 13GD32 | CE36: 13QD06W
A37: 45140 | B37: A级 | C37: 无 | F37: =E37-1.9 -> #VALUE! | I37: 12 | J37: =IFERROR(E37/I37,"") | K37: =IFERROR(E37/#REF!,"") | L37: 71181 | M37: - | W37: - | Y37: - | AA37: - | AC37: - | AD37: 33 | AE37: - | AG37: - | AH37: 5083 | AI37: - | AJ37: 801 | AK37: - | AL37: 106 | AM37: - | AN37: 3595 | AO37: - | AP37: 2166 | AQ37: - | AR37: 315 | AS37: - | BH37: 1 | BI37: C | BJ37: 19 | BK37: 3083 | BL37: - | BM37: F | BN37: 128 | BO37: 935 | BP37: -
A38: 45141 | B38: A级 | C38: 无 | F38: =E38-1.9 -> #VALUE! | I38: 10 | J38: =IFERROR(E38/I38,"") | K38: =IFERROR(E38/#REF!,"") | L38: 54265 | M38: - | W38: - | Y38: - | AA38: - | AC38: - | AD38: 32 | AE38: - | AG38: - | AH38: 4786 | AI38: - | AJ38: 193 | AK38: - | AL38: 129 | AM38: - | AN38: 2773 | AO38: - | AP38: 2047 | AQ38: - | AR38: 248 | AS38: - | BH38: 1 | BI38: D | BJ38: 35 | BK38: 2041 | BL38: - | BM38: F | BN38: 177 | BO38: 710 | BP38: -
A39: 45142 | B39: A级 | C39: 无 | F39: =E39-1.9 -> #VALUE! | I39: 13 | J39: =IFERROR(E39/I39,"") | K39: =IFERROR(E39/#REF!,"") | L39: 51135 | M39: - | W39: - | Y39: - | AA39: - | AC39: - | AD39: 37 | AE39: - | AG39: - | AH39: 5264 | AI39: - | AJ39: 475 | AK39: - | AL39: 113 | AM39: - | AN39: 6855 | AO39: - | AP39: 2351 | AQ39: - | AR39: 276 | AS39: - | BH39: 0.95 | BI39: D | BJ39: 31 | BK39: 2193 | BL39: - | BM39: F | BN39: 199 | BO39: 642 | BP39: -
A40: 45143 | B40: 预售 | C40: 无 | F40: =E40 | I40: 0 | J40: =IFERROR(E40/I40,"") | K40: =IFERROR(E40/#REF!,"") | L40: 19694 | M40: - | W40: - | Y40: - | AA40: - | AC40: - | AD40: 26 | AE40: - | AG40: - | AH40: 5661 | AI40: - | AJ40: 913 | AK40: - | AL40: 148 | AM40: - | AN40: 1388 | AO40: - | AP40: 2427 | AQ40: - | AR40: 374 | AS40: - | BH40: 0.95 | BI40: D | BJ40: 26 | BK40: 2440 | BL40: - | BM40: F | BN40: 171 | BO40: 760 | BP40: -
A41: 45144 | B41: 预售 | C41: 无 | F41: =E41 | I41: 0 | J41: =IFERROR(E41/I41,"") | K41: =IFERROR(E41/#REF!,"") | L41: 11997 | M41: - | W41: - | Y41: - | AA41: - | AC41: - | AD41: 32 | AE41: - | AG41: - | AH41: 5827 | AI41: - | AJ41: 660 | AK41: - | AL41: 160 | AM41: - | AN41: 1590 | AO41: - | AP41: 2625 | AQ41: - | AR41: 420 | AS41: - | BH41: 0.85 | BI41: D | BJ41: 25 | BK41: 2878 | BL41: - | BM41: F | BN41: 112 | BO41: 1053 | BP41: -
A42: 45145 | B42: S级 | C42: 无 | F42: =E42-0.96 -> #VALUE! | I42: 40 | J42: =IFERROR(E42/I42,"") | K42: =IFERROR(E42/#REF!,"") | L42: 111147 | M42: - | W42: - | Y42: - | AA42: - | AC42: - | AD42: 18 | AE42: - | AG42: - | AH42: 6564 | AI42: - | AJ42: 1033 | AK42: - | AL42: 168 | AM42: - | AN42: 1398 | AO42: - | AP42: 2631 | AQ42: - | AR42: 458 | AS42: - | BH42: 0.9 | BI42: D | BJ42: 25 | BK42: 2750 | BL42: - | BM42: F | BN42: 111 | BO42: 1050 | BP42: -
A43: 45146 | B43: S级 | C43: 无 | F43: =E43-3.2 -> #VALUE! | I43: 20 | J43: =IFERROR(E43/I43,"") | K43: =IFERROR(E43/#REF!,"") | L43: 52574 | M43: - | W43: - | Y43: - | AA43: - | AC43: - | AE43: - | AG43: - | AH43: 5623 | AI43: - | AJ43: 716 | AK43: - | AL43: 100 | AM43: - | AN43: 1181 | AO43: - | AP43: 2293 | AQ43: - | AR43: 397 | AS43: - | BH43: 0.95 | BI43: D | BJ43: 26 | BK43: 2398 | BL43: - | BM43: F | BN43: 135 | BO43: 893 | BP43: - | BV43: 16GD32 | BW43: 16QC05 | BX43: 海尔锦绣 | BY43: 16QD31 | BZ43: 13GD31 | CA43: 16QD06W | CB43: 海尔云程 | CC43: 能率13E4 | CD43: 13QC05 | CE43: 13QD06W
A44: 45147 | B44: A级 | C44: 无 | F44: =E44-1.6 -> #VALUE! | I44: 10 | J44: =IFERROR(E44/I44,"") | K44: =IFERROR(E44/#REF!,"") | L44: 40989 | M44: - | W44: - | Y44: - | AA44: - | AC44: - | AE44: - | AG44: - | AH44: 5367 | AI44: - | AJ44: 506 | AK44: - | AL44: 124 | AM44: - | AN44: 1595 | AO44: - | AP44: 2334 | AQ44: - | AR44: 385 | AS44: - | BH44: 0.9 | BI44: D | BJ44: 22 | BK44: 3116 | BL44: - | BM44: F | BN44: 117 | BO44: 1000 | BP44: -
A45: 45148 | B45: A级 | C45: 无 | F45: =E45-1.28 -> #VALUE! | I45: 12 | J45: =IFERROR(E45/I45,"") | K45: =IFERROR(E45/#REF!,"") | L45: 45186 | M45: - | O45: 5.2 | Q45: =O45/E45 -> #VALUE! | W45: - | Y45: - | AA45: - | AC45: - | AE45: - | AG45: - | AH45: 5090 | AI45: - | AJ45: 698 | AK45: - | AL45: 97 | AM45: - | AN45: 1707 | AO45: - | AP45: 2303 | AQ45: - | AR45: 344 | AS45: - | AV45: 284 | AW45: 0 | AX45: 0.049460118 | AZ45: 18 | BA45: 0 | BB45: 0.063380282 | BH45: 0.9 | BI45: D | BJ45: 29 | BK45: 2181 | BL45: - | BM45: F | BN45: 159 | BO45: 759 | BP45: -
A46: 45149 | B46: 预售 | C46: 无 | F46: =E46 | I46: 0 | J46: =IFERROR(E46/I46,"") | K46: =IFERROR(E46/#REF!,"") | L46: 18395 | M46: - | O46: 6.89 | Q46: =O46/E46 -> #VALUE! | W46: - | Y46: - | AA46: - | AC46: - | AE46: - | AG46: - | AH46: 5454 | AI46: - | AJ46: 975 | AK46: - | AL46: 116 | AM46: - | AN46: 1807 | AO46: - | AP46: 2266 | AQ46: - | AR46: 369 | AS46: - | AV46: 255 | AX46: 0.040826129 | AZ46: 24 | BB46: 0.094117647 | BH46: 0.9 | BI46: D | BJ46: 26 | BK46: 2194 | BL46: - | BM46: F | BN46: 178 | BO46: 751 | BP46: -
A47: 45150 | B47: 预售 | C47: 无 | F47: =E47 | I47: 0 | J47: =IFERROR(E47/I47,"") | K47: =IFERROR(E47/#REF!,"") | L47: 8597 | M47: - | O47: 5.1 | Q47: =O47/E47 -> #VALUE! | W47: - | Y47: - | AA47: - | AC47: - | AE47: - | AG47: - | AH47: 5903 | AI47: - | AJ47: 1247 | AK47: - | AL47: 125 | AM47: - | AN47: 2306 | AO47: - | AP47: 2610 | AQ47: - | AR47: 418 | AS47: - | AV47: 242 | AX47: 0.032956557 | AZ47: 24 | BB47: 0.099173554 | BH47: 0.95 | BI47: C | BJ47: 19 | BK47: 2993 | BL47: - | BM47: F | BN47: 124 | BO47: 1104 | BP47: -
A48: 45151 | B48: 预售 | C48: 无 | F48: =E48 | I48: 0 | J48: =IFERROR(E48/I48,"") | K48: =IFERROR(E48/#REF!,"") | L48: 2599 | M48: - | O48: 7.7 | Q48: =O48/E48 -> #VALUE! | W48: - | Y48: - | AA48: - | AC48: - | AE48: - | AG48: - | AH48: 6761 | AI48: - | AJ48: 1410 | AK48: - | AL48: 177 | AM48: - | AN48: 2370 | AO48: - | AP48: 3010 | AQ48: - | AR48: 436 | AS48: - | AV48: 316 | AX48: 0.040005064 | AZ48: 36 | BB48: 0.11392405 | BH48: 0.95 | BI48: D | BJ48: 22 | BK48: 3355 | BL48: - | BM48: F | BN48: 116 | BO48: 1246 | BP48: -
A49: 45152 | B49: 预售+S级 | C49: 无 | F49: =E49 | I49: 59 | J49: =IFERROR(E49/I49,"") | K49: =IFERROR(E49/#REF!,"") | L49: 254008 | M49: - | O49: 15.63 | Q49: =O49/E49 -> #VALUE! | W49: - | Y49: - | AA49: - | AC49: - | AE49: - | AG49: - | AH49: 7987 | AI49: - | AJ49: 1620 | AK49: - | AL49: 216 | AM49: - | AN49: 2221 | AO49: - | AP49: 3079 | AQ49: - | AR49: 611 | AS49: - | AV49: 422 | AX49: 0.049734826 | AZ49: 62 | BB49: 0.14691943 | BH49: 1 | BI49: C | BJ49: 17 | BK49: 3740 | BL49: - | BM49: E | BN49: 97 | BO49: 1396 | BP49: -
A50: 45153 | B50: S级 | C50: 无 | F50: =E50-3.5 -> #VALUE! | I50: 26 | J50: =IFERROR(E50/I50,"") | K50: =IFERROR(E50/#REF!,"") | L50: 118223 | M50: - | O50: 8.86 | Q50: =O50/E50 -> #VALUE! | W50: - | Y50: - | AA50: - | AC50: - | AE50: - | AG50: - | AH50: 6472 | AI50: - | AJ50: 1270 | AK50: - | AL50: 155 | AM50: - | AN50: 1963 | AO50: - | AP50: 2741 | AQ50: - | AR50: 444 | AS50: - | AV50: 297 | AX50: 0.041078838 | AZ50: 29 | BB50: 0.097643098 | BH50: 1 | BI50: D | BJ50: 22 | BK50: 2655 | BL50: - | BM50: F | BN50: 135 | BO50: 1035 | BP50: - | BV50: 16GD32 | BW50: 13GD31 | BX50: 海尔锦绣 | BY50: 16QC05 | BZ50: 16QD31 | CA50: 16QD06W | CB50: 海尔云程 | CC50: 13QC05 | CD50: 16GD61R | CE50: 厂直16QD31+SG
A51: 45154 | B51: A级 | C51: 无 | F51: =E51-1.9 -> #VALUE! | I51: 0 | J51: =IFERROR(E51/I51,"") | K51: =IFERROR(E51/#REF!,"") | L51: 28493 | M51: - | O51: 3.31 | Q51: =O51/E51 -> #VALUE! | W51: - | Y51: - | AA51: - | AC51: - | AE51: - | AG51: - | AH51: 6145 | AI51: - | AJ51: 654 | AK51: - | AL51: 160 | AM51: - | AN51: 2136 | AO51: - | AP51: 2825 | AQ51: - | AR51: 411 | AS51: - | AV51: 314 | AX51: 0.045933294 | AZ51: 13 | BB51: 0.041401274 | BH51: 1 | BI51: C | BJ51: 18 | BK51: 2888 | BL51: - | BM51: F | BN51: 116 | BO51: 1142 | BP51: -
A52: 45155 | B52: 预售+S级 | C52: 无 | F52: =E52-0.5 -> #VALUE! | I52: 24 | J52: =IFERROR(E52/I52,"") | K52: =IFERROR(E52/#REF!,"") | L52: 20875 | M52: - | O52: 8.4 | Q52: =O52/E52 -> #VALUE! | W52: - | Y52: - | AA52: - | AC52: - | AE52: - | AG52: - | AH52: 6388 | AI52: - | AJ52: 1228 | AK52: - | AL52: 176 | AM52: - | AN52: 1736 | AO52: - | AP52: 2808 | AQ52: - | AR52: 427 | AS52: - | AV52: 297 | AX52: 0.042844778 | AZ52: 28 | BB52: 0.094276094 | BH52: 1 | BI52: C | BJ52: 20 | BK52: 2919 | BL52: - | BM52: F | BN52: 118 | BO52: 1115 | BP52: -
A53: 45156 | B53: S级 | C53: 无 | F53: =E53-0.96 -> #VALUE! | I53: 23 | J53: =IFERROR(E53/I53,"") | K53: =IFERROR(E53/#REF!,"") | L53: 110548 | M53: - | O53: 9.3 | Q53: =O53/E53 -> #VALUE! | W53: - | Y53: - | AA53: - | AC53: - | AE53: - | AG53: - | AH53: 6868 | AI53: - | AJ53: 1011 | AK53: - | AL53: 167 | AM53: - | AN53: 1560 | AO53: - | AP53: 2687 | AQ53: - | AR53: 1103 | AS53: - | AV53: 328 | AX53: 0.045733408 | AZ53: 32 | BB53: 0.097560976 | BH53: 1 | BI53: C | BJ53: 16 | BK53: 3056 | BL53: - | BM53: F | BN53: 119 | BO53: 1058 | BP53: -
A54: 45157 | B54: A级 | C54: 无 | F54: =E54 | I54: 10 | J54: =IFERROR(E54/I54,"") | K54: =IFERROR(E54/#REF!,"") | L54: 25992 | M54: - | O54: 6.3 | Q54: =O54/E54 -> #VALUE! | W54: - | Y54: - | AA54: - | AC54: - | AE54: - | AG54: - | AH54: 6686 | AI54: - | AJ54: 648 | AK54: - | AL54: 107 | AM54: - | AN54: 1954 | AO54: - | AP54: 2999 | AQ54: - | AR54: 1020 | AS54: - | AV54: 309 | AX54: 0.042236195 | AZ54: 18 | BB54: 0.058252427 | BH54: 0.96 | BI54: C | BJ54: 20 | BK54: 3120 | BL54: - | BM54: F | BN54: 113 | BO54: 1223 | BP54: -
A55: 45158 | B55: A级 | C55: 无 | F55: =E55 | I55: 12 | J55: =IFERROR(E55/I55,"") | K55: =IFERROR(E55/#REF!,"") | L55: 53586 | M55: - | O55: 3.5 | Q55: =O55/E55 -> #VALUE! | W55: - | Y55: - | AA55: - | AC55: - | AE55: - | AG55: - | AH55: 6992 | AI55: - | AJ55: 698 | AK55: - | AL55: 138 | AM55: - | AN55: 2062 | AO55: - | AP55: 3158 | AQ55: - | AR55: 1032 | AS55: - | AV55: 247 | AX55: 0.032435982 | AZ55: 12 | BB55: 0.048582996 | BH55: 0.96 | BI55: D | BJ55: 24 | BK55: 3029 | BL55: - | BM55: F | BN55: 113 | BO55: 1220 | BP55: -
A56: 45159 | B56: A级 | C56: 无 | F56: =E56-1 -> #VALUE! | I56: 13 | J56: =IFERROR(E56/I56,"") | K56: =IFERROR(E56/#REF!,"") | L56: 69977 | M56: - | O56: 4.33 | Q56: =O56/E56 -> #VALUE! | W56: - | Y56: - | AA56: - | AC56: - | AE56: - | AG56: - | AH56: 7120 | AI56: - | AJ56: 752 | AK56: - | AL56: 160 | AM56: - | AN56: 2001 | AO56: - | AP56: 3200 | AQ56: - | AR56: 1027 | AS56: - | AV56: 301 | AX56: 0.038964401 | AZ56: 14 | BB56: 0.046511628 | BH56: 0.96 | BI56: C | BJ56: 17 | BK56: 3462 | BL56: - | BM56: F | BN56: 103 | BO56: 1325 | BP56: -
A57: 45160 | B57: A级 | C57: 无 | F57: =E57-1.6 -> #VALUE! | I57: 0 | J57: =IFERROR(E57/I57,"") | K57: =IFERROR(E57/#REF!,"") | L57: 33891 | M57: - | O57: 5.6 | Q57: =O57/E57 -> #VALUE! | W57: - | Y57: - | AA57: - | AC57: - | AE57: - | AG57: - | AH57: 6278 | AI57: - | AJ57: 822 | AK57: - | AL57: 99 | AM57: - | AN57: 1290 | AO57: - | AP57: 2751 | AQ57: - | AR57: 996 | AS57: - | AV57: 278 | AX57: 0.042644577 | AZ57: 17 | BB57: 0.061151079 | BH57: 0.92 | BI57: C | BJ57: 20 | BK57: 2858 | BL57: - | BM57: F | BN57: 138 | BO57: 914 | BP57: - | BV57: 16GD32 | BW57: 13GD31 | BX57: 16QD31 | BY57: 海尔锦绣 | BZ57: 16QC05 | CA57: 海尔云程 | CB57: 16QD06W | CC57: 13GD32 | CD57: 能率16E4 | CE57: 13QC05
A58: 45161 | B58: A级 | C58: 无 | F58: =E58-2 -> #VALUE! | I58: 0 | J58: =IFERROR(E58/I58,"") | K58: =IFERROR(E58/#REF!,"") | L58: 38384 | M58: - | O58: 6.25 | Q58: =O58/E58 -> #VALUE! | W58: - | Y58: - | AA58: - | AC58: - | AE58: - | AG58: - | AH58: 36117 | AI58: - | AJ58: 1188 | AK58: - | AL58: 135 | AM58: - | AN58: 1520 | AO58: - | AP58: 3191 | AQ58: - | AR58: 596 | AS58: - | AV58: 288 | AX58: 0.0075201713 | AZ58: 20 | BB58: 0.069444444 | BI58: C | BJ58: 18 | BK58: 3536 | BL58: - | BM58: F | BN58: 110 | BO58: 1266 | BP58: -
A59: 45162 | B59: A级 | C59: 无 | F59: =E59-0.6 -> #VALUE! | I59: 25 | J59: =IFERROR(E59/I59,"") | K59: =IFERROR(E59/#REF!,"") | L59: 30721 | M59: - | O59: 8.18 | Q59: =O59/E59 -> #VALUE! | W59: - | Y59: - | AA59: - | AC59: - | AE59: - | AG59: - | AH59: 36170 | AI59: - | AJ59: 1244 | AK59: - | AL59: 128 | AM59: - | AN59: 1108 | AO59: - | AP59: 2927 | AQ59: - | AR59: 606 | AS59: - | AV59: 278 | AX59: 0.0073267796 | AZ59: 21 | BB59: 0.075539568 | BI59: C | BJ59: 14 | BK59: 3660 | BL59: - | BM59: F | BN59: 109 | BO59: 1206 | BP59: -
A60: 45163 | B60: A级 | C60: 无 | F60: =E60 | I60: 21 | J60: =IFERROR(E60/I60,"") | K60: =IFERROR(E60/#REF!,"") | L60: 60961 | M60: - | O60: 5.49 | Q60: =O60/E60 -> #VALUE! | W60: - | Y60: - | AA60: - | AC60: - | AE60: - | AG60: - | AH60: 7159 | AI60: - | AJ60: 513 | AK60: - | AL60: 91 | AM60: - | AN60: 900 | AO60: - | AP60: 2603 | AQ60: - | AR60: 446 | AS60: - | AV60: 258 | AX60: 0.03727785 | AZ60: 20 | BB60: 0.07751938 | BI60: C | BJ60: 20 | BK60: 3312 | BL60: - | BM60: F | BN60: 117 | BO60: 1127 | BP60: -
A61: 45164 | B61: A级 | C61: 无 | F61: =E61 | I61: 10 | J61: =IFERROR(E61/I61,"") | K61: =IFERROR(E61/#REF!,"") | L61: 35237 | M61: - | O61: 6.76 | Q61: =O61/E61 -> #VALUE! | W61: - | Y61: - | AA61: - | AC61: - | AE61: - | AG61: - | AH61: 7021 | AI61: - | AJ61: 222 | AK61: - | AL61: 84 | AM61: - | AN61: 1466 | AO61: - | AP61: 2931 | AQ61: - | AR61: 492 | AS61: - | AV61: 249 | AX61: 0.03555619 | AZ61: 23 | BB61: 0.092369478 | BI61: C | BJ61: 20 | BK61: 3480 | BL61: - | BM61: F | BN61: 128 | BO61: 1173 | BP61: -
A62: 45165 | B62: A级 | C62: 无 | F62: =E62-0.6 -> #VALUE! | I62: 12 | J62: =IFERROR(E62/I62,"") | K62: =IFERROR(E62/#REF!,"") | L62: 38988 | M62: - | O62: 4.73 | Q62: =O62/E62 -> #VALUE! | W62: - | Y62: - | AA62: - | AC62: - | AE62: - | AG62: - | AH62: 7247 | AI62: - | AJ62: 504 | AK62: - | AL62: 115 | AM62: - | AN62: 1594 | AO62: - | AP62: 3204 | AQ62: - | AR62: 509 | AS62: - | AV62: 261 | AX62: 0.035539216 | AZ62: 17 | BB62: 0.0651341 | BI62: D | BJ62: 19 | BK62: 3674 | BL62: - | BM62: F | BN62: 131 | BO62: 1218 | BP62: -
A63: 45166 | B63: A级 | C63: 无 | F63: =E63 | I63: 13 | J63: =IFERROR(E63/I63,"") | K63: =IFERROR(E63/#REF!,"") | L63: 61202 | M63: - | O63: 7.63 | Q63: =O63/E63 -> #VALUE! | W63: - | Y63: - | AA63: - | AC63: - | AE63: - | AG63: - | AH63: 36700 | AI63: - | AJ63: 515 | AK63: - | AL63: 170 | AM63: - | AN63: 18338 | AO63: - | AP63: 3284 | AQ63: - | AR63: 880 | AS63: - | AV63: 322 | AX63: 0.0061624435 | AZ63: 24 | BB63: 0.074534161 | BI63: D | BJ63: 21 | BK63: 3570 | BL63: - | BM63: F | BN63: 120 | BO63: 1317 | BP63: -
A64: 45167 | B64: 预售 | C64: 无 | F64: =E64 | I64: 0 | J64: =IFERROR(E64/I64,"") | K64: =IFERROR(E64/#REF!,"") | L64: 9579 | M64: - | O64: 6.52 | Q64: =O64/E64 -> #VALUE! | W64: - | Y64: - | AA64: - | AC64: - | AE64: - | AG64: - | AH64: 13718 | AI64: - | AJ64: 803 | AK64: - | AL64: 164 | AM64: - | AN64: 9601 | AO64: - | AP64: 3089 | AQ64: - | AR64: 901 | AS64: - | AV64: 308 | AX64: 0.013309135 | AZ64: 22 | BB64: 0.071428571 | BI64: D | BJ64: 22 | BK64: 3280 | BL64: - | BM64: F | BN64: 128 | BO64: 1250 | BP64: - | BV64: 16GD32 | BW64: 16QC05 | BX64: 13GD31 | BY64: 海尔锦绣 | BZ64: 海尔云程 | CA64: 16QD31 | CB64: 13QC05 | CC64: 16QD06W | CD64: 能率16E4 | CE64: 能率16EA2
A65: 45168 | B65: 预售 | C65: 无 | F65: =E65 | I65: 0 | J65: =IFERROR(E65/I65,"") | K65: =IFERROR(E65/#REF!,"") | L65: 14995 | M65: - | O65: 12.46 | Q65: =O65/E65 -> #VALUE! | W65: - | Y65: - | AA65: - | AC65: - | AE65: - | AG65: - | AH65: 11960 | AI65: - | AJ65: 1021 | AK65: - | AL65: 148 | AM65: - | AN65: 1924 | AO65: - | AP65: 2784 | AQ65: - | AR65: 699 | AS65: - | AV65: 306 | AX65: 0.021288437 | AZ65: 39 | BB65: 0.12745098 | BI65: C | BJ65: 18 | BK65: 3410 | BL65: - | BM65: F | BN65: 118 | BO65: 1367 | BP65: -
A66: 45169 | B66: 31号晚8开门红 | C66: 无 | F66: =E66 | I66: 45 | J66: =IFERROR(E66/I66,"") | K66: =IFERROR(E66/#REF!,"") | L66: 126540 | M66: - | O66: 14.46 | Q66: =O66/E66 -> #VALUE! | W66: - | Y66: - | AA66: - | AC66: - | AE66: - | AG66: - | AH66: 9357 | AI66: - | AJ66: 1174 | AK66: - | AL66: 130 | AM66: - | AN66: 1431 | AO66: - | AP66: 2963 | AQ66: - | AR66: 610 | AS66: - | AV66: 350 | AX66: 0.030728709 | AZ66: 45 | BB66: 0.12857143 | BI66: C | BJ66: 16 | BK66: 3535 | BL66: - | BM66: F | BN66: 107 | BO66: 1485 | BP66: -
A67: 45170 | C67: 无 | F67: =E67 | J67: =IFERROR(E67/I67,"") | K67: =IFERROR(E67/#REF!,"") | L67: 44267 | M67: - | O67: 6.79 | Q67: =O67/E67 -> #VALUE! | W67: - | Y67: - | AA67: - | AC67: - | AE67: - | AG67: - | AH67: 4626 | AI67: - | AJ67: 570 | AK67: - | AL67: 103 | AM67: - | AN67: 1545 | AO67: - | AP67: 2564 | AQ67: - | AR67: 464 | AS67: - | AV67: 265 | AX67: 0.041264404 | AZ67: 22 | BB67: 0.083018868 | BI67: C | BJ67: 19 | BK67: 2952 | BL67: - | BM67: F | BN67: 140 | BO67: 1071 | BP67: -
A68: 45171 | B68: 日销 | C68: 无 | F68: =E68 | J68: =IFERROR(E68/I68,"") | K68: =IFERROR(E68/#REF!,"") | L68: 53383 | M68: - | O68: 4.52 | Q68: =O68/E68 -> #VALUE! | W68: - | Y68: - | AA68: - | AC68: - | AE68: - | AG68: - | AH68: 4916 | AI68: - | AJ68: 631 | AK68: - | AL68: 121 | AM68: - | AN68: 1439 | AO68: - | AP68: 3219 | AQ68: - | AR68: 487 | AS68: - | AV68: 321 | AX68: 0.04851141 | AZ68: 14 | BB68: 0.043613707 | BI68: C | BJ68: 17 | BK68: 3369 | BL68: - | BM68: F | BN68: 127 | BO68: 1258 | BP68: -
A69: 45172 | B69: 预售 | C69: 无 | F69: =E69 | J69: =IFERROR(E69/I69,"") | K69: =IFERROR(E69/#REF!,"") | L69: 7298 | M69: - | O69: 1.47 | Q69: =O69/E69 -> #VALUE! | W69: - | Y69: - | AA69: - | AC69: - | AE69: - | AG69: - | AH69: 4518 | AI69: - | AJ69: 813 | AK69: - | AL69: 112 | AM69: - | AN69: 1497 | AO69: - | AP69: 2589 | AQ69: - | AR69: 610 | AS69: - | AV69: 222 | AX69: 0.034703767 | AZ69: 7 | BB69: 0.031531532 | BI69: D | BJ69: 35 | BK69: 1769 | BL69: - | BM69: F | BN69: 230 | BO69: 717 | BP69: -
A70: 45173 | B70: 晚8点 | C70: 无 | F70: =E70 | J70: =IFERROR(E70/I70,"") | K70: =IFERROR(E70/#REF!,"") | L70: 185373 | M70: - | O70: 12.16 | Q70: =O70/E70 -> #VALUE! | W70: - | Y70: - | AA70: - | AC70: - | AE70: - | AG70: - | AH70: 4622 | AI70: - | AJ70: 1000 | AK70: - | AL70: 166 | AM70: - | AN70: 1624 | AO70: - | AP70: 2489 | AQ70: - | AR70: 607 | AS70: - | AV70: 309 | AX70: 0.046202153 | AZ70: 40 | BB70: 0.12944984 | BI70: D | BJ70: 28 | BK70: 1981 | BL70: - | BM70: F | BN70: 205 | BO70: 735 | BP70: -
A71: 45174 | B71: 预售 | C71: 无 | F71: =E71 | J71: =IFERROR(E71/I71,"") | L71: 21393 | M71: - | O71: 9.64 | Q71: =O71/E71 -> #VALUE! | W71: - | Y71: - | AA71: - | AC71: - | AE71: - | AG71: - | AH71: 5236 | AI71: - | AJ71: 1014 | AK71: - | AL71: 134 | AM71: - | AN71: 1133 | AO71: - | AP71: 3241 | AQ71: - | AR71: 597 | AS71: - | AV71: 329 | AX71: 0.047882404 | AZ71: 35 | BB71: 0.10638298 | BI71: C | BJ71: 17 | BK71: 3436 | BL71: - | BM71: E | BN71: 92 | BO71: 1263 | BP71: - | BV71: 16GD32 | BW71: 13GD31 | BX71: 海尔锦绣 | BY71: 16QC05 | BZ71: 16QD06W | CA71: 海尔云程 | CB71: 16QC06 | CC71: 16QD31 | CD71: 小店16C08 | CE71: 13QC05
A72: 45175 | B72: 预售 | C72: 无 | F72: =E72 | J72: =IFERROR(E72/I72,"") | L72: 11598 | M72: - | O72: 7.81 | Q72: =O72/E72 -> #VALUE! | W72: - | Y72: - | AA72: - | AC72: - | AE72: - | AG72: - | AH72: 4976 | AI72: - | AJ72: 1263 | AK72: - | AL72: 210 | AM72: - | AN72: 1125 | AO72: - | AP72: 2913 | AQ72: - | AR72: 560 | AS72: - | AV72: 342 | AX72: 0.050257164 | AZ72: 26 | BB72: 0.076023392 | BI72: C | BJ72: 19 | BK72: 3033 | BL72: - | BM72: F | BN72: 110 | BO72: 1136 | BP72: -
A73: 45176 | B73: 7号晚8 | C73: 无 | F73: =E73 | J73: =IFERROR(E73/I73,"") | L73: 296971 | M73: - | O73: 12.93 | Q73: =O73/E73 -> #VALUE! | W73: - | Y73: - | AA73: - | AC73: - | AE73: - | AG73: - | AH73: 5195 | AI73: - | AJ73: 1109 | AK73: - | AL73: 182 | AM73: - | AN73: 949 | AO73: - | AP73: 3156 | AQ73: - | AR73: 661 | AS73: - | AV73: 410 | AX73: 0.060939358 | AZ73: 39 | BB73: 0.095121951 | BI73: C | BJ73: 15 | BK73: 3797 | BL73: - | BM73: E | BN73: 91 | BO73: 1326 | BP73: -
A74: 45177 | C74: 无 | F74: =E74 | J74: =IFERROR(E74/I74,"") | L74: 53366 | M74: - | O74: 7.78 | Q74: =O74/E74 -> #VALUE! | W74: - | Y74: - | AA74: - | AC74: - | AE74: - | AG74: - | AH74: 6338 | AI74: - | AJ74: 912 | AK74: - | AL74: 133 | AM74: - | AN74: 970 | AO74: - | AP74: 3011 | AQ74: - | AR74: 478 | AS74: - | AV74: 321 | AX74: 0.052152721 | AZ74: 30 | BB74: 0.093457944 | BI74: C | BJ74: 20 | BK74: 3147 | BL74: - | BM74: F | BN74: 107 | BO74: 1129 | BP74: -
A75: 45178 | C75: 无 | F75: =E75 | J75: =IFERROR(E75/I75,"") | L75: 88956 | M75: - | O75: 7.37 | Q75: =O75/E75 -> #VALUE! | W75: - | Y75: - | AA75: - | AC75: - | AE75: - | AG75: - | AH75: 7846 | AI75: - | AJ75: 872 | AK75: - | AL75: 109 | AM75: - | AN75: 1167 | AO75: - | AP75: 3847 | AQ75: - | AR75: 617 | AS75: - | AV75: 380 | AX75: 0.051976474 | AZ75: 27 | BB75: 0.071052632 | BI75: C | BJ75: 19 | BK75: 3655 | BL75: - | BM75: F | BN75: 101 | BO75: 1390 | BP75: -
A76: 45179 | B76: 预售 | C76: 无 | F76: =E76 | J76: =IFERROR(E76/I76,"") | L76: 31490 | M76: - | O76: 2.51 | Q76: =O76/E76 -> #VALUE! | W76: - | Y76: - | AA76: - | AC76: - | AE76: - | AG76: - | AH76: 7479 | AI76: - | AJ76: 769 | AK76: - | AL76: 146 | AM76: - | AN76: 833 | AO76: - | AP76: 3650 | AQ76: - | AR76: 569 | AS76: - | AV76: 358 | AX76: 0.053257959 | AZ76: 7 | BB76: 0.019553073 | BI76: D | BJ76: 22 | BK76: 3620 | BL76: - | BM76: F | BN76: 103 | BO76: 1478 | BP76: -
A77: 45180 | B77: 预售 | C77: 无 | F77: =E77 | J77: =IFERROR(E77/I77,"") | L77: 88371 | M77: - | O77: 7.36 | Q77: =O77/E77 -> #VALUE! | W77: - | Y77: - | AA77: - | AC77: - | AE77: - | AG77: - | AH77: 5446 | AI77: - | AJ77: 513 | AK77: - | AL77: 145 | AM77: - | AN77: 1300 | AO77: - | AP77: 3573 | AQ77: - | AR77: 597 | AS77: - | AV77: 353 | AX77: 0.050551339 | AZ77: 24 | BB77: 0.067988669 | BI77: C | BJ77: 18 | BK77: 3863 | BL77: - | BM77: E | BN77: 98 | BO77: 1337 | BP77: -
A78: 45181 | B78: 预售 | C78: 无 | F78: =E78 | J78: =IFERROR(E78/I78,"") | L78: 36406 | M78: - | O78: 4.92 | Q78: =O78/E78 -> #VALUE! | W78: - | Y78: - | AA78: - | AC78: - | AE78: - | AG78: - | AH78: 5202 | AI78: - | AJ78: 643 | AK78: - | AL78: 150 | AM78: - | AN78: 1328 | AO78: - | AP78: 3295 | AQ78: - | AR78: 620 | AS78: - | AV78: 291 | AX78: 0.042693662 | AZ78: 14 | BB78: 0.048109966 | BI78: C | BJ78: 17 | BK78: 3562 | BL78: - | BM78: F | BN78: 109 | BO78: 1207 | BP78: - | BV78: 16QC05 | BW78: 16GD32 | BX78: 海尔锦绣 | BY78: 13GD31 | BZ78: 海尔云程 | CA78: 13QC05 | CB78: 能率16E4 | CC78: 16GD61R | CD78: 美的16MATE | CE78: 厂直16QC05+SG
A79: 45182 | B79: 预售 | C79: 无 | F79: =E79 | J79: =IFERROR(E79/I79,"") | L79: 91754 | M79: - | O79: 8.04 | Q79: =O79/E79 -> #VALUE! | W79: - | Y79: - | AA79: - | AC79: - | AE79: - | AG79: - | AH79: 5367 | AI79: - | AJ79: 747 | AK79: - | AL79: 235 | AM79: - | AN79: 878 | AO79: - | AP79: 3445 | AQ79: - | AR79: 595 | AS79: - | AV79: 359 | AX79: 0.0535661 | AZ79: 24 | BB79: 0.066852368 | BI79: C | BJ79: 14 | BK79: 4397 | BL79: - | BM79: E | BN79: 80 | BO79: 1562 | BP79: -
A80: 45183 | B80: 晚8点 | C80: 无 | F80: =E80 | J80: =IFERROR(E80/I80,"") | L80: 95769 | M80: - | Q80: =O80/E80 -> #VALUE! | W80: - | Y80: - | AA80: - | AC80: - | AE80: - | AG80: - | AH80: 5918 | AI80: - | AJ80: 756 | AK80: - | AL80: 185 | AM80: - | AN80: 1180 | AO80: - | AP80: 3869 | AQ80: - | AR80: 635 | AS80: - | AV80: 386 | AZ80: 47 | BB80: 0.12176166 | BI80: B | BJ80: 10 | BK80: 5479 | BL80: - | BM80: E | BN80: 69 | BO80: 1788 | BP80: -
A81: 45184 | C81: 无 | F81: =E81 | J81: =IFERROR(E81/I81,"") | L81: 37669 | M81: - | Q81: =O81/E81 -> #VALUE! | W81: - | Y81: - | AA81: - | AC81: - | AE81: - | AG81: - | AH81: 5243 | AI81: - | AJ81: 528 | AK81: - | AL81: 150 | AM81: - | AN81: 1374 | AO81: - | AP81: 3459 | AQ81: - | AR81: 461 | AS81: - | AV81: 416 | AZ81: 26 | BB81: 0.0625 | BI81: C | BJ81: 14 | BK81: 4466 | BL81: - | BM81: E | BN81: 88 | BO81: 1403 | BP81: -
A82: 45185 | B82: 预售 | C82: 无 | F82: =E82 | J82: =IFERROR(E82/I82,"") | L82: 12307 | M82: - | Q82: =O82/E82 -> #VALUE! | W82: - | Y82: - | AA82: - | AC82: - | AE82: - | AG82: - | AH82: 5961 | AI82: - | AJ82: 505 | AK82: - | AL82: 159 | AM82: - | AN82: 1473 | AO82: - | AP82: 3926 | AQ82: - | AR82: 632 | AS82: - | AV82: 489 | AZ82: 46 | BB82: 0.09406953 | BI82: B | BJ82: 8 | BK82: 6169 | BL82: - | BM82: E | BN82: 62 | BO82: 2090 | BP82: -
A83: 45186 | B83: 预售 | C83: 无 | F83: =E83 | J83: =IFERROR(E83/I83,"") | L83: 11609 | M83: - | Q83: =O83/E83 -> #VALUE! | W83: - | Y83: - | AA83: - | AC83: - | AE83: - | AG83: - | AH83: 6731 | AI83: - | AJ83: 741 | AK83: - | AL83: 179 | AM83: - | AN83: 1205 | AO83: - | AP83: 4445 | AQ83: - | AR83: 707 | AS83: - | AV83: 535 | AZ83: 43 | BB83: 0.080373832 | BI83: B | BJ83: 9 | BK83: 6889 | BL83: - | BM83: E | BN83: 66 | BO83: 2191 | BP83: -
A84: 45187 | B84: 预售 | C84: 无 | F84: =E84 | J84: =IFERROR(E84/I84,"") | L84: 15947 | M84: - | Q84: =O84/E84 -> #VALUE! | W84: - | Y84: - | AA84: - | AC84: - | AE84: - | AG84: - | AH84: 6241 | AI84: - | AJ84: 919 | AK84: - | AL84: 269 | AM84: - | AN84: 1323 | AO84: - | AP84: 3988 | AQ84: - | AR84: 736 | AS84: - | AV84: 477 | AZ84: 44 | BB84: 0.092243187 | BI84: B | BJ84: 9 | BK84: 6058 | BL84: - | BM84: E | BN84: 67 | BO84: 2047 | BP84: -
A85: 45188 | B85: 晚8点 | C85: 无 | F85: =E85 | J85: =IFERROR(E85/I85,"") | L85: 145299 | M85: - | Q85: =O85/E85 -> #VALUE! | W85: - | Y85: - | AA85: - | AC85: - | AE85: - | AG85: - | AH85: 6553 | AI85: - | AJ85: 719 | AK85: - | AL85: 229 | AM85: - | AN85: 1443 | AO85: - | AP85: 4080 | AQ85: - | AR85: 805 | AS85: - | AV85: 578 | AZ85: 66 | BB85: 0.11418685 | BI85: B | BJ85: 8 | BK85: 6284 | BL85: - | BM85: E | BN85: 58 | BO85: 2036 | BP85: -
A86: 45189 | B86: 日销 | C86: 无 | F86: =E86 | J86: =IFERROR(E86/I86,"") | L86: 92045.05 | M86: - | Q86: =O86/E86 -> #VALUE! | W86: - | Y86: - | AA86: - | AC86: - | AE86: - | AG86: - | AH86: 6698 | AI86: - | AJ86: 609 | AK86: - | AL86: 182 | AM86: - | AN86: 1232 | AO86: - | AP86: 3713 | AQ86: - | AR86: 744 | AS86: - | AV86: 508 | AZ86: 57 | BB86: 0.11220472 | BI86: B | BJ86: 10 | BK86: 5374 | BL86: - | BM86: E | BN86: 66 | BO86: 1725 | BP86: -
A87: 45190 | B87: 预售 | C87: 无 | F87: =E87 | J87: =IFERROR(E87/I87,"") | L87: 68858 | M87: - | Q87: =O87/E87 -> #VALUE! | W87: 5 | Y87: 2 | AA87: 2.5 | AC87: 162.5 | AE87: - | AG87: 0 | AH87: 5575 | AI87: 2 | AJ87: 685 | AK87: - | AL87: 141 | AM87: - | AN87: 1537 | AO87: - | AP87: 3284 | AQ87: - | AR87: 527 | AS87: - | AV87: 452 | AZ87: 40 | BB87: 0.088495575 | BI87: B | BJ87: 9 | BK87: 5385 | BL87: - | BM87: E | BN87: 93 | BO87: 1434 | BP87: -
A88: 45191 | B88: 预售 | C88: 无 | F88: =E88 | J88: =IFERROR(E88/I88,"") | L88: 82093 | M88: - | Q88: =O88/E88 -> #VALUE! | W88: 11 | Y88: 6 | AA88: 1.83 | AC88: 248.67 | AE88: - | AG88: 0 | AH88: 4939 | AI88: 6 | AJ88: 767 | AK88: - | AL88: 173 | AM88: - | AN88: 1458 | AO88: 1 | AP88: 2790 | AQ88: - | AR88: 627 | AS88: - | AV88: 425 | AZ88: 32 | BB88: 0.075294118 | BI88: C | BJ88: 11 | BK88: 4703 | BL88: - | BM88: F | BN88: 114 | BO88: 1092 | BP88: -
A89: 45192 | B89: 预售 | C89: 无 | F89: =E89 | J89: =IFERROR(E89/I89,"") | L89: 102768 | M89: - | Q89: =O89/E89 -> #VALUE! | W89: 14 | Y89: 6 | AA89: 2.33 | AC89: 217.5 | AE89: - | AG89: 0 | AH89: 5883 | AI89: 6 | AJ89: 965 | AK89: - | AL89: 194 | AM89: - | AN89: 1161 | AO89: - | AP89: 3479 | AQ89: - | AR89: 978 | AS89: - | AV89: 467 | AZ89: 44 | BB89: 0.094218415 | BI89: C | BJ89: 13 | BK89: 5032 | BL89: - | BM89: E | BN89: 85 | BO89: 1560 | BP89: -
A90: 45193 | B90: 晚8点 | C90: 无 | F90: =E90 | J90: =IFERROR(E90/I90,"") | L90: 145253 | M90: - | Q90: =O90/E90 -> #VALUE! | W90: 1 | Y90: 1 | AA90: 1 | AC90: 12 | AE90: - | AG90: 2 | AH90: 7332 | AI90: 1 | AJ90: 1081 | AK90: - | AL90: 203 | AM90: - | AN90: 1343 | AO90: - | AP90: 4430 | AQ90: - | AR90: 1163 | AS90: - | AV90: 563 | AZ90: 54 | BB90: 0.095914742 | BI90: B | BJ90: 9 | BK90: 6695 | BL90: - | BM90: E | BN90: 70 | BO90: 2244 | BP90: -
A91: 45194 | B91: 日销 | C91: 预售 | F91: =E91 | J91: =IFERROR(E91/I91,"") | L91: 91704 | M91: 0 | Q91: =O91/E91 -> #VALUE! | W91: 32 | Y91: 18 | AA91: 1.78 | AC91: 50.94 | AE91: - | AG91: 0 | AH91: 6891 | AI91: 13 | AJ91: 638 | AK91: 6 | AL91: 1150 | AM91: 1 | AN91: 167 | AO91: - | AP91: 4047 | AQ91: 2 | AR91: 887 | AS91: - | AV91: 525 | AZ91: 45 | BB91: 0.085714286 | BI91: C | BJ91: 11 | BK91: 6168 | BL91: - | BM91: E | BN91: 70 | BO91: 1999 | BP91: -
A92: 45195 | B92: 预售 | C92: 预售 | F92: =E92 | J92: =IFERROR(E92/I92,"") | L92: 11296 | M92: 3599 | Q92: =O92/E92 -> #VALUE! | W92: 325 | Y92: 156 | AA92: 2.08 | AC92: 94.16 | AE92: - | AG92: 0 | AH92: 5609 | AI92: 114 | AJ92: 659 | AK92: 60 | AL92: 1254 | AM92: 3 | AN92: 163 | AO92: - | AP92: 3319 | AQ92: 31 | AR92: 782 | AS92: 1 | AV92: 483 | AZ92: 0 | BB92: 0 | BI92: C | BJ92: 16 | BK92: 3997 | BL92: - | BM92: F | BN92: 107 | BO92: 1257 | BP92: -
A93: 45196 | B93: 预售 | C93: 预售 | F93: =E93 | J93: =IFERROR(E93/I93,"") | L93: 8998 | M93: 6798 | Q93: =O93/E93 -> #VALUE! | W93: 702 | Y93: 355 | AA93: 1.98 | AC93: 74.68 | AE93: - | AG93: 0 | AH93: 5281 | AI93: 257 | AJ93: 858 | AK93: 137 | AL93: 1140 | AM93: 4 | AN93: 182 | AO93: 5 | AP93: 2992 | AQ93: 84 | AR93: 677 | AS93: 25 | AV93: 391 | AZ93: 39 | BB93: 0.099744246 | BI93: C | BJ93: 14 | BK93: 4421 | BL93: - | BM93: E | BN93: 93 | BO93: 1422 | BP93: -
A94: 45197 | B94: 晚8点 | C94: 预售 | F94: =E94 | J94: =IFERROR(E94/I94,"") | L94: 128758 | M94: 21765 | Q94: =O94/E94 -> #VALUE! | W94: 2198 | Y94: 1170 | AA94: 1.88 | AC94: 65.46 | AE94: - | AG94: 0 | AH94: 4771 | AI94: 517 | AJ94: 827 | AK94: 446 | AL94: 1446 | AM94: 17 | AN94: 180 | AO94: 426 | AP94: 2663 | AQ94: 169 | AR94: 591 | AS94: 105 | AV94: 428 | AZ94: 56 | BB94: 0.13084112 | BI94: C | BJ94: 14 | BK94: 3818 | BL94: - | BM94: F | BN94: 116 | BO94: 1160 | BP94: -
A95: 45198 | B95: 日销 | C95: 预售 | F95: =E95 | J95: =IFERROR(E95/I95,"") | L95: 124609 | M95: 5849 | Q95: =O95/E95 -> #VALUE! | W95: 4449 | Y95: 2544 | AA95: 1.75 | AC95: 70.47 | AE95: - | AG95: 0 | AH95: 4803 | AI95: 859 | AJ95: 936 | AK95: 789 | AL95: 1712 | AM95: 24 | AN95: 97 | AO95: 1376 | AP95: 2693 | AQ95: 243 | AR95: 632 | AS95: 180 | AV95: 366 | AZ95: 55 | BB95: 0.15027322 | BI95: C | BJ95: 14 | BK95: 4109 | BL95: - | BM95: E | BN95: 95 | BO95: 1706 | BP95: -
A96: 45199 | B96: 日销 | C96: 晚8点 | F96: =E96 | J96: =IFERROR(E96/I96,"") | L96: 96365 | M96: 163189 | Q96: =O96/E96 -> #VALUE! | W96: 4822 | Y96: 2290 | AA96: 2.11 | AC96: 74.44 | AE96: - | AG96: 46 | AH96: 6015 | AI96: 1105 | AJ96: 1013 | AK96: 931 | AL96: 1932 | AM96: 18 | AN96: 123 | AO96: 726 | AP96: 3383 | AQ96: 411 | AR96: 750 | AS96: 207 | AV96: 423 | AZ96: 39 | BB96: 0.092198582 | BI96: C | BJ96: 11 | BK96: 4977 | BL96: - | BM96: E | BN96: 96 | BO96: 1833 | BP96: -
A97: 45200 | B97: 日销 | F97: =E97 | J97: =IFERROR(E97/I97,"") | L97: 128824 | M97: 151802 | Q97: =O97/E97 -> #VALUE! | W97: 4079 | Y97: 2093 | AA97: 1.95 | AC97: 68.84 | AE97: - | AG97: 89 | AH97: 5765 | AI97: 1046 | AJ97: 939 | AK97: 709 | AL97: 1797 | AM97: 8 | AN97: 116 | AO97: 732 | AP97: 3281 | AQ97: 491 | AR97: 757 | AS97: 177 | AV97: 0 | AZ97: 0 | BB97: #DIV/0! | BI97: C | BJ97: 16 | BK97: 4053 | BL97: 642 | BM97: F | BN97: 133 | BO97: 1326 | BP97: 228
A98: 45201 | B98: 日销 | F98: =E98 | J98: =IFERROR(E98/I98,"") | L98: 117401 | M98: 37621 | Q98: =O98/E98 -> #VALUE! | W98: 1536 | Y98: 722 | AA98: 2.13 | AC98: 60.79 | AE98: - | AG98: 35 | AH98: 5659 | AI98: 541 | AJ98: 781 | AK98: 249 | AL98: 1311 | AM98: 5 | AN98: 153 | AO98: 27 | AP98: 3333 | AQ98: 296 | AR98: 729 | AS98: 76 | AV98: 0 | AZ98: 0 | BB98: #DIV/0! | BI98: C | BJ98: 14 | BK98: 4334 | BL98: 255 | BM98: F | BN98: 102 | BO98: 1484 | BP98: 116
A99: 45202 | B99: 日销 | F99: =E99 | J99: =IFERROR(E99/I99,"") | L99: 96547 | M99: 36828 | Q99: =O99/E99 -> #VALUE! | W99: 1727 | Y99: 825 | AA99: 2.09 | AC99: 72.02 | AE99: - | AG99: 51 | AH99: 5966 | AI99: 577 | AJ99: 686 | AK99: 313 | AL99: 1217 | AM99: 17 | AN99: 176 | AO99: 13 | AP99: 3608 | AQ99: 285 | AR99: 644 | AS99: 69 | AV99: 0 | AZ99: 0 | BB99: #DIV/0! | BI99: C | BJ99: 15 | BK99: 4467 | BL99: 258 | BM99: E | BN99: 90 | BO99: 1579 | BP99: 94
A100: 45203 | B100: 日销 | F100: =E100 | J100: =IFERROR(E100/I100,"") | L100: 68990 | M100: 2849 | Q100: =O100/E100 -> #VALUE! | W100: 1129 | Y100: 565 | AA100: 2 | AC100: 66.41 | AE100: - | AG100: 32 | AH100: 6332 | AI100: 527 | AJ100: 517 | AK100: 33 | AL100: 1486 | AM100: 6 | AN100: 128 | AO100: 21 | AP100: 3814 | AQ100: 315 | AR100: 776 | AS100: 81 | AV100: 0 | AZ100: 0 | BB100: #DIV/0! | BI100: C | BJ100: 14 | BK100: 3896 | BL100: 405 | BM100: F | BN100: 135 | BO100: 1191 | BP100: 125
...

Sheet 单品16GD32
A1: 100039706989 | D1: 销售出库 | V1: 流量 | AT1: 转化 | BH1: 京仓现货率 | BI1: 关键词排名 | BQ1: 流失分析 | CF1: 负同比每日分析
A2: 日期 | B2: 价格政策 | D2: 销售额 | L2: 模块销售占比 | V2: PV | X2: UV | Z2: 人均浏览量 | AB2: 平均停留时间 | AD2: 关注人数 | AF2: 加购人数 | AH2: 站内免费 | AJ2: 站内付费 | AL2: 站外免费 | AN2: 站外付费 | AP2: 搜索 | AR2: 内容 | AT2: 店铺转化率 | AV2: 询单 数 | AX2: 询单 率 | AZ2: 询单 成交数 | BB2: 询单 转化 | BD2: 静默成交数 | BF2: 静默转化 | BI2: 燃气热水器 | BM2: 热水器 | BQ2: 流量流失 | BV2: 销售流失
B3: Y-23 | C3: Y-22 | D3: Y-23 数量 | E3: Y-23 金额 | F3: 实际销售 | G3: Y-22 金额 | H3: 同比 | I3: 目标 | J3: 达成率 | K3: 类目占比 | L3: 推广成交金额 | M3: 同比 | N3: 占比 | O3: 客服成交金额 | P3: 同比 | Q3: 占比 | R3: Y-23 | S3: Y-22 | T3: 同比 | U3: 占比 | V3: Y-23 | W3: Y-22 | X3: Y-23 | Y3: Y-22 | Z3: Y-23 | AA3: Y-22 | AB3: Y-23 | AC3: Y-22 | AD3: Y-23 | AE3: Y-22 | AF3: Y-23 | AG3: Y-22 | AH3: Y-23 | AI3: Y-22 | AJ3: Y-23 | AK3: Y-22 | AL3: Y-23 | AM3: Y-22 | AN3: Y-23 | AO3: Y-22 | AP3: Y-23 | AQ3: Y-22 | AR3: Y-23 | AS3: Y-22 | AT3: Y-23 | AU3: Y-22 | AV3: Y-23 | AW3: Y-22 | AX3: Y-23 | AY3: Y-22 | AZ3: Y-23 | BA3: Y-22 | BB3: Y-23 | BC3: Y-22 | BD3: Y-23 | BE3: Y-22 | BF3: Y-23 | BG3: Y-22 | BI3: 层级 | BJ3: 排名 | BK3: 搜索曝光 | BL3: Y-22搜索曝光 | BM3: 层级 | BN3: 排名 | BO3: 搜索曝光 | BP3: Y-22搜索曝光 | BQ3: TOP 1 | BR3: TOP 2 | BS3: TOP 3 | BT3: TOP 4 | BU3: TOP 5 | BV3: TOP 1 | BW3: TOP 2 | BX3: TOP 3 | BY3: TOP 4 | BZ3: TOP 5 | CA3: TOP 6 | CB3: TOP 7 | CC3: TOP 8 | CD3: TOP 9 | CE3: TOP 10
A4: 填写人员 | B4: 运营 | C4: 运营 | D4: 张超 | E4: 张超 | F4: 运营 | G4: 张超 | H4: 张超 | I4: 张超 | J4: 张超 | K4: 张超 | L4: 推广 | M4: 推广 | N4: 推广 | O4: 客服 | P4: 客服 | Q4: 客服 | R4: 直播 | S4: 直播 | T4: 直播 | U4: 直播 | V4: 运营 | W4: 运营 | X4: 运营 | Y4: 运营 | Z4: 运营 | AA4: 运营 | AB4: 运营 | AC4: 运营 | AD4: 运营 | AE4: 运营 | AF4: 运营 | AG4: 运营 | AH4: 运营 | AI4: 运营 | AJ4: 运营 | AK4: 运营 | AL4: 运营 | AM4: 运营 | AN4: 运营 | AO4: 运营 | AP4: 运营 | AQ4: 运营 | AR4: 运营 | AS4: 运营 | AT4: 客服 | AU4: 客服 | AV4: 客服 | AW4: 客服 | AX4: 客服 | AY4: 客服 | AZ4: 客服 | BA4: 客服 | BB4: 客服 | BC4: 客服 | BD4: 客服 | BE4: 客服 | BF4: 客服 | BG4: 客服 | BH4: 供应链 | BI4: 运营 | BJ4: 运营 | BK4: 运营 | BL4: 运营 | BM4: 运营 | BN4: 运营 | BO4: 运营 | BP4: 运营 | BQ4: 运营 | BR4: 运营 | BS4: 运营 | BT4: 运营 | BU4: 运营 | BV4: 运营 | BW4: 运营 | BX4: 运营 | BY4: 运营 | BZ4: 运营 | CA4: 运营 | CB4: 运营 | CC4: 运营 | CD4: 运营 | CE4: 运营 | CF4: 运营
A5: 45108 | B5: A | C5: 无 | F5: 2.1294 | H5: =IFERROR(E5/G5-1,"") | I5: 1.0797 | J5: =IFERROR(E5/I5,"") | K5: =IFERROR(E5/#REF!,"") | L5: 31440 | M5: - | R5: 0 | S5: 0 | W5: - | Y5: - | AA5: - | AC5: - | AD5: 7 | AE5: - | AG5: - | AH5: 767 | AI5: - | AJ5: 274 | AK5: - | AL5: 20 | AM5: - | AN5: 18 | AO5: - | AP5: 300 | AQ5: - | AR5: 36 | AS5: - | AT5: 0.0031 | AU5: - | BI5: F | BJ5: 227 | BK5: 288 | BL5: - | BM5: F | BN5: 767 | BO5: 131 | BP5: -
A6: 45109 | B6: A | C6: 无 | F6: 1.7695 | H6: =IFERROR(E6/G6-1,"") | I6: 0.7198 | J6: =IFERROR(E6/I6,"") | K6: =IFERROR(E6/#REF!,"") | L6: 29514 | M6: - | R6: 0 | S6: 0 | W6: - | Y6: - | AA6: - | AC6: - | AD6: 8 | AE6: - | AG6: - | AH6: 853 | AI6: - | AJ6: 297 | AK6: - | AL6: 26 | AM6: - | AN6: 21 | AO6: - | AP6: 319 | AQ6: - | AR6: 49 | AS6: - | AT6: 0.0019 | AU6: - | BI6: F | BJ6: 142 | BK6: 455 | BL6: - | BM6: F | BN6: 1346 | BO6: 57 | BP6: -
A7: 45110 | B7: 预约 | C7: 无 | F7: 1.0497 | H7: =IFERROR(E7/G7-1,"") | I7: 0 | J7: =IFERROR(E7/I7,"") | K7: =IFERROR(E7/#REF!,"") | L7: 7098 | M7: - | R7: 0 | S7: 0 | W7: - | Y7: - | AA7: - | AC7: - | AD7: 12 | AE7: - | AG7: - | AH7: 991 | AI7: - | AJ7: 385 | AK7: - | AL7: 36 | AM7: - | AN7: 19 | AO7: - | AP7: 404 | AQ7: - | AR7: 61 | AS7: - | AT7: 0 | AU7: - | BI7: F | BJ7: 127 | BK7: 502 | BL7: - | BM7: F | BN7: 911 | BO7: 93 | BP7: - | BV7: 16GD31 | BW7: 16QD31 | BX7: 16QD06W | BY7: POP16GD32 | BZ7: 13GD31 | CA7: 16QC05 | CB7: 海尔云程 | CC7: 史密斯TJ1 | CD7: 厂直16GD32 | CE7: 海尔锦绣
A8: 45111 | B8: A | C8: 无 | F8: 6.8281 | H8: =IFERROR(E8/G8-1,"") | I8: 6.4782 | J8: =IFERROR(E8/I8,"") | K8: =IFERROR(E8/#REF!,"") | L8: 28992 | M8: - | R8: 0 | S8: 0 | W8: - | Y8: - | AA8: - | AC8: - | AD8: 12 | AE8: - | AG8: - | AH8: 1067 | AI8: - | AJ8: 331 | AK8: - | AL8: 45 | AM8: - | AN8: 31 | AO8: - | AP8: 440 | AQ8: - | AR8: 78 | AS8: - | AT8: 0.0137 | AU8: - | BI8: F | BJ8: 112 | BK8: 579 | BL8: - | BM8: F | BN8: 722 | BO8: 134 | BP8: -
A9: 45112 | B9: A | C9: 无 | F9: 7.5579 | H9: =IFERROR(E9/G9-1,"") | I9: 7.5579 | J9: =IFERROR(E9/I9,"") | K9: =IFERROR(E9/#REF!,"") | L9: 28452 | M9: - | R9: 3199 | S9: 0 | W9: - | Y9: - | AA9: - | AC9: - | AD9: 8 | AE9: - | AG9: - | AH9: 1234 | AI9: - | AJ9: 343 | AK9: - | AL9: 51 | AM9: - | AN9: 17 | AO9: - | AP9: 556 | AQ9: - | AR9: 73 | AS9: - | AT9: 0.0142 | AU9: - | BH9: 0.75 | BI9: E | BJ9: 75 | BK9: 826 | BL9: - | BM9: F | BN9: 526 | BO9: 191 | BP9: -
A10: 45113 | B10: 预约 | C10: 无 | F10: 0.6998 | H10: =IFERROR(E10/G10-1,"") | I10: 0 | J10: =IFERROR(E10/I10,"") | K10: =IFERROR(E10/#REF!,"") | L10: 9198 | M10: - | R10: 0 | S10: 0 | W10: - | Y10: - | AA10: - | AC10: - | AD10: 9 | AE10: - | AG10: - | AH10: 798 | AI10: - | AJ10: 297 | AK10: - | AL10: 55 | AM10: - | AN10: 11 | AO10: - | AP10: 259 | AQ10: - | AR10: 43 | AS10: - | AT10: 0 | AU10: - | BH10: 0.65 | BI10: F | BJ10: 199 | BK10: 295 | BL10: - | BM10: F | BN10: 970 | BO10: 78 | BP10: -
A11: 45114 | B11: A | C11: 无 | F11: 2.4893 | H11: =IFERROR(E11/G11-1,"") | I11: 1.4396 | J11: =IFERROR(E11/I11,"") | K11: =IFERROR(E11/#REF!,"") | L11: 9597 | M11: - | R11: 0 | S11: 0 | W11: - | Y11: - | AA11: - | AC11: - | AD11: 2 | AE11: - | AG11: - | AH11: 728 | AI11: - | AJ11: 147 | AK11: - | AL11: 25 | AM11: - | AN11: 11 | AO11: - | AP11: 222 | AQ11: - | AR11: 30 | AS11: - | AT11: 0.0048 | AU11: - | BH11: 0.45 | BI11: F | BJ11: 215 | BK11: 266 | BL11: - | BM11: F | BN11: 1086 | BO11: 65 | BP11: -
A12: 45115 | B12: A | C12: 无 | F12: 4.2888 | H12: =IFERROR(E12/G12-1,"") | I12: 3.2391 | J12: =IFERROR(E12/I12,"") | K12: =IFERROR(E12/#REF!,"") | L12: 7098 | M12: - | R12: 0 | S12: 0 | W12: - | Y12: - | AA12: - | AC12: - | AD12: 9 | AE12: - | AG12: - | AH12: 798 | AI12: - | AJ12: 215 | AK12: - | AL12: 36 | AM12: - | AN12: 7 | AO12: - | AP12: 290 | AQ12: - | AR12: 39 | AS12: - | AT12: 0.0093 | AU12: - | BI12: F | BJ12: 158 | BK12: 407 | BL12: - | BM12: F | BN12: 1054 | BO12: 80 | BP12: -
A13: 45116 | B13: 预约 | C13: 无 | F13: 1.0497 | H13: =IFERROR(E13/G13-1,"") | I13: 0 | J13: =IFERROR(E13/I13,"") | K13: =IFERROR(E13/#REF!,"") | L13: 2849 | M13: - | R13: 0 | S13: 0 | W13: - | Y13: - | AA13: - | AC13: - | AD13: 4 | AE13: - | AG13: - | AH13: 895 | AI13: - | AJ13: 355 | AK13: - | AL13: 25 | AM13: - | AN13: 19 | AO13: - | AP13: 336 | AQ13: - | AR13: 61 | AS13: - | AT13: 0 | AU13: - | BI13: F | BJ13: 200 | BK13: 352 | BL13: - | BM13: F | BN13: 1451 | BO13: 50 | BP13: -
A14: 45117 | B14: 预约 | C14: 无 | F14: 1.0497 | H14: =IFERROR(E14/G14-1,"") | I14: 0 | J14: =IFERROR(E14/I14,"") | K14: =IFERROR(E14/#REF!,"") | L14: 9720 | M14: - | R14: 0 | S14: 0 | W14: - | Y14: - | AA14: - | AC14: - | AD14: 5 | AE14: - | AG14: - | AH14: 826 | AI14: - | AJ14: 281 | AK14: - | AL14: 25 | AM14: - | AN14: 17 | AO14: - | AP14: 251 | AQ14: - | AR14: 45 | AS14: - | AT14: 0 | AU14: - | BH14: 0.65 | BI14: F | BJ14: 221 | BK14: 288 | BL14: - | BM14: F | BN14: 1246 | BO14: 56 | BP14: -
A15: 45118 | B15: A | C15: 无 | F15: 7.9381 | H15: =IFERROR(E15/G15-1,"") | I15: 7.9381 | J15: =IFERROR(E15/I15,"") | K15: =IFERROR(E15/#REF!,"") | L15: 23893 | M15: - | R15: 6398 | S15: 0 | W15: - | Y15: - | AA15: - | AC15: - | AD15: 4 | AE15: - | AG15: - | AH15: 731 | AI15: - | AJ15: 262 | AK15: - | AL15: 23 | AM15: - | AN15: 44 | AO15: - | AP15: 214 | AQ15: - | AR15: 59 | AS15: - | AT15: 0.0122 | AU15: - | BI15: F | BJ15: 334 | BK15: 192 | BL15: - | BM15: F | BN15: 1071 | BO15: 76 | BP15: - | BV15: 16QD31 | BW15: 16GD31 | BX15: 16QD06W | BY15: 厂直16GD32 | BZ15: 16QC05 | CA15: POP16GD32 | CB15: 13QC05 | CC15: 海尔锦绣 | CD15: POP16QC06 | CE15: 海尔云程
A16: 45119 | B16: A | C16: 无 | F16: 4.1489 | H16: =IFERROR(E16/G16-1,"") | I16: 8.8 | J16: =IFERROR(E16/I16,"") | K16: =IFERROR(E16/#REF!,"") | L16: 14095 | M16: - | R16: 0 | S16: 0 | W16: - | Y16: - | AA16: - | AC16: - | AD16: 5 | AE16: - | AG16: - | AH16: 730 | AI16: - | AJ16: 132 | AK16: - | AL16: 24 | AM16: - | AN16: 24 | AO16: - | AP16: 235 | AQ16: - | AR16: 57 | AS16: - | AT16: 0.0095 | AU16: - | BH16: 0.8 | BI16: F | BJ16: 275 | BK16: 239 | BL16: - | BM16: F | BN16: 958 | BO16: 90 | BP16: -
A17: 45120 | B17: A | C17: 无 | F17: 4.6087 | H17: =IFERROR(E17/G17-1,"") | I17: 7.2 | J17: =IFERROR(E17/I17,"") | K17: =IFERROR(E17/#REF!,"") | L17: 14196 | M17: - | R17: 3199 | S17: 0 | W17: - | Y17: - | AA17: - | AC17: - | AD17: 1 | AE17: - | AG17: - | AH17: 709 | AI17: - | AJ17: 262 | AK17: - | AL17: 50 | AM17: - | AN17: 32 | AO17: - | AP17: 236 | AQ17: - | AR17: 37 | AS17: - | AT17: 0.0065 | AU17: - | BH17: 0.8 | BI17: F | BJ17: 378 | BK17: 161 | BL17: - | BM17: F | BN17: 1323 | BO17: 51 | BP17: -
A18: 45121 | B18: 预约 | C18: 无 | F18: 3.9389 | H18: =IFERROR(E18/G18-1,"") | I18: 0 | J18: =IFERROR(E18/I18,"") | K18: =IFERROR(E18/#REF!,"") | L18: 19476 | M18: - | R18: ？ | S18: 0 | W18: - | Y18: - | AA18: - | AC18: - | AD18: 5 | AE18: - | AG18: - | AH18: 938 | AI18: - | AJ18: 302 | AK18: - | AL18: 27 | AM18: - | AN18: 92 | AO18: - | AP18: 389 | AQ18: - | AR18: 104 | AS18: - | AT18: 0.0074 | AU18: - | BH18: 0.85 | BI18: F | BJ18: 189 | BK18: 364 | BL18: - | BM18: F | BN18: 653 | BO18: 165 | BP18: -
A19: 45122 | B19: 预约 | C19: 无 | F19: 1.0497 | H19: =IFERROR(E19/G19-1,"") | I19: 0 | J19: =IFERROR(E19/I19,"") | K19: =IFERROR(E19/#REF!,"") | L19: 19576 | M19: - | R19: 0 | S19: 0 | W19: - | Y19: - | AA19: - | AC19: - | AD19: 7 | AE19: - | AG19: - | AH19: 1049 | AI19: - | AJ19: 484 | AK19: - | AL19: 27 | AM19: - | AN19: 51 | AO19: - | AP19: 466 | AQ19: - | AR19: 91 | AS19: - | AT19: 0 | AU19: - | BI19: F | BJ19: 130 | BK19: 505 | BL19: - | BM19: F | BN19: 787 | BO19: 130 | BP19: -
A20: 45123 | B20: S | C20: 无 | F20: 3.9189 | H20: =IFERROR(E20/G20-1,"") | I20: 22.4 | J20: =IFERROR(E20/I20,"") | K20: =IFERROR(E20/#REF!,"") | L20: 34790 | M20: - | R20: 6798 | S20: 0 | W20: - | Y20: - | AA20: - | AC20: - | AD20: 8 | AE20: - | AG20: - | AH20: 1340 | AI20: - | AJ20: 635 | AK20: - | AL20: 37 | AM20: - | AN20: 66 | AO20: - | AP20: 614 | AQ20: - | AR20: 137 | AS20: - | AT20: 0.0038 | AU20: - | BI20: F | BJ20: 147 | BK20: 518 | BL20: - | BM20: F | BN20: 1104 | BO20: 132 | BP20: -
A21: 45124 | B21: S | C21: 无 | F21: 6.4382 | H21: =IFERROR(E21/G21-1,"") | I21: 14.4 | J21: =IFERROR(E21/I21,"") | K21: =IFERROR(E21/#REF!,"") | L21: 47484 | M21: - | R21: 3199 | S21: 0 | W21: - | Y21: - | AA21: - | AC21: - | AD21: 13 | AE21: - | AG21: - | AH21: 1490 | AI21: - | AJ21: 509 | AK21: - | AL21: 40 | AM21: - | AN21: 16 | AO21: - | AP21: 717 | AQ21: - | AR21: 140 | AS21: - | AT21: 0.0078 | AU21: - | BH21: 0.85 | BI21: E | BJ21: 89 | BK21: 703 | BL21: - | BM21: F | BN21: 875 | BO21: 170 | BP21: -
A22: 45125 | B22: A | C22: 无 | F22: 5.6884 | H22: =IFERROR(E22/G22-1,"") | I22: 7.2 | J22: =IFERROR(E22/I22,"") | K22: =IFERROR(E22/#REF!,"") | L22: 70130 | M22: - | R22: 6398 | S22: 0 | W22: - | Y22: - | AA22: - | AC22: - | AD22: 11 | AE22: - | AG22: - | AH22: 1223 | AI22: - | AJ22: 372 | AK22: - | AL22: 35 | AM22: - | AN22: 23 | AO22: - | AP22: 606 | AQ22: - | AR22: 129 | AS22: - | AT22: 0.0061 | AU22: - | BH22: 0.85 | BI22: F | BJ22: 121 | BK22: 512 | BL22: - | BM22: F | BN22: 913 | BO22: 123 | BP22: - | BV22: 16GD31 | BW22: 16QD31 | BX22: 16QD06W | BY22: 13GD32 | BZ22: 16QD06* | CA22: 16QC05 | CB22: 厂直16GD32 | CC22: POP16GD32 | CD22: 海尔锦绣 | CE22: POP16QC06
A23: 45126 | B23: 预售 | C23: 无 | F23: 2.1494 | H23: =IFERROR(E23/G23-1,"") | I23: 0 | J23: =IFERROR(E23/I23,"") | K23: =IFERROR(E23/#REF!,"") | L23: 44581 | M23: - | R23: 0 | S23: 0 | W23: - | Y23: - | AA23: - | AC23: - | AD23: 5 | AE23: - | AG23: - | AH23: 1141 | AI23: - | AJ23: 337 | AK23: - | AL23: 27 | AM23: - | AN23: 22 | AO23: - | AP23: 540 | AQ23: - | AR23: 130 | AS23: - | AT23: 0.0037 | AU23: - | BH23: 0.85 | BI23: F | BJ23: 158 | BK23: 428 | BL23: - | BM23: F | BN23: 1195 | BO23: 91 | BP23: -
A24: 45127 | B24: 预售 | C24: 无 | F24: 5.351 | H24: =IFERROR(E24/G24-1,"") | I24: 13.6 | J24: =IFERROR(E24/I24,"") | K24: =IFERROR(E24/#REF!,"") | L24: 19715 | M24: - | R24: 3199 | S24: 0 | W24: - | Y24: - | AA24: - | AC24: - | AD24: 9 | AE24: - | AG24: - | AH24: 1038 | AI24: - | AJ24: 322 | AK24: - | AL24: 28 | AM24: - | AN24: 18 | AO24: - | AP24: 492 | AQ24: - | AR24: 117 | AS24: - | AT24: 0.0098 | AU24: - | BH24: 0.65 | BI24: F | BJ24: 166 | BK24: 391 | BL24: - | BM24: F | BN24: 848 | BO24: 114 | BP24: -
A25: 45128 | B25: S | C25: 无 | F25: 5.0011 | H25: =IFERROR(E25/G25-1,"") | I25: 10.4 | J25: =IFERROR(E25/I25,"") | K25: =IFERROR(E25/#REF!,"") | L25: 20494 | M25: - | R25: 0 | S25: 0 | W25: - | Y25: - | AA25: - | AC25: - | AD25: 8 | AE25: - | AG25: - | AH25: 1275 | AI25: - | AJ25: 312 | AK25: - | AL25: 48 | AM25: - | AN25: 770 | AO25: - | AP25: 652 | AQ25: - | AR25: 125 | AS25: - | AT25: 0.0054 | AU25: - | BH25: 0.55 | BI25: E | BJ25: 94 | BK25: 623 | BL25: - | BM25: F | BN25: 540 | BO25: 195 | BP25: -
A26: 45129 | B26: A | C26: 无 | F26: 6.7481 | H26: =IFERROR(E26/G26-1,"") | I26: 7.2 | J26: =IFERROR(E26/I26,"") | K26: =IFERROR(E26/#REF!,"") | L26: 17395 | M26: - | R26: 6246 | S26: 0 | W26: - | Y26: - | AA26: - | AC26: - | AD26: 11 | AE26: - | AG26: - | AH26: 1692 | AI26: - | AJ26: 399 | AK26: - | AL26: 39 | AM26: - | AN26: 2849 | AO26: - | AP26: 871 | AQ26: - | AR26: 155 | AS26: - | AT26: 0.0036 | AU26: - | BI26: E | BJ26: 73 | BK26: 946 | BL26: - | BM26: F | BN26: 481 | BO26: 251 | BP26: -
A27: 45130 | B27: A | C27: 无 | F27: 5.7015 | H27: =IFERROR(E27/G27-1,"") | I27: 0 | J27: =IFERROR(E27/I27,"") | K27: =IFERROR(E27/#REF!,"") | L27: 55266 | M27: - | R27: 0 | S27: 0 | W27: - | Y27: - | AA27: - | AC27: - | AD27: 16 | AE27: - | AG27: - | AH27: 1977 | AI27: - | AJ27: 521 | AK27: - | AL27: 51 | AM27: - | AN27: 1953 | AO27: - | AP27: 1151 | AQ27: - | AR27: 194 | AS27: - | AT27: 0.0029 | AU27: - | BI27: E | BJ27: 65 | BK27: 1180 | BL27: - | BM27: F | BN27: 426 | BO27: 295 | BP27: -
A28: 45131 | B28: 预约 | C28: 无 | F28: 5.0389 | H28: =IFERROR(E28/G28-1,"") | I28: 14.4 | J28: =IFERROR(E28/I28,"") | K28: =IFERROR(E28/#REF!,"") | L28: 35979 | M28: - | R28: 9597 | S28: 0 | W28: - | Y28: - | AA28: - | AC28: - | AD28: 12 | AE28: - | AG28: - | AH28: 1657 | AI28: - | AJ28: 596 | AK28: - | AL28: 49 | AM28: - | AN28: 2800 | AO28: - | AP28: 800 | AQ28: - | AR28: 161 | AS28: - | AT28: 0.003 | AU28: - | BH28: 0.8 | BI28: E | BJ28: 77 | BK28: 830 | BL28: - | BM28: F | BN28: 579 | BO28: 184 | BP28: -
A29: 45132 | B29: S | C29: 无 | F29: 10.4196 | H29: =IFERROR(E29/G29-1,"") | I29: 11.2 | J29: =IFERROR(E29/I29,"") | K29: =IFERROR(E29/#REF!,"") | L29: 28673 | M29: - | R29: 3199 | S29: 0 | W29: - | Y29: - | AA29: - | AC29: - | AD29: 6 | AE29: - | AG29: - | AH29: 1825 | AI29: - | AJ29: 470 | AK29: - | AL29: 75 | AM29: - | AN29: 1091 | AO29: - | AP29: 971 | AQ29: - | AR29: 144 | AS29: - | AT29: 0.0092 | AU29: - | BH29: 0.95 | BI29: E | BJ29: 65 | BK29: 1041 | BL29: - | BM29: F | BN29: 393 | BO29: 288 | BP29: - | BV29: 16QD31 | BW29: 16GD31 | BX29: 厂直16GD32 | BY29: 13GD31 | BZ29: 厂直16GD31 | CA29: 16QD06W | CB29: 厂直13GD31 | CC29: 13GD32 | CD29: 16QC05 | CE29: 五星16GD32
A30: 45133 | B30: A | C30: 无 | F30: 22.854 | H30: =IFERROR(E30/G30-1,"") | I30: 6.4 | J30: =IFERROR(E30/I30,"") | K30: =IFERROR(E30/#REF!,"") | L30: 18725 | M30: - | R30: 0 | S30: 0 | W30: - | Y30: - | AA30: - | AC30: - | AD30: 19 | AE30: - | AG30: - | AH30: 1759 | AI30: - | AJ30: 364 | AK30: - | AL30: 69 | AM30: - | AN30: 732 | AO30: - | AP30: 942 | AQ30: - | AR30: 164 | AS30: - | AT30: 0.0123 | AU30: - | BI30: E | BJ30: 59 | BK30: 1091 | BL30: - | BM30: F | BN30: 376 | BO30: 305 | BP30: -
A31: 45134 | B31: A | C31: 无 | F31: 18.9403 | H31: =IFERROR(E31/G31-1,"") | I31: 8 | J31: =IFERROR(E31/I31,"") | K31: =IFERROR(E31/#REF!,"") | L31: 15977 | M31: - | R31: 3199 | S31: 0 | W31: - | Y31: - | AA31: - | AC31: - | AD31: 19 | AE31: - | AG31: - | AH31: 1863 | AI31: - | AJ31: 429 | AK31: - | AL31: 64 | AM31: - | AN31: 1198 | AO31: - | AP31: 1006 | AQ31: - | AR31: 187 | AS31: - | AT31: 0.0098 | AU31: - | BH31: 0.95 | BI31: E | BJ31: 63 | BK31: 984 | BL31: - | BM31: F | BN31: 363 | BO31: 309 | BP31: -
A32: 45135 | B32: A | C32: 无 | F32: 6.8031 | H32: =IFERROR(E32/G32-1,"") | I32: 8 | J32: =IFERROR(E32/I32,"") | K32: =IFERROR(E32/#REF!,"") | L32: 18535 | M32: - | R32: 0 | S32: 0 | W32: - | Y32: - | AA32: - | AC32: - | AD32: 11 | AE32: - | AG32: - | AH32: 1770 | AI32: - | AJ32: 317 | AK32: - | AL32: 34 | AM32: - | AN32: 2051 | AO32: - | AP32: 940 | AQ32: - | AR32: 158 | AS32: - | AT32: 0.0049 | AU32: - | BH32: 0.9 | BI32: E | BJ32: 57 | BK32: 1055 | BL32: - | BM32: F | BN32: 361 | BO32: 296 | BP32: -
A33: 45136 | B33: 预售 | C33: 无 | F33: 0.3499 | H33: =IFERROR(E33/G33-1,"") | I33: 0 | J33: =IFERROR(E33/I33,"") | K33: =IFERROR(E33/#REF!,"") | L33: 21194 | M33: - | R33: 0 | S33: 0 | W33: - | Y33: - | AA33: - | AC33: - | AD33: 21 | AE33: - | AG33: - | AH33: 2199 | AI33: - | AJ33: 497 | AK33: - | AL33: 76 | AM33: - | AN33: 4368 | AO33: - | AP33: 1194 | AQ33: - | AR33: 160 | AS33: - | AT33: 0 | AU33: - | BI33: E | BJ33: 52 | BK33: 1205 | BL33: - | BM33: F | BN33: 338 | BO33: 367 | BP33: -
A34: 45137 | B34: 预售 | C34: 无 | F34: =E34 | H34: =IFERROR(E34/G34-1,"") | I34: 0 | J34: =IFERROR(E34/I34,"") | K34: =IFERROR(E34/#REF!,"") | L34: 23453 | M34: - | O34: 14.7459 | P34: / | Q34: 0.1344 | R34: 0 | S34: 0 | W34: - | Y34: - | AA34: - | AC34: - | AD34: 11 | AE34: - | AG34: - | AH34: 2092 | AI34: - | AJ34: 449 | AK34: - | AL34: 53 | AM34: - | AN34: 1815 | AO34: - | AP34: 1105 | AQ34: - | AR34: 130 | AS34: - | AT34: 0 | AU34: - | AV34: 115 | AW34: - | AY34: - | AZ34: 15 | BA34: - | BB34: 0.13043478 | BC34: - | BH34: 0.8 | BI34: E | BJ34: 58 | BK34: 1231 | BL34: - | BM34: F | BN34: 357 | BO34: 342 | BP34: -
A35: 45138 | B35: 限时 | C35: 无 | F35: =E35 | H35: =IFERROR(E35/G35-1,"") | I35: 24 | J35: =IFERROR(E35/I35,"") | K35: =IFERROR(E35/#REF!,"") | L35: 66682 | M35: - | R35: 9842 | S35: 0 | W35: - | Y35: - | AA35: - | AC35: - | AD35: 14 | AE35: - | AG35: - | AH35: 2146 | AI35: - | AJ35: 459 | AK35: - | AL35: 78 | AM35: - | AN35: 2459 | AO35: - | AP35: 1150 | AQ35: - | AR35: 106 | AS35: - | AT35: 0.0117 | AU35: - | BH35: 0.8 | BI35: E | BJ35: 55 | BK35: 1282 | BL35: - | BM35: F | BN35: 373 | BO35: 334 | BP35: -
A36: 45139 | B36: S级 | C36: 无 | F36: =E36 | I36: 12 | J36: =IFERROR(E36/I36,"") | K36: =IFERROR(E36/#REF!,"") | L36: 25211 | M36: - | O36: 10.867 | W36: - | Y36: - | AA36: - | AC36: - | AD36: 10 | AE36: - | AG36: - | AH36: 2724 | AI36: - | AJ36: 411 | AK36: - | AL36: 50 | AM36: - | AN36: 1987 | AO36: - | AP36: 1085 | AQ36: - | AR36: 144 | AS36: - | AT36: 0.011480787 | AV36: 134 | AW36: - | AX36: 0.0313 | AY36: - | BH36: 0.8 | BI36: E | BJ36: 58 | BK36: 1114 | BL36: - | BM36: F | BN36: 403 | BO36: 318 | BP36: - | BV36: 16GD31 | BW36: 16QD31 | BX36: 16QD06W | BY36: 16QC05 | BZ36: 13GD31 | CA36: 13GD32 | CB36: 海尔锦绣 | CC36: 能率16E4 | CD36: 海尔云程 | CE36: 小店C08
A37: 45140 | B37: A级 | C37: 无 | F37: =E37-2.1 -> #VALUE! | I37: 6 | J37: =IFERROR(E37/I37,"") | K37: =IFERROR(E37/#REF!,"") | L37: 39190 | M37: - | W37: - | Y37: - | AA37: - | AC37: - | AD37: 8 | AE37: - | AG37: - | AH37: 2393 | AI37: - | AJ37: 282 | AK37: - | AL37: 55 | AM37: - | AN37: 1475 | AO37: - | AP37: 944 | AQ37: - | AR37: 93 | AS37: - | BH37: 0.65 | BI37: E | BJ37: 55 | BK37: 1244 | BL37: - | BM37: F | BN37: 373 | BO37: 326 | BP37: - | CE37: 小店C08
A38: 45141 | B38: A级 | C38: 无 | F38: =E38-2.1 -> #VALUE! | I38: 6 | J38: =IFERROR(E38/I38,"") | K38: =IFERROR(E38/#REF!,"") | L38: 10797 | M38: - | W38: - | Y38: - | AA38: - | AC38: - | AD38: 9 | AE38: - | AG38: - | AH38: 2549 | AI38: - | AJ38: 308 | AK38: - | AL38: 57 | AM38: - | AN38: 2640 | AO38: - | AP38: 997 | AQ38: - | AR38: 109 | AS38: - | BH38: 0.65 | BI38: E | BJ38: 62 | BK38: 1037 | BL38: - | BM38: F | BN38: 435 | BO38: 272 | BP38: - | CE38: 小店C08
A39: 45142 | B39: A级 | C39: 无 | F39: =E39-2.45 -> #VALUE! | I39: 8 | J39: =IFERROR(E39/I39,"") | K39: =IFERROR(E39/#REF!,"") | L39: 20776 | M39: - | W39: - | Y39: - | AA39: - | AC39: - | AD39: 11 | AE39: - | AG39: - | AH39: 2733 | AI39: - | AJ39: 335 | AK39: - | AL39: 60 | AM39: - | AN39: 2555 | AO39: - | AP39: 1130 | AQ39: - | AR39: 112 | AS39: - | BH39: 0.65 | BI39: E | BJ39: 54 | BK39: 1271 | BL39: - | BM39: F | BN39: 338 | BO39: 359 | BP39: - | CE39: 小店C08
A40: 45143 | B40: 预售 | C40: 无 | F40: =E40 | I40: 0 | J40: =IFERROR(E40/I40,"") | K40: =IFERROR(E40/#REF!,"") | L40: 12796 | M40: - | W40: - | Y40: - | AA40: - | AC40: - | AD40: 23 | AE40: - | AG40: - | AH40: 2821 | AI40: - | AJ40: 478 | AK40: - | AL40: 54 | AM40: - | AN40: 903 | AO40: - | AP40: 1214 | AQ40: - | AR40: 142 | AS40: - | BH40: 0.7 | BI40: D | BJ40: 49 | BK40: 1509 | BL40: - | BM40: F | BN40: 296 | BO40: 421 | BP40: - | CE40: 小店C08
A41: 45144 | B41: 预售 | C41: 无 | F41: =E41 | I41: 0 | J41: =IFERROR(E41/I41,"") | K41: =IFERROR(E41/#REF!,"") | L41: 23023 | M41: - | W41: - | Y41: - | AA41: - | AC41: - | AD41: 14 | AE41: - | AG41: - | AH41: 3215 | AI41: - | AJ41: 574 | AK41: - | AL41: 81 | AM41: - | AN41: 1484 | AO41: - | AP41: 1390 | AQ41: - | AR41: 145 | AS41: - | BH41: 0.95 | BI41: D | BJ41: 45 | BK41: 1711 | BL41: - | BM41: F | BN41: 256 | BO41: 503 | BP41: - | CE41: 小店C08
A42: 45145 | B42: S级 | C42: 无 | F42: =E42-1 -> #VALUE! | I42: 22 | J42: =IFERROR(E42/I42,"") | K42: =IFERROR(E42/#REF!,"") | L42: 60082 | M42: - | W42: - | Y42: - | AA42: - | AC42: - | AE42: - | AG42: - | AH42: 3562 | AI42: - | AJ42: 589 | AK42: - | AL42: 102 | AM42: - | AN42: 1230 | AO42: - | AP42: 1283 | AQ42: - | AR42: 276 | AS42: - | BH42: 0.95 | BI42: D | BJ42: 49 | BK42: 1391 | BL42: - | BM42: F | BN42: 283 | BO42: 221 | BP42: - | CE42: 小店C08
A43: 45146 | B43: S级 | C43: 无 | F43: =E43-3.5 -> #VALUE! | I43: 12 | J43: =IFERROR(E43/I43,"") | K43: =IFERROR(E43/#REF!,"") | L43: 52044 | M43: - | W43: - | Y43: - | AA43: - | AC43: - | AE43: - | AG43: - | AH43: 3571 | AI43: - | AJ43: 473 | AK43: - | AL43: 96 | AM43: - | AN43: 960 | AO43: - | AP43: 1380 | AQ43: - | AR43: 266 | AS43: - | BH43: 1 | BI43: D | BJ43: 44 | BK43: 1446 | BL43: - | BM43: F | BN43: 359 | BO43: 176 | BP43: - | BV43: 16GD31 | BW43: 16QD31 | BX43: 16QC05 | BY43: 16QD06W | BZ43: 海尔云程 | CA43: 海尔锦绣 | CB43: 能率16E4 | CC43: 13GD31 | CD43: 13GD32 | CE43: 能率16V36A
A44: 45147 | B44: A级 | C44: 无 | F44: =E44-1.4 -> #VALUE! | I44: 6 | J44: =IFERROR(E44/I44,"") | K44: =IFERROR(E44/#REF!,"") | L44: 23493 | M44: - | W44: - | Y44: - | AA44: - | AC44: - | AE44: - | AG44: - | AH44: 3289 | AI44: - | AJ44: 341 | AK44: - | AL44: 109 | AM44: - | AN44: 1047 | AO44: - | AP44: 1244 | AQ44: - | AR44: 278 | AS44: - | BH44: 1 | BI44: D | BJ44: 38 | BK44: 1716 | BL44: - | BM44: F | BN44: 454 | BO44: 119 | BP44: -
A45: 45148 | B45: A级 | C45: 无 | F45: =E45-1.75 -> #VALUE! | I45: 6 | J45: =IFERROR(E45/I45,"") | K45: =IFERROR(E45/#REF!,"") | L45: 21994 | M45: - | O45: 3.2 | W45: - | Y45: - | AA45: - | AC45: - | AE45: - | AG45: - | AH45: 3314 | AI45: - | AJ45: 386 | AK45: - | AL45: 89 | AM45: - | AN45: 1313 | AO45: - | AP45: 1386 | AQ45: - | AR45: 304 | AS45: - | AV45: 158 | AW45: - | AX45: 0.040306122 | AY45: #VALUE! | AZ45: 10 | BA45: - | BB45: 0.063291139 | BC45: #VALUE! | BH45: 1 | BI45: D | BJ45: 44 | BK45: 1441 | BL45: - | BM45: F | BN45: 289 | BO45: 444 | BP45: -
A46: 45149 | B46: 预售 | C46: 无 | I46: 0 | J46: =IFERROR(E46/I46,"") | K46: =IFERROR(E46/#REF!,"") | L46: 47887 | M46: - | O46: 4.5 | W46: - | Y46: - | AA46: - | AC46: - | AE46: - | AG46: - | AH46: 3355 | AI46: - | AJ46: 498 | AK46: - | AL46: 80 | AM46: - | AN46: 1318 | AO46: - | AP46: 1379 | AQ46: - | AR46: 260 | AS46: - | AV46: 198 | AX46: 0.048577036 | AY46: #VALUE! | AZ46: 13 | BB46: 0.065656566 | BC46: #DIV/0! | BH46: 1 | BI46: D | BJ46: 49 | BK46: 1190 | BL46: - | BM46: F | BN46: 341 | BO46: 398 | BP46: -
A47: 45150 | B47: 预售 | C47: 无 | F47: =E47 | I47: 0 | J47: =IFERROR(E47/I47,"") | K47: =IFERROR(E47/#REF!,"") | L47: 43687 | M47: - | O47: 5.5 | W47: - | Y47: - | AA47: - | AC47: - | AE47: - | AG47: - | AH47: 3442 | AI47: - | AJ47: 671 | AK47: - | AL47: 61 | AM47: - | AN47: 1793 | AO47: - | AP47: 1471 | AQ47: - | AR47: 226 | AS47: - | AV47: 164 | AX47: 0.035683203 | AY47: #VALUE! | AZ47: 21 | BB47: 0.12804878 | BC47: #DIV/0! | BH47: 1 | BI47: D | BJ47: 41 | BK47: 1590 | BL47: - | BM47: F | BN47: 261 | BO47: 548 | BP47: -
A48: 45151 | B48: 预售 | C48: 无 | F48: =E48 | I48: 0 | J48: =IFERROR(E48/I48,"") | K48: =IFERROR(E48/#REF!,"") | L48: 57182 | M48: - | O48: 4.4 | W48: - | Y48: - | AA48: - | AC48: - | AE48: - | AG48: - | AH48: 3884 | AI48: - | AJ48: 700 | AK48: - | AL48: 68 | AM48: - | AN48: 1783 | AO48: - | AP48: 1591 | AQ48: - | AR48: 286 | AS48: - | AV48: 149 | AX48: 0.030514028 | AY48: #VALUE! | AZ48: 17 | BB48: 0.11409396 | BC48: #DIV/0! | BH48: 0.93 | BI48: D | BJ48: 41 | BK48: 1591 | BL48: - | BM48: F | BN48: 249 | BO48: 568 | BP48: -
A49: 45152 | B49: 预售+S级 | C49: 无 | F49: =E49 | I49: 36 | J49: =IFERROR(E49/I49,"") | K49: =IFERROR(E49/#REF!,"") | L49: 149389 | M49: - | O49: 14.7 | W49: - | Y49: - | AA49: - | AC49: - | AE49: - | AG49: - | AH49: 4704 | AI49: - | AJ49: 1009 | AK49: - | AL49: 128 | AM49: - | AN49: 2096 | AO49: - | AP49: 1639 | AQ49: - | AR49: 338 | AS49: - | AV49: 252 | AX49: 0.044148563 | AY49: #VALUE! | AZ49: 51 | BB49: 0.20238095 | BC49: #DIV/0! | BH49: 0.93 | BI49: D | BJ49: 38 | BK49: 1759 | BL49: - | BM49: F | BN49: 243 | BO49: 574 | BP49: -
A50: 45153 | B50: S级 | C50: 无 | F50: =E50-3.8 -> #VALUE! | I50: 16 | J50: =IFERROR(E50/I50,"") | K50: =IFERROR(E50/#REF!,"") | L50: 71590 | M50: - | O50: 5.9 | W50: - | Y50: - | AA50: - | AC50: - | AE50: - | AG50: - | AH50: 3787 | AI50: - | AJ50: 831 | AK50: - | AL50: 101 | AM50: - | AN50: 1719 | AO50: - | AP50: 1406 | AQ50: - | AR50: 250 | AS50: - | AV50: 190 | AX50: 0.039765592 | AY50: #VALUE! | AZ50: 21 | BB50: 0.11052632 | BC50: #DIV/0! | BH50: 1 | BI50: E | BJ50: 64 | BK50: 1185 | BL50: - | BM50: F | BN50: 338 | BO50: 397 | BP50: - | BV50: 16GD31 | BW50: 16QD31 | BX50: 16QD06W | BY50: 海尔锦绣 | BZ50: 13GD31 | CA50: 16GD61R | CB50: 16QC05 | CC50: 13GD32 | CD50: 厂直16QD31+SG | CE50: 海尔云程
A51: 45154 | B51: A级 | C51: 无 | F51: =E51-2 -> #VALUE! | I51: 0 | J51: =IFERROR(E51/I51,"") | K51: =IFERROR(E51/#REF!,"") | L51: 64783 | M51: - | O51: 4.8 | W51: - | Y51: - | AA51: - | AC51: - | AE51: - | AG51: - | AH51: 3252 | AI51: - | AJ51: 666 | AK51: - | AL51: 86 | AM51: - | AN51: 1964 | AO51: - | AP51: 1214 | AQ51: - | AR51: 222 | AS51: - | AV51: 146 | AX51: 0.032137354 | AY51: #VALUE! | AZ51: 16 | BB51: 0.10958904 | BC51: #DIV/0! | BH51: 1 | BI51: E | BJ51: 58 | BK51: 1114 | BL51: - | BM51: F | BN51: 366 | BO51: 369 | BP51: -
A52: 45155 | B52: 预售+S级 | C52: 无 | F52: =E52-0.35 -> #VALUE! | I52: 21 | J52: =IFERROR(E52/I52,"") | K52: =IFERROR(E52/#REF!,"") | L52: 59163 | M52: - | O52: 4.1 | W52: - | Y52: - | AA52: - | AC52: - | AE52: - | AG52: - | AH52: 3278 | AI52: - | AJ52: 733 | AK52: - | AL52: 88 | AM52: - | AN52: 1517 | AO52: - | AP52: 1220 | AQ52: - | AR52: 191 | AS52: - | AV52: 202 | AX52: 0.048198521 | AY52: #VALUE! | AZ52: 15 | BB52: 0.074257426 | BC52: #DIV/0! | BH52: 1 | BI52: E | BJ52: 58 | BK52: 1104 | BL52: - | BM52: F | BN52: 323 | BO52: 406 | BP52: -
A53: 45156 | B53: S级 | C53: 无 | F53: =E53-1 -> #VALUE! | I53: 14 | J53: =IFERROR(E53/I53,"") | K53: =IFERROR(E53/#REF!,"") | L53: 74289 | M53: - | O53: 5.41 | W53: - | Y53: - | AA53: - | AC53: - | AE53: - | AG53: - | AH53: 4040 | AI53: - | AJ53: 590 | AK53: - | AL53: 85 | AM53: - | AN53: 1360 | AO53: - | AP53: 1293 | AQ53: - | AR53: 869 | AS53: - | AV53: 168 | AX53: 0.035472973 | AY53: #VALUE! | AZ53: 11 | BB53: 0.06547619 | BC53: #DIV/0! | BH53: 1 | BI53: D | BJ53: 38 | BK53: 1475 | BL53: - | BM53: F | BN53: 280 | BO53: 447 | BP53: -
A54: 45157 | B54: A级 | C54: 无 | F54: =E54 | I54: 6 | J54: =IFERROR(E54/I54,"") | K54: =IFERROR(E54/#REF!,"") | L54: 35290 | M54: - | O54: 2.63 | W54: - | Y54: - | AA54: - | AC54: - | AE54: - | AG54: - | AH54: 3751 | AI54: - | AJ54: 367 | AK54: - | AL54: 71 | AM54: - | AN54: 1600 | AO54: - | AP54: 1223 | AQ54: - | AR54: 833 | AS54: - | AV54: 134 | AX54: 0.028743029 | AY54: #VALUE! | AZ54: 8 | BB54: 0.059701493 | BC54: #DIV/0! | BH54: 1 | BI54: E | BJ54: 54 | BK54: 1257 | BL54: - | BM54: F | BN54: 341 | BO54: 401 | BP54: -
A55: 45158 | B55: A级 | C55: 无 | F55: =E55 | I55: 6 | J55: =IFERROR(E55/I55,"") | K55: =IFERROR(E55/#REF!,"") | L55: 47467 | M55: - | O55: 1.7 | W55: - | Y55: - | AA55: - | AC55: - | AE55: - | AG55: - | AH55: 3879 | AI55: - | AJ55: 553 | AK55: - | AL55: 98 | AM55: - | AN55: 1664 | AO55: - | AP55: 1320 | AQ55: - | AR55: 802 | AS55: - | AV55: 148 | AX55: 0.029977719 | AY55: #VALUE! | AZ55: 6 | BB55: 0.040540541 | BC55: #DIV/0! | BH55: 1 | BI55: E | BJ55: 62 | BK55: 1224 | BL55: - | BM55: F | BN55: 370 | BO55: 398 | BP55: -
A56: 45159 | B56: A级 | C56: 无 | F56: =E56-1.4 -> #VALUE! | I56: 8 | J56: =IFERROR(E56/I56,"") | K56: =IFERROR(E56/#REF!,"") | L56: 64664 | M56: - | O56: 2.61 | W56: - | Y56: - | AA56: - | AC56: - | AE56: - | AG56: - | AH56: 4271 | AI56: - | AJ56: 486 | AK56: - | AL56: 76 | AM56: - | AN56: 1579 | AO56: - | AP56: 1618 | AQ56: - | AR56: 835 | AS56: - | AV56: 167 | AX56: 0.032604451 | AZ56: 9 | BB56: 0.053892216 | BH56: 1 | BI56: D | BJ56: 39 | BK56: 1728 | BL56: - | BM56: F | BN56: 233 | BO56: 598 | BP56: -
A57: 45160 | B57: A级 | C57: 无 | F57: =E57-1.7 -> #VALUE! | I57: 0 | J57: =IFERROR(E57/I57,"") | K57: =IFERROR(E57/#REF!,"") | L57: 51867 | M57: - | O57: 2.84 | W57: - | Y57: - | AA57: - | AC57: - | AE57: - | AG57: - | AH57: 3744 | AI57: - | AJ57: 509 | AK57: - | AL57: 72 | AM57: - | AN57: 1511 | AO57: - | AP57: 1281 | AQ57: - | AR57: 826 | AS57: - | AV57: 133 | AX57: 0.028364257 | AZ57: 10 | BB57: 0.07518797 | BH57: 1 | BI57: E | BJ57: 55 | BK57: 1119 | BL57: - | BM57: F | BN57: 385 | BO57: 329 | BP57: - | BV57: 16GD31 | BW57: 16QD31 | BX57: 16QD06W | BY57: 13GD31 | BZ57: 海尔锦绣 | CA57: 海尔云程 | CB57: 13GD32 | CC57: 16QC05 | CD57: 13QD06W | CE57: POP16QC06
A58: 45161 | B58: 预售 | C58: 无 | F58: =E58-2.4 -> #VALUE! | I58: 0 | J58: =IFERROR(E58/I58,"") | K58: =IFERROR(E58/#REF!,"") | L58: 20 | M58: - | O58: 4.2 | W58: - | Y58: - | AA58: - | AC58: - | AE58: - | AG58: - | AH58: 9074 | AI58: - | AJ58: 806 | AK58: - | AL58: 102 | AM58: - | AN58: 1764 | AO58: - | AP58: 1424 | AQ58: - | AR58: 277 | AS58: - | AV58: 146 | AX58: 0.03229374 | AZ58: 14 | BB58: 0.095890411 | BI58: D | BJ58: 43 | BK58: 1393 | BL58: - | BM58: F | BN58: 333 | BO58: 409 | BP58: -
A59: 45162 | B59: 预售+S级 | C59: 无 | F59: =E59 | I59: 22 | J59: =IFERROR(E59/I59,"") | K59: =IFERROR(E59/#REF!,"") | L59: 62382 | M59: - | O59: 3.43 | W59: - | Y59: - | AA59: - | AC59: - | AE59: - | AG59: - | AH59: 9339 | AI59: - | AJ59: 1045 | AK59: - | AL59: 130 | AM59: - | AN59: 1347 | AO59: - | AP59: 1319 | AQ59: - | AR59: 351 | AS59: - | AV59: 168 | AX59: 0.039464412 | AZ59: 8 | BB59: 0.047619048 | BI59: D | BJ59: 39 | BK59: 1557 | BL59: - | BM59: F | BN59: 299 | BO59: 443 | BP59: -
A60: 45163 | B60: S级 | C60: 无 | F60: =E60-0.7 -> #VALUE! | I60: 13 | J60: =IFERROR(E60/I60,"") | K60: =IFERROR(E60/#REF!,"") | L60: 38390 | M60: - | O60: 3.33 | W60: - | Y60: - | AA60: - | AC60: - | AE60: - | AG60: - | AH60: 2919 | AI60: - | AJ60: 613 | AK60: - | AL60: 71 | AM60: - | AN60: 770 | AO60: - | AP60: 1075 | AQ60: - | AR60: 286 | AS60: - | AV60: 130 | AX60: 0.039109507 | AZ60: 9 | BB60: 0.069230769 | BI60: D | BJ60: 50 | BK60: 1296 | BL60: - | BM60: F | BN60: 414 | BO60: 322 | BP60: -
A61: 45164 | B61: A级 | C61: 无 | F61: =E61 | I61: 6 | J61: =IFERROR(E61/I61,"") | K61: =IFERROR(E61/#REF!,"") | L61: 40670 | M61: - | O61: 2.56 | W61: - | Y61: - | AA61: - | AC61: - | AE61: - | AG61: - | AH61: 3333 | AI61: - | AJ61: 493 | AK61: - | AL61: 65 | AM61: - | AN61: 1419 | AO61: - | AP61: 1331 | AQ61: - | AR61: 325 | AS61: - | AV61: 126 | AX61: 0.03081438 | AZ61: 9 | BB61: 0.071428571 | BI61: E | BJ61: 51 | BK61: 1460 | BL61: - | BM61: F | BN61: 340 | BO61: 465 | BP61: -
A62: 45165 | B62: A级 | C62: 无 | F62: =E62-0.3 -> #VALUE! | I62: 6 | J62: =IFERROR(E62/I62,"") | K62: =IFERROR(E62/#REF!,"") | L62: 37986 | M62: - | O62: 4.78 | W62: - | Y62: - | AA62: - | AC62: - | AE62: - | AG62: - | AH62: 3784 | AI62: - | AJ62: 351 | AK62: - | AL62: 87 | AM62: - | AN62: 1345 | AO62: - | AP62: 1555 | AQ62: - | AR62: 337 | AS62: - | AV62: 170 | AX62: 0.039608574 | AZ62: 13 | BB62: 0.076470588 | BI62: D | BJ62: 44 | BK62: 1758 | BL62: - | BM62: F | BN62: 290 | BO62: 549 | BP62: -
A63: 45166 | B63: A级 | C63: 无 | F63: =E63 | I63: 8 | J63: =IFERROR(E63/I63,"") | K63: =IFERROR(E63/#REF!,"") | L63: 40388 | M63: - | O63: 2.51 | W63: - | Y63: - | AA63: - | AC63: - | AE63: - | AG63: - | AH63: 3362 | AI63: - | AJ63: 314 | AK63: - | AL63: 70 | AM63: - | AN63: 1287 | AO63: - | AP63: 1281 | AQ63: - | AR63: 421 | AS63: - | AV63: 125 | AX63: 0.031613556 | AZ63: 6 | BB63: 0.048 | BI63: E | BJ63: 63 | BK63: 1320 | BL63: - | BM63: F | BN63: 404 | BO63: 386 | BP63: -
A64: 45167 | B64: 预售 | C64: 无 | F64: =E64 | I64: 0 | J64: =IFERROR(E64/I64,"") | K64: =IFERROR(E64/#REF!,"") | L64: 5898 | M64: - | O64: 4.63 | W64: - | Y64: - | AA64: - | AC64: - | AE64: - | AG64: - | AH64: 2628 | AI64: - | AJ64: 568 | AK64: - | AL64: 83 | AM64: - | AN64: 1455 | AO64: - | AP64: 1154 | AQ64: - | AR64: 376 | AS64: - | AV64: 147 | AX64: 0.034106729 | AZ64: 16 | BB64: 0.10884354 | BI64: E | BJ64: 68 | BK64: 1153 | BL64: - | BM64: F | BN64: 415 | BO64: 396 | BP64: - | BV64: 16GD31 | BW64: 16QD31 | BX64: 海尔云程 | BY64: 16QD06W | BZ64: 能率16E4 | CA64: 13GD31 | CB64: 海尔锦绣 | CC64: POP16GD32 | CD64: 16QC05 | CE64: 16GD61R
A65: 45168 | B65: 预售 | C65: 无 | F65: =E65 | I65: 0 | J65: =IFERROR(E65/I65,"") | K65: =IFERROR(E65/#REF!,"") | L65: 7798 | M65: - | O65: 4.35 | W65: - | Y65: - | AA65: - | AC65: - | AE65: - | AG65: - | AH65: 2635 | AI65: - | AJ65: 628 | AK65: - | AL65: 95 | AM65: - | AN65: 1310 | AO65: - | AP65: 1234 | AQ65: - | AR65: 350 | AS65: - | AV65: 160 | AX65: 0.037753657 | AZ65: 15 | BB65: 0.09375 | BI65: D | BJ65: 46 | BK65: 1393 | BL65: - | BM65: F | BN65: 365 | BO65: 451 | BP65: -
A66: 45169 | B66: 31号晚8开门红 | C66: 无 | F66: =E66 | I66: 27 | J66: =IFERROR(E66/I66,"") | K66: =IFERROR(E66/#REF!,"") | L66: 74176 | M66: - | O66: 9.1 | W66: - | Y66: - | AA66: - | AC66: - | AE66: - | AG66: - | AH66: 2751 | AI66: - | AJ66: 699 | AK66: - | AL66: 108 | AM66: - | AN66: 873 | AO66: - | AP66: 1261 | AQ66: - | AR66: 318 | AS66: - | AV66: 195 | AX66: 0.04847129 | AZ66: 30 | BB66: 0.15384615 | BI66: D | BJ66: 50 | BK66: 1297 | BL66: - | BM66: F | BN66: 392 | BO66: 418 | BP66: -
A67: 45170 | C67: 无 | F67: =E67 | J67: =IFERROR(E67/I67,"") | K67: =IFERROR(E67/#REF!,"") | L67: 34289 | M67: - | O67: 5.33 | W67: - | Y67: - | AA67: - | AC67: - | AG67: - | AH67: 2550 | AI67: - | AJ67: 470 | AK67: - | AL67: 80 | AM67: - | AN67: 1206 | AO67: - | AP67: 1238 | AQ67: - | AR67: 259 | AS67: - | AV67: 172 | AX67: 0.042989253 | AZ67: 14 | BB67: 0.081395349 | BI67: E | BJ67: 53 | BK67: 1123 | BL67: - | BM67: F | BN67: 428 | BO67: 381 | BP67: -
A68: 45171 | B68: 日销 | C68: 无 | F68: =E68 | J68: =IFERROR(E68/I68,"") | K68: =IFERROR(E68/#REF!,"") | L68: 43069 | M68: - | O68: 5.05 | W68: - | Y68: - | AA68: - | AC68: - | AG68: - | AH68: 2481 | AI68: - | AJ68: 504 | AK68: - | AL68: 111 | AM68: - | AN68: 1466 | AO68: - | AP68: 1157 | AQ68: - | AR68: 264 | AS68: - | AV68: 172 | AX68: 0.041040325 | AZ68: 15 | BB68: 0.087209302 | BI68: E | BJ68: 64 | BK68: 1116 | BL68: - | BM68: F | BN68: 492 | BO68: 342 | BP68: -
A69: 45172 | B69: 预售 | C69: 无 | F69: =E69 | J69: =IFERROR(E69/I69,"") | K69: =IFERROR(E69/#REF!,"") | L69: 8698 | M69: - | O69: 2.54 | W69: - | Y69: - | AA69: - | AC69: - | AG69: - | AH69: 2323 | AI69: - | AJ69: 575 | AK69: - | AL69: 69 | AM69: - | AN69: 1298 | AO69: - | AP69: 899 | AQ69: - | AR69: 313 | AS69: - | AV69: 162 | AX69: 0.041242363 | AZ69: 5 | BB69: 0.030864198 | BI69: E | BJ69: 113 | BK69: 677 | BL69: - | BM69: F | BN69: 660 | BO69: 246 | BP69: -
A70: 45173 | B70: 晚8点 | C70: 无 | F70: =E70 | J70: =IFERROR(E70/I70,"") | K70: =IFERROR(E70/#REF!,"") | L70: 84456 | M70: - | O70: 6.3 | W70: - | Y70: - | AA70: - | AC70: - | AG70: - | AH70: 2294 | AI70: - | AJ70: 551 | AK70: - | AL70: 102 | AM70: - | AN70: 1179 | AO70: - | AP70: 906 | AQ70: - | AR70: 299 | AS70: - | AV70: 157 | AX70: 0.041534392 | AZ70: 20 | BB70: 0.12738854 | BI70: F | BJ70: 109 | BK70: 696 | BL70: - | BM70: F | BN70: 630 | BO70: 237 | BP70: -
A71: 45174 | B71: 预售 | C71: 无 | F71: =E71 | J71: =IFERROR(E71/I71,"") | K71: =IFERROR(E71/#REF!,"") | L71: 21393 | M71: - | O71: 4.18 | W71: - | Y71: - | AA71: - | AC71: - | AG71: - | AH71: 2557 | AI71: - | AJ71: 692 | AK71: - | AL71: 94 | AM71: - | AN71: 1028 | AO71: - | AP71: 1226 | AQ71: - | AR71: 327 | AS71: - | AV71: 165 | AX71: 0.041488559 | AZ71: 12 | BB71: 0.072727273 | BI71: E | BJ71: 60 | BK71: 1174 | BL71: - | BM71: F | BN71: 379 | BO71: 363 | BP71: - | BV71: 16GD31 | BW71: 13GD31 | BX71: 16QD31 | BY71: 海尔锦绣 | BZ71: 16QD06W | CA71: 海尔云程 | CB71: 16QC05 | CC71: 16QC06 | CD71: 小店16C08 | CE71: 13GD32
A72: 45175 | B72: 预售 | C72: 无 | F72: =E72 | J72: =IFERROR(E72/I72,"") | K72: =IFERROR(E72/#REF!,"") | L72: 12107 | M72: - | O72: 5.45 | W72: - | Y72: - | AA72: - | AC72: - | AG72: - | AH72: 2615 | AI72: - | AJ72: 776 | AK72: - | AL72: 135 | AM72: - | AN72: 1122 | AO72: - | AP72: 1176 | AQ72: - | AR72: 344 | AS72: - | AV72: 180 | AX72: 0.043175822 | AZ72: 21 | BB72: 0.11666667 | BI72: E | BJ72: 53 | BK72: 1248 | BL72: - | BM72: F | BN72: 376 | BO72: 356 | BP72: -
A73: 45176 | B73: 7号晚8 | C73: 无 | F73: =E73 | J73: =IFERROR(E73/I73,"") | K73: =IFERROR(E73/#REF!,"") | L73: 79557 | M73: - | O73: 7.77 | W73: - | Y73: - | AA73: - | AC73: - | AG73: - | AH73: 2706 | AI73: - | AJ73: 626 | AK73: - | AL73: 132 | AM73: - | AN73: 941 | AO73: - | AP73: 1251 | AQ73: - | AR73: 390 | AS73: - | AV73: 211 | AX73: 0.053162006 | AZ73: 24 | BB73: 0.11374408 | BI73: E | BJ73: 57 | BK73: 1231 | BL73: - | BM73: F | BN73: 350 | BO73: 381 | BP73: -
A74: 45177 | C74: 无 | F74: =E74 | J74: =IFERROR(E74/I74,"") | K74: =IFERROR(E74/#REF!,"") | L74: 37389 | M74: - | O74: 3.89 | W74: - | Y74: - | AA74: - | AC74: - | AG74: - | AH74: 3292 | AI74: - | AJ74: 555 | AK74: - | AL74: 81 | AM74: - | AN74: 1016 | AO74: - | AP74: 1237 | AQ74: - | AR74: 271 | AS74: - | AV74: 163 | AX74: 0.043817204 | AZ74: 14 | BB74: 0.085889571 | BI74: E | BJ74: 72 | BK74: 1002 | BL74: - | BM74: F | BN74: 441 | BO74: 297 | BP74: -
A75: 45178 | C75: 无 | F75: =E75 | J75: =IFERROR(E75/I75,"") | K75: =IFERROR(E75/#REF!,"") | L75: 38570 | M75: - | O75: 5.11 | W75: - | Y75: - | AA75: - | AC75: - | AG75: - | AH75: 3647 | AI75: - | AJ75: 551 | AK75: - | AL75: 74 | AM75: - | AN75: 1145 | AO75: - | AP75: 1420 | AQ75: - | AR75: 303 | AS75: - | AV75: 171 | AX75: 0.041727672 | AZ75: 17 | BB75: 0.099415205 | BI75: E | BJ75: 74 | BK75: 1163 | BL75: - | BM75: F | BN75: 453 | BO75: 323 | BP75: -
A76: 45179 | B76: 预售 | C76: 无 | F76: =E76 | J76: =IFERROR(E76/I76,"") | K76: =IFERROR(E76/#REF!,"") | L76: 37272 | M76: - | O76: 3.8 | W76: - | Y76: - | AA76: - | AC76: - | AG76: - | AH76: 3568 | AI76: - | AJ76: 496 | AK76: - | AL76: 77 | AM76: - | AN76: 1133 | AO76: - | AP76: 1371 | AQ76: - | AR76: 289 | AS76: - | AV76: 179 | AX76: 0.043915604 | AZ76: 10 | BB76: 0.055865922 | BI76: E | BJ76: 78 | BK76: 1164 | BL76: - | BM76: F | BN76: 360 | BO76: 404 | BP76: -
A77: 45180 | B77: 预售 | C77: 无 | F77: =E77 | J77: =IFERROR(E77/I77,"") | K77: =IFERROR(E77/#REF!,"") | L77: 74579 | M77: - | O77: 4.1 | W77: - | Y77: - | AA77: - | AC77: - | AG77: - | AH77: 2684 | AI77: - | AJ77: 527 | AK77: - | AL77: 80 | AM77: - | AN77: 1015 | AO77: - | AP77: 1351 | AQ77: - | AR77: 317 | AS77: - | AV77: 212 | AX77: 0.053266332 | AZ77: 13 | BB77: 0.061320755 | BI77: E | BJ77: 60 | BK77: 1279 | BL77: - | BM77: F | BN77: 347 | BO77: 376 | BP77: -
A78: 45181 | B78: 预售 | C78: 无 | F78: =E78 | J78: =IFERROR(E78/I78,"") | K78: =IFERROR(E78/#REF!,"") | L78: 28250 | M78: - | O78: 6.05 | W78: - | Y78: - | AA78: - | AC78: - | AG78: - | AH78: 2698 | AI78: - | AJ78: 474 | AK78: - | AL78: 85 | AM78: - | AN78: 1137 | AO78: - | AP78: 1426 | AQ78: - | AR78: 275 | AS78: - | AV78: 184 | AX78: 0.045420884 | AZ78: 14 | BB78: 0.076086957 | BI78: E | BJ78: 59 | BK78: 1204 | BL78: - | BM78: F | BN78: 324 | BO78: 396 | BP78: - | BV78: 16GD31 | BW78: 16QC05 | BX78: 海尔锦绣 | BY78: 13QC05 | BZ78: 16QD31 | CA78: 16QD06W | CB78: 16GD61R | CC78: 13GD31 | CD78: 厂直16QC05+SG | CE78: 小店16C08
A79: 45182 | B79: 预售 | C79: 无 | F79: =E79 | J79: =IFERROR(E79/I79,"") | K79: =IFERROR(E79/#REF!,"") | L79: 13996 | M79: - | O79: 2.63 | W79: - | Y79: - | AA79: - | AC79: - | AG79: - | AH79: 2336 | AI79: - | AJ79: 472 | AK79: - | AL79: 82 | AM79: - | AN79: 825 | AO79: - | AP79: 1177 | AQ79: - | AR79: 233 | AS79: - | AV79: 155 | AX79: 0.045534665 | AZ79: 8 | BB79: 0.051612903 | BI79: E | BJ79: 59 | BK79: 1186 | BL79: - | BM79: F | BN79: 358 | BO79: 369 | BP79: -
A80: 45183 | B80: 晚8点 | C80: 无 | F80: =E80 | J80: =IFERROR(E80/I80,"") | K80: =IFERROR(E80/#REF!,"") | L80: 19594 | M80: - | W80: - | Y80: - | AA80: - | AC80: - | AG80: - | AH80: 2386 | AI80: - | AJ80: 565 | AK80: - | AL80: 77 | AM80: - | AN80: 1134 | AO80: - | AP80: 999 | AQ80: - | AR80: 281 | AS80: - | AV80: 135 | AX80: 0.035386632 | AZ80: 12 | BB80: 0.088888889 | BI80: E | BJ80: 63 | BK80: 1094 | BL80: - | BM80: F | BN80: 451 | BO80: 291 | BP80: -
A81: 45184 | C81: 无 | F81: =E81 | J81: =IFERROR(E81/I81,"") | K81: =IFERROR(E81/#REF!,"") | L81: 64562 | M81: - | W81: - | Y81: - | AA81: - | AC81: - | AG81: - | AH81: 2696 | AI81: - | AJ81: 543 | AK81: - | AL81: 89 | AM81: - | AN81: 1058 | AO81: - | AP81: 1111 | AQ81: - | AR81: 254 | AS81: - | AV81: 190 | AX81: 0.047240179 | AZ81: 27 | BB81: 0.14210526 | BI81: E | BJ81: 67 | BK81: 1047 | BL81: - | BM81: F | BN81: 320 | BO81: 409 | BP81: -
A82: 45185 | B82: 预售 | C82: 无 | F82: =E82 | J82: =IFERROR(E82/I82,"") | K82: =IFERROR(E82/#REF!,"") | L82: 13596 | M82: - | W82: - | Y82: - | AA82: - | AC82: - | AG82: - | AH82: 2735 | AI82: - | AJ82: 564 | AK82: - | AL82: 77 | AM82: - | AN82: 1173 | AO82: - | AP82: 1245 | AQ82: - | AR82: 275 | AS82: - | AV82: 170 | AZ82: 18 | BI82: E | BJ82: 57 | BK82: 1263 | BL82: - | BM82: F | BN82: 300 | BO82: 462 | BP82: -
A83: 45186 | B83: 预售 | C83: 无 | F83: =E83 | J83: =IFERROR(E83/I83,"") | K83: =IFERROR(E83/#REF!,"") | L83: 8408 | M83: - | W83: - | Y83: - | AA83: - | AC83: - | AG83: - | AH83: 2991 | AI83: - | AJ83: 662 | AK83: - | AL83: 113 | AM83: - | AN83: 929 | AO83: - | AP83: 1493 | AQ83: - | AR83: 336 | AS83: - | AV83: 187 | AZ83: 23 | BI83: E | BJ83: 51 | BK83: 1672 | BL83: - | BM83: F | BN83: 265 | BO83: 571 | BP83: -
A84: 45187 | B84: 预售 | C84: 无 | F84: =E84 | J84: =IFERROR(E84/I84,"") | K84: =IFERROR(E84/#REF!,"") | L84: 5499 | M84: - | W84: - | Y84: - | AA84: - | AC84: - | AG84: - | AH84: 3472 | AI84: - | AJ84: 562 | AK84: - | AL84: 104 | AM84: - | AN84: 1131 | AO84: - | AP84: 1319 | AQ84: - | AR84: 322 | AS84: - | AV84: 150 | AZ84: 13 | BI84: F | BJ84: 49 | BK84: 1486 | BL84: - | BM84: F | BN84: 297 | BO84: 467 | BP84: -
A85: 45188 | B85: 晚8点 | C85: 无 | F85: =E85 | J85: =IFERROR(E85/I85,"") | K85: =IFERROR(E85/#REF!,"") | L85: 73988 | M85: - | W85: - | Y85: - | AA85: - | AC85: - | AG85: - | AH85: 3124 | AI85: - | AJ85: 464 | AK85: - | AL85: 102 | AM85: - | AN85: 825 | AO85: - | AP85: 1625 | AQ85: - | AR85: 372 | AS85: - | AV85: 221 | AZ85: 33 | BI85: D | BJ85: 39 | BK85: 1649 | BL85: - | BM85: F | BN85: 243 | BO85: 563 | BP85: -
A86: 45189 | B86: 日销 | C86: 无 | F86: =E86 | J86: =IFERROR(E86/I86,"") | K86: =IFERROR(E86/#REF!,"") | L86: 48085 | M86: - | W86: 1 | Y86: 1 | AA86: 1 | AC86: 67 | AG86: 0 | AH86: 2902 | AI86: - | AJ86: 458 | AK86: - | AL86: 90 | AM86: - | AN86: 851 | AO86: - | AP86: 1334 | AQ86: - | AR86: 289 | AS86: - | AV86: 181 | AZ86: 22 | BI86: E | BJ86: 55 | BK86: 1262 | BL86: - | BM86: F | BN86: 322 | BO86: 428 | BP86: -
A87: 45190 | B87: 预售 | C87: 无 | F87: =E87 | J87: =IFERROR(E87/I87,"") | K87: =IFERROR(E87/#REF!,"") | L87: 21803 | M87: - | W87: 1 | Y87: 1 | AA87: 1 | AC87: 216 | AG87: 0 | AH87: 2709 | AI87: - | AJ87: 483 | AK87: - | AL87: 95 | AM87: - | AN87: 1062 | AO87: - | AP87: 1295 | AQ87: - | AR87: 289 | AS87: - | AV87: 181 | AZ87: 25 | BI87: E | BJ87: 51 | BK87: 1205 | BL87: - | BM87: F | BN87: 401 | BO87: 343 | BP87: -
A88: 45191 | B88: 预售 | C88: 无 | F88: =E88 | J88: =IFERROR(E88/I88,"") | K88: =IFERROR(E88/#REF!,"") | L88: 35271 | M88: - | W88: 1 | Y88: 1 | AA88: 1 | AC88: 300 | AG88: 0 | AH88: 2158 | AI88: - | AJ88: 468 | AK88: - | AL88: 72 | AM88: - | AN88: 1224 | AO88: - | AP88: 837 | AQ88: - | AR88: 230 | AS88: - | AV88: 156 | AZ88: 16 | BI88: E | BJ88: 71 | BK88: 874 | BL88: - | BM88: F | BN88: 463 | BO88: 259 | BP88: -
A89: 45192 | B89: 预售 | C89: 无 | F89: =E89 | J89: =IFERROR(E89/I89,"") | K89: =IFERROR(E89/#REF!,"") | L89: 41788 | M89: - | W89: 6 | Y89: 2 | AA89: 3 | AC89: 250.5 | AG89: 0 | AH89: 2535 | AI89: - | AJ89: 643 | AK89: - | AL89: 67 | AM89: - | AN89: 1195 | AO89: - | AP89: 1111 | AQ89: - | AR89: 325 | AS89: - | AV89: 168 | AZ89: 15 | BI89: E | BJ89: 70 | BK89: 1019 | BL89: - | BM89: F | BN89: 458 | BO89: 297 | BP89: -
A90: 45193 | B90: 晚8点 | C90: 无 | F90: =E90 | J90: =IFERROR(E90/I90,"") | K90: =IFERROR(E90/#REF!,"") | L90: 97354 | M90: - | W90: 3 | Y90: 1 | AA90: 3 | AC90: 53 | AG90: 0 | AH90: 3341 | AI90: - | AJ90: 656 | AK90: - | AL90: 100 | AM90: - | AN90: 888 | AO90: - | AP90: 1516 | AQ90: - | AR90: 386 | AS90: - | AV90: 187 | AZ90: 22 | BI90: E | BJ90: 51 | BK90: 1490 | BL90: - | BM90: F | BN90: 330 | BO90: 489 | BP90: -
A91: 45194 | B91: 日销 | C91: 预售 | F91: =E91 | J91: =IFERROR(E91/I91,"") | K91: =IFERROR(E91/#REF!,"") | L91: 34789 | M91: 0 | W91: 201 | Y91: 76 | AA91: 2.64 | AC91: 109.21 | AG91: 0 | AH91: 3195 | AI91: - | AJ91: 369 | AK91: - | AL91: 98 | AM91: - | AN91: 863 | AO91: - | AP91: 1344 | AQ91: - | AR91: 307 | AS91: - | AV91: 204 | AZ91: 21 | BI91: D | BJ91: 48 | BK91: 1382 | BL91: - | BM91: F | BN91: 345 | BO91: 423 | BP91: -
A92: 45195 | B92: 预售 | C92: 预售 | F92: =E92 | J92: =IFERROR(E92/I92,"") | K92: =IFERROR(E92/#REF!,"") | L92: 16096 | M92: 0 | W92: 383 | Y92: 196 | AA92: 1.95 | AC92: 100.69 | AG92: 0 | AH92: 2386 | AI92: - | AJ92: 378 | AK92: - | AL92: 73 | AM92: - | AN92: 920 | AO92: - | AP92: 1000 | AQ92: - | AR92: 299 | AS92: - | AV92: 145 | AZ92: 0 | BI92: E | BJ92: 83 | BK92: 833 | BL92: - | BM92: F | BN92: 572 | BO92: 242 | BP92: -
A93: 45196 | B93: 预售 | C93: 预售 | F93: =E93 | J93: =IFERROR(E93/I93,"") | K93: =IFERROR(E93/#REF!,"") | L93: 5598 | M93: 0 | W93: 1079 | Y93: 760 | AA93: 1.42 | AC93: 34.97 | AG93: 0 | AH93: 2227 | AI93: - | AJ93: 599 | AK93: - | AL93: 84 | AM93: - | AN93: 1009 | AO93: - | AP93: 914 | AQ93: - | AR93: 211 | AS93: - | AV93: 164 | AZ93: 17 | BI93: E | BJ93: 88 | BK93: 783 | BL93: 145 | BM93: F | BN93: 468 | BO93: 292 | BP93: 22
A94: 45197 | B94: 晚8点 | C94: 预售 | F94: =E94 | J94: =IFERROR(E94/I94,"") | K94: =IFERROR(E94/#REF!,"") | L94: 74658 | M94: 14316 | W94: 1781 | Y94: 863 | AA94: 2.06 | AC94: 68.61 | AG94: 0 | AH94: 2089 | AI94: - | AJ94: 585 | AK94: - | AL94: 70 | AM94: - | AN94: 1289 | AO94: - | AP94: 793 | AQ94: - | AR94: 227 | AS94: - | AV94: 172 | AZ94: 21 | BI94: E | BJ94: 86 | BK94: 681 | BL94: 227 | BM94: F | BN94: 587 | BO94: 203 | BP94: 40
A95: 45198 | B95: 日销 | C95: 预售 | F95: =E95 | J95: =IFERROR(E95/I95,"") | K95: =IFERROR(E95/#REF!,"") | L95: 55199 | M95: 23075 | W95: 3073 | Y95: 1554 | AA95: 1.98 | AC95: 76.64 | AG95: 0 | AH95: 2547 | AI95: - | AJ95: 578 | AK95: - | AL95: 43 | AM95: - | AN95: 695 | AO95: - | AP95: 881 | AQ95: - | AR95: 222 | AS95: - | AV95: 135 | AZ95: 18 | BI95: E | BJ95: 72 | BK95: 921 | BL95: 314 | BM95: F | BN95: 430 | BO95: 357 | BP95: 89
A96: 45199 | B96: 日销 | C96: 晚8点 | F96: =E96 | J96: =IFERROR(E96/I96,"") | K96: =IFERROR(E96/#REF!,"") | L96: 53465 | M96: 33151 | W96: 3543 | Y96: 1747 | AA96: 2.03 | AC96: 71.49 | AG96: 44 | AH96: 4919 | AI96: - | AJ96: 768 | AK96: - | AL96: 69 | AM96: - | AN96: 1376 | AO96: - | AP96: 1244 | AQ96: - | AR96: 291 | AS96: - | AV96: 176 | AZ96: 17 | BI96: E | BJ96: 77 | BK96: 1100 | BL96: 265 | BM96: F | BN96: 444 | BO96: 396 | BP96: 92
A97: 45200 | B97: 日销 | F97: =E97 | J97: =IFERROR(E97/I97,"") | K97: =IFERROR(E97/#REF!,"") | L97: 79704 | M97: 65431 | W97: 1761 | Y97: 825 | AA97: 2.13 | AC97: 71.25 | AG97: 53 | AH97: 3314 | AI97: 454 | AJ97: 555 | AK97: 448 | AL97: 63 | AM97: 3 | AN97: 806 | AO97: 54 | AP97: 1211 | AQ97: 176 | AR97: 325 | AS97: 51 | AV97: 0 | AZ97: 0 | BI97: E | BJ97: 74 | BK97: 1103 | BL97: 219 | BM97: F | BN97: 431 | BO97: 400 | BP97: 77
A98: 45201 | B98: 日销 | F98: =E98 | J98: =IFERROR(E98/I98,"") | K98: =IFERROR(E98/#REF!,"") | L98: 78779 | M98: 7198 | W98: 908 | Y98: 435 | AA98: 2.09 | AC98: 76.01 | AG98: 20 | AH98: 2892 | AI98: 296 | AJ98: 540 | AK98: 165 | AL98: 39 | AM98: 11 | AN98: 845 | AO98: 19 | AP98: 1274 | AQ98: 91 | AR98: 312 | AS98: 41 | AV98: 0 | AZ98: 0 | BI98: E | BJ98: 63 | BK98: 1218 | BL98: 109 | BM98: F | BN98: 431 | BO98: 371 | BP98: 34
A99: 45202 | B99: 日销 | F99: =E99 | J99: =IFERROR(E99/I99,"") | K99: =IFERROR(E99/#REF!,"") | L99: 42489 | M99: 10028 | W99: 867 | Y99: 418 | AA99: 2.07 | AC99: 74.67 | AG99: 34 | AH99: 3117 | AI99: 313 | AJ99: 536 | AK99: 133 | AL99: 54 | AM99: 8 | AN99: 850 | AO99: 8 | AP99: 1408 | AQ99: 110 | AR99: 298 | AS99: 46 | AV99: 0 | AZ99: 0 | BI99: E | BJ99: 62 | BK99: 1255 | BL99: 105 | BM99: F | BN99: 358 | BO99: 430 | BP99: 23
A100: 45203 | B100: 日销 | F100: =E100 | J100: =IFERROR(E100/I100,"") | K100: =IFERROR(E100/#REF!,"") | L100: 66661 | M100: 0 | W100: 635 | Y100: 268 | AA100: 2.37 | AC100: 84.72 | AG100: 23 | AH100: 3271 | AI100: 249 | AJ100: 362 | AK100: 17 | AL100: 81 | AM100: 2 | AN100: 1011 | AO100: 8 | AP100: 1522 | AQ100: 97 | AR100: 310 | AS100: 63 | AV100: 0 | AZ100: 0 | BI100: E | BJ100: 61 | BK100: 1408 | BL100: 110 | BM100: F | BN100: 352 | BO100: 436 | BP100: 24
...

Sheet 单品16QD06W
A1: 7月 sku:100009176306 | D1: 销售出库 | X1: 流量 | AV1: 转化 | BJ1: 京仓现货率 | BK1: 关键词排名 | BS1: 流失分析 | CH1: 负同比每日分析
A2: 日期 | B2: 价格政策 | D2: 销售额 | L2: 模块销售占比 | X2: PV | Z2: UV | AB2: 人均浏览量 | AD2: 平均停留时间 | AF2: 关注人数 | AH2: 加购人数 | AJ2: 站内免费 | AL2: 站内付费 | AN2: 站外免费 | AP2: 站外付费 | AR2: 搜索 | AT2: 内容 | AV2: 店铺转化率 | AX2: 询单 数 | AZ2: 询单 率 | BB2: 询单 成交数 | BD2: 询单 转化 | BF2: 静默成交数 | BH2: 静默转化 | BK2: 燃气热水器 | BO2: 热水器 | BS2: 流量流失 | BX2: 销售流失
B3: Y-23 | C3: Y-22 | D3: Y-23 数量 | E3: Y-23 金额 | F3: 实际销售 | G3: Y-22 金额 | H3: 同比 | I3: 目标 | J3: 达成率 | K3: 类目占比 | L3: Y23推广成交金额 | M3: Y22推广成交金额 | N3: 同比 | O3: 占比 | P3: Y-23 | Q3: Y-22 | R3: 同比 | S3: 占比 | T3: Y-23 | U3: Y-22 | V3: 同比 | W3: 占比 | X3: Y-23 | Y3: Y-22 | Z3: Y-23 | AA3: Y-22 | AB3: Y-23 | AC3: Y-22 | AD3: Y-23 | AE3: Y-22 | AF3: Y-23 | AG3: Y-22 | AH3: Y-23 | AI3: Y-22 | AJ3: Y-23 | AK3: Y-22 | AL3: Y-23 | AM3: Y-22 | AN3: Y-23 | AO3: Y-22 | AP3: Y-23 | AQ3: Y-22 | AR3: Y-23 | AS3: Y-22 | AT3: Y-23 | AU3: Y-22 | AV3: Y-23 | AW3: Y-22 | AX3: Y-23 | AY3: Y-22 | AZ3: Y-23 | BA3: Y-22 | BB3: Y-23 | BC3: Y-22 | BD3: Y-23 | BE3: Y-22 | BF3: Y-23 | BG3: Y-22 | BH3: Y-23 | BI3: Y-22 | BK3: 层级 | BL3: 排名 | BM3: 搜索曝光 | BN3: Y-22搜索曝光 | BO3: 层级 | BP3: 排名 | BQ3: 搜索曝光 | BR3: Y-22搜索曝光 | BS3: TOP 1 | BT3: TOP 2 | BU3: TOP 3 | BV3: TOP 4 | BW3: TOP 5 | BX3: TOP 1 | BY3: TOP 2 | BZ3: TOP 3 | CA3: TOP 4 | CB3: TOP 5 | CC3: TOP 6 | CD3: TOP 7 | CE3: TOP 8 | CF3: TOP 9 | CG3: TOP 10
A4: 填写人员 | B4: 运营 | C4: 运营 | D4: 张超 | E4: 张超 | F4: 运营 | G4: 张超 | H4: 张超 | I4: 张超 | J4: 张超 | K4: 张超 | L4: 推广 | M4: 推广 | N4: 推广 | O4: 推广 | P4: 客服 | Q4: 客服 | R4: 客服 | S4: 客服 | T4: 直播 | U4: 直播 | V4: 直播 | W4: 直播 | X4: 运营 | Y4: 运营 | Z4: 运营 | AA4: 运营 | AB4: 运营 | AC4: 运营 | AD4: 运营 | AE4: 运营 | AF4: 运营 | AG4: 运营 | AH4: 运营 | AI4: 运营 | AJ4: 运营 | AK4: 运营 | AL4: 运营 | AM4: 运营 | AN4: 运营 | AO4: 运营 | AP4: 运营 | AQ4: 运营 | AR4: 运营 | AS4: 运营 | AT4: 运营 | AU4: 运营 | AV4: 客服 | AW4: 客服 | AX4: 客服 | AY4: 客服 | AZ4: 客服 | BA4: 客服 | BB4: 客服 | BC4: 客服 | BD4: 客服 | BE4: 客服 | BF4: 客服 | BG4: 客服 | BH4: 客服 | BI4: 客服 | BJ4: 供应链 | BK4: 运营 | BL4: 运营 | BM4: 运营 | BN4: 运营 | BO4: 运营 | BP4: 运营 | BQ4: 运营 | BR4: 运营 | BS4: 运营 | BT4: 运营 | BU4: 运营 | BV4: 运营 | BW4: 运营 | BX4: 运营 | BY4: 运营 | BZ4: 运营 | CA4: 运营 | CB4: 运营 | CC4: 运营 | CD4: 运营 | CE4: 运营 | CF4: 运营 | CG4: 运营 | CH4: 运营
A5: 45108 | B5: A | C5: 日销 | F5: 4.4791 | G5: 5.612 | H5: =IFERROR(E5/G5-1,"") | I5: 3.5793 | J5: =IFERROR(E5/I5,"") | K5: =IFERROR(E5/#REF!,"") | L5: 66322 | M5: 30203.76 | N5: =L5/M5-1 -> 1.1958193 | T5: 0 | U5: 8967.68 | Y5: 6236 | AA5: 2063 | AC5: 3 | AE5: 84 | AF5: 15 | AG5: 6 | AI5: 102 | AJ5: 1967 | AK5: 1786 | AL5: 595 | AM5: 321 | AN5: 94 | AO5: 74 | AP5: 30 | AQ5: 99 | AR5: 1012 | AS5: 994 | AT5: 156 | AU5: 145 | AV5: 0.0033 | AW5: 0.0126 | BK5: E | BL5: 98 | BM5: 755 | BN5: 998 | BO5: F | BP5: 551 | BQ5: 208 | BR5: 301
A6: 45109 | B6: A | C6: 闪购 | F6: 6.1787 | G6: 9.2912 | H6: =IFERROR(E6/G6-1,"") | I6: 5.2789 | J6: =IFERROR(E6/I6,"") | K6: =IFERROR(E6/#REF!,"") | L6: 22467 | M6: 37991.1 | N6: =L6/M6-1 -> -0.40862465 | T6: 0 | U6: 0 | Y6: 7527 | AA6: 2429 | AC6: 3 | AE6: 89 | AF6: 17 | AG6: 11 | AI6: 97 | AJ6: 2177 | AK6: 2051 | AL6: 632 | AM6: 440 | AN6: 116 | AO6: 69 | AP6: 36 | AQ6: 166 | AR6: 1125 | AS6: 1113 | AT6: 138 | AU6: 153 | AV6: 0.0042 | AW6: 0.0095 | BK6: E | BL6: 77 | BM6: 1074 | BN6: 1299 | BO6: F | BP6: 528 | BQ6: 227 | BR6: 332
A7: 45110 | B7: 预约 | C7: 日销 | F7: 0.8998 | G7: 0.4369 | H7: =IFERROR(E7/G7-1,"") | I7: 0.4499 | J7: =IFERROR(E7/I7,"") | K7: =IFERROR(E7/#REF!,"") | L7: 35146 | M7: 22267 | N7: =L7/M7-1 -> 0.57838955 | T7: 0 | U7: 0 | Y7: 7101 | AA7: 2403 | AC7: 3 | AE7: 89 | AF7: 16 | AG7: 16 | AI7: 113 | AJ7: 1828 | AK7: 2002 | AL7: 504 | AM7: 564 | AN7: 94 | AO7: 83 | AP7: 35 | AQ7: 110 | AR7: 779 | AS7: 1063 | AT7: 175 | AU7: 226 | AV7: 0.0004 | AW7: 0.0029 | BK7: F | BL7: 123 | BM7: 511 | BN7: 1030 | BO7: F | BP7: 855 | BQ7: 106 | BR7: 224 | BX7: 16QD31 | BY7: 16GD31 | BZ7: 海尔锦绣 | CA7: 16GD32 | CB7: POP16QC06 | CC7: 海尔云程 | CD7: 13QD06W | CE7: 海尔致远 | CF7: 能率16E4 | CG7: POP16GD32
A8: 45111 | B8: A | C8: 预约晚8点 | F8: 8.0487 | G8: 9.1474 | H8: =IFERROR(E8/G8-1,"") | I8: 6.699 | J8: =IFERROR(E8/I8,"") | K8: =IFERROR(E8/#REF!,"") | L8: 66870 | M8: 43640.41 | N8: =L8/M8-1 -> 0.53229541 | T8: 4599 | U8: 9198 | Y8: 8376 | AA8: 2942 | AC8: 3 | AE8: 74 | AF8: 18 | AG8: 17 | AI8: 102 | AJ8: 1815 | AK8: 2471 | AL8: 539 | AM8: 613 | AN8: 108 | AO8: 129 | AP8: 31 | AQ8: 102 | AR8: 728 | AS8: 953 | AT8: 172 | AU8: 213 | AV8: 0.0063 | AW8: 0.0095 | BK8: F | BL8: 138 | BM8: 468 | BN8: 835 | BO8: F | BP8: 908 | BQ8: 93 | BR8: 186
A9: 45112 | B9: A | C9: 日销 | F9: 12.0174 | G9: 9.3312 | H9: =IFERROR(E9/G9-1,"") | I9: 9.7679 | J9: =IFERROR(E9/I9,"") | K9: =IFERROR(E9/#REF!,"") | L9: 57174 | M9: 65231 | N9: =L9/M9-1 -> -0.12351489 | T9: 0 | U9: 9198 | Y9: 8309 | AA9: 2767 | AC9: 3 | AE9: 89 | AF9: 21 | AG9: 6 | AI9: 119 | AJ9: 2070 | AK9: 2280 | AL9: 578 | AM9: 587 | AN9: 122 | AO9: 86 | AP9: 20 | AQ9: 187 | AR9: 1051 | AS9: 1155 | AT9: 199 | AU9: 188 | AV9: 0.0084 | AW9: 0.0101 | BJ9: 1 | BK9: E | BL9: 72 | BM9: 872 | BN9: 1213 | BO9: F | BP9: 595 | BQ9: 168 | BR9: 252
A10: 45113 | B10: A | C10: 日销 | F10: 6.9987 | G10: 6.9963 | H10: =IFERROR(E10/G10-1,"") | I10: 6.9987 | J10: =IFERROR(E10/I10,"") | K10: =IFERROR(E10/#REF!,"") | L10: 71395 | M10: 72133.63 | N10: =L10/M10-1 -> -0.010239745 | T10: 0 | U10: 9198 | Y10: 8167 | AA10: 2567 | AC10: 3 | AE10: 89 | AF10: 8 | AG10: 9 | AI10: 127 | AJ10: 2020 | AK10: 2094 | AL10: 523 | AM10: 672 | AN10: 87 | AO10: 74 | AP10: 26 | AQ10: 143 | AR10: 1091 | AS10: 1177 | AT10: 164 | AU10: 199 | AV10: 0.0059 | AW10: 0.0086 | BJ10: 1 | BK10: E | BL10: 80 | BM10: 738 | BN10: 1133 | BO10: F | BP10: 444 | BQ10: 242 | BR10: 594
A11: 45114 | B11: A | C11: 预约晚8点 | F11: 7.2385 | G11: 5.1525 | H11: =IFERROR(E11/G11-1,"") | I11: 6.3387 | J11: =IFERROR(E11/I11,"") | K11: =IFERROR(E11/#REF!,"") | L11: 34694 | M11: 109910.41 | N11: =L11/M11-1 -> -0.68434291 | T11: 4599 | U11: 24295 | Y11: 6666 | AA11: 2209 | AC11: 3 | AE11: 91 | AF11: 15 | AG11: 14 | AI11: 95 | AJ11: 1918 | AK11: 1730 | AL11: 589 | AM11: 598 | AN11: 102 | AO11: 72 | AP11: 27 | AQ11: 137 | AR11: 966 | AS11: 891 | AT11: 143 | AU11: 184 | AV11: 0.006 | AW11: 0.0081 | BJ11: 1 | BK11: E | BL11: 87 | BM11: 704 | BN11: 616 | BO11: F | BP11: 559 | BQ11: 164 | BR11: 137
A12: 45115 | B12: A | C12: 日销 | F12: 7.9283 | G12: 3.9395 | H12: =IFERROR(E12/G12-1,"") | I12: 7.9283 | J12: =IFERROR(E12/I12,"") | K12: =IFERROR(E12/#REF!,"") | L12: 26553 | M12: 67231 | N12: =L12/M12-1 -> -0.60504827 | T12: 0 | U12: 0 | Y12: 6390 | AA12: 2093 | AC12: 3 | AE12: 86 | AF12: 14 | AG12: 5 | AI12: 89 | AJ12: 2212 | AK12: 1699 | AL12: 665 | AM12: 490 | AN12: 103 | AO12: 72 | AP12: 37 | AQ12: 143 | AR12: 1162 | AS12: 861 | AT12: 196 | AU12: 156 | AV12: 0.0064 | AW12: 0.0072 | BK12: E | BL12: 82 | BM12: 868 | BN12: 490 | BO12: F | BP12: 405 | BQ12: 274 | BR12: 146
A13: 45116 | B13: 预约 | C13: 日销 | F13: 1.7996 | G13: 6.3287 | H13: =IFERROR(E13/G13-1,"") | I13: 0 | J13: =IFERROR(E13/I13,"") | K13: =IFERROR(E13/#REF!,"") | L13: 20946 | M13: 46280 | N13: =L13/M13-1 -> -0.54740709 | T13: 0 | U13: 10498 | Y13: 7875 | AA13: 2918 | AC13: 3 | AE13: 77 | AF13: 7 | AG13: 12 | AI13: 94 | AJ13: 1818 | AK13: 2413 | AL13: 648 | AM13: 669 | AN13: 69 | AO13: 79 | AP13: 39 | AQ13: 146 | AR13: 822 | AS13: 899 | AT13: 200 | AU13: 178 | AV13: 0 | AW13: 0.0055 | BK13: F | BL13: 166 | BM13: 433 | BN13: 517 | BO13: F | BP13: 867 | BQ13: 113 | BR13: 141
A14: 45117 | B14: 预约 | C14: 预约 | F14: 3.5093 | G14: 7.3584 | H14: =IFERROR(E14/G14-1,"") | I14: 0.36 | J14: =IFERROR(E14/I14,"") | K14: =IFERROR(E14/#REF!,"") | L14: 48295 | M14: 40511 | N14: =L14/M14-1 -> 0.19214534 | T14: 4499 | U14: 9198 | Y14: 10055 | AA14: 3177 | AC14: 3 | AE14: 88 | AF14: 12 | AG14: 16 | AI14: 165 | AJ14: 1187 | AK14: 2667 | AL14: 555 | AM14: 638 | AN14: 65 | AO14: 101 | AP14: 27 | AQ14: 200 | AR14: 360 | AS14: 1403 | AT14: 126 | AU14: 237 | AV14: 0.0006 | AW14: 0.0054 | BJ14: 1 | BK14: F | BL14: 402 | BM14: 143 | BN14: 1368 | BO14: F | BP14: 1343 | BQ14: 50 | BR14: 377
A15: 45118 | B15: A | C15: 预约+闪购 | F15: 7.6384 | G15: 1.7496 | H15: =IFERROR(E15/G15-1,"") | I15: 7.6384 | J15: =IFERROR(E15/I15,"") | K15: =IFERROR(E15/#REF!,"") | L15: 61287 | M15: 27168 | N15: =L15/M15-1 -> 1.2558525 | T15: 4599 | U15: 9198 | Y15: 8412 | AA15: 2651 | AC15: 3 | AE15: 93 | AF15: 3 | AG15: 11 | AI15: 134 | AJ15: 1331 | AK15: 2081 | AL15: 641 | AM15: 681 | AN15: 61 | AO15: 107 | AP15: 19 | AQ15: 196 | AR15: 479 | AS15: 1073 | AT15: 172 | AU15: 193 | AV15: 0.0049 | AW15: 0.0045 | BK15: F | BL15: 303 | BM15: 213 | BN15: 663 | BO15: F | BP15: 1025 | BQ15: 82 | BR15: 136 | BX15: 16QD31 | BY15: 16GD31 | BZ15: 厂直16QD06W | CA15: 卡萨帝16CJS | CB15: 能率16E4 | CC15: 海尔云程 | CD15: 16QC05 | CE15: 16GD61R | CF15: 16GD32 | CG15: 能率16V36A
A16: 45119 | B16: A | C16: 晚8点 | F16: 6.6687 | G16: 21.9262 | H16: =IFERROR(E16/G16-1,"") | I16: 9.9 | J16: =IFERROR(E16/I16,"") | K16: =IFERROR(E16/#REF!,"") | L16: 28081 | M16: 115133 | N16: =L16/M16-1 -> -0.75609947 | T16: 0 | U16: 15097 | Y16: 7974 | AA16: 2547 | AC16: 3 | AE16: 96 | AF16: 14 | AG16: 13 | AI16: 113 | AJ16: 1756 | AK16: 2070 | AL16: 619 | AM16: 597 | AN16: 84 | AO16: 122 | AP16: 43 | AQ16: 190 | AR16: 800 | AS16: 978 | AT16: 157 | AU16: 181 | AV16: 0.0049 | AW16: 0.0192 | BJ16: 1 | BK16: F | BL16: 151 | BM16: 441 | BN16: 602 | BO16: F | BP16: 782 | BQ16: 127 | BR16: 143
A17: 45120 | B17: A | F17: 7.7783 | G17: 8.5214 | H17: =IFERROR(E17/G17-1,"") | I17: 8.1 | J17: =IFERROR(E17/I17,"") | K17: =IFERROR(E17/#REF!,"") | L17: 51088 | M17: 60676 | N17: =L17/M17-1 -> -0.15801965 | T17: 18396 | U17: 0 | Y17: 7110 | AA17: 2430 | AC17: 3 | AE17: 89 | AF17: 12 | AG17: 12 | AI17: 114 | AJ17: 1667 | AK17: 2015 | AL17: 379 | AM17: 523 | AN17: 119 | AO17: 85 | AP17: 36 | AQ17: 170 | AR17: 769 | AS17: 1093 | AT17: 154 | AU17: 150 | AV17: 0.0065 | AW17: 0.0103 | BJ17: 0.6 | BK17: F | BL17: 140 | BM17: 484 | BN17: 756 | BO17: F | BP17: 775 | BQ17: 121 | BR17: 193
A18: 45121 | B18: 预约 | C18: 预约晚8点 | F18: 6.6487 | G18: 4.5306 | H18: =IFERROR(E18/G18-1,"") | I18: 0 | J18: =IFERROR(E18/I18,"") | K18: =IFERROR(E18/#REF!,"") | L18: 41905 | M18: 68425 | N18: =L18/M18-1 -> -0.38757764 | T18: ？ | U18: 0 | Y18: 7560 | AA18: 2384 | AC18: 3 | AE18: 91 | AF18: 6 | AG18: 9 | AI18: 92 | AJ18: 1540 | AK18: 1933 | AL18: 413 | AM18: 608 | AN18: 87 | AO18: 86 | AP18: 47 | AQ18: 113 | AR18: 693 | AS18: 995 | AT18: 157 | AU18: 169 | AV18: 0.0048 | AW18: 0.0063 | BJ18: 0.6 | BK18: F | BL18: 174 | BM18: 396 | BN18: 562 | BO18: F | BP18: 685 | BQ18: 154 | BR18: 150
A19: 45122 | B19: 预约 | C19: 日销 | F19: 1.7996 | G19: 24.4865 | H19: =IFERROR(E19/G19-1,"") | I19: 0 | J19: =IFERROR(E19/I19,"") | K19: =IFERROR(E19/#REF!,"") | L19: 16725 | M19: 96312 | N19: =L19/M19-1 -> -0.82634563 | T19: 0 | U19: 0 | Y19: 8587 | AA19: 3221 | AC19: 3 | AE19: 78 | AF19: 16 | AG19: 20 | AI19: 110 | AJ19: 1448 | AK19: 2755 | AL19: 729 | AM19: 548 | AN19: 114 | AO19: 89 | AP19: 39 | AQ19: 209 | AR19: 573 | AS19: 1152 | AT19: 134 | AU19: 220 | AV19: 0.0005 | AW19: 0.0112 | BK19: F | BL19: 234 | BM19: 310 | BN19: 1147 | BO19: F | BP19: 980 | BQ19: 92 | BR19: 258
A20: 45123 | B20: S | C20: 日销 | F20: 7.7583 | G20: 6.2986 | H20: =IFERROR(E20/G20-1,"") | I20: 25.2 | J20: =IFERROR(E20/I20,"") | K20: =IFERROR(E20/#REF!,"") | L20: 23115 | M20: 57649 | N20: =L20/M20-1 -> -0.59903901 | T20: 0 | U20: 0 | Y20: 8414 | AA20: 2824 | AC20: 3 | AE20: 85 | AF20: 16 | AG20: 17 | AI20: 103 | AJ20: 1548 | AK20: 2332 | AL20: 784 | AM20: 661 | AN20: 83 | AO20: 80 | AP20: 36 | AQ20: 137 | AR20: 619 | AS20: 1301 | AT20: 176 | AU20: 168 | AV20: 0.0051 | AW20: 0.0067 | BK20: F | BL20: 280 | BM20: 274 | BN20: 1214 | BO20: F | BP20: 1588 | BQ20: 82 | BR20: 270
A21: 45124 | B21: S | C21: 预约 | F21: 2.7594 | G21: 0.3938 | H21: =IFERROR(E21/G21-1,"") | I21: 16.2 | J21: =IFERROR(E21/I21,"") | K21: =IFERROR(E21/#REF!,"") | L21: 53238 | M21: 11551 | N21: =L21/M21-1 -> 3.6089516 | T21: 0 | U21: 4599 | Y21: 7654 | AA21: 2641 | AC21: 3 | AE21: 86 | AF21: 8 | AG21: 16 | AI21: 124 | AJ21: 1844 | AK21: 2118 | AL21: 578 | AM21: 720 | AN21: 102 | AO21: 89 | AP21: 49 | AQ21: 127 | AR21: 785 | AS21: 1112 | AT21: 170 | AU21: 186 | AV21: 0.0026 | AW21: 0.0027 | BJ21: 0.9 | BK21: F | BL21: 163 | BM21: 402 | BN21: 719 | BO21: F | BP21: 1105 | BQ21: 130 | BR21: 146
A22: 45125 | B22: A | C22: 预约 | F22: 8.0384 | G22: 0 | H22: =IFERROR(E22/G22-1,"") | I22: 8.1 | J22: =IFERROR(E22/I22,"") | K22: =IFERROR(E22/#REF!,"") | L22: 126981 | M22: 23970 | N22: =L22/M22-1 -> 4.2974969 | T22: 0 | U22: 4599 | Y22: 7806 | AA22: 2556 | AC22: 3 | AE22: 90 | AF22: 10 | AG22: 12 | AI22: 92 | AJ22: 1824 | AK22: 2019 | AL22: 594 | AM22: 660 | AN22: 94 | AO22: 104 | AP22: 37 | AQ22: 163 | AR22: 925 | AS22: 880 | AT22: 122 | AU22: 169 | AV22: 0.0057 | AW22: 0.002 | BJ22: 0.9 | BK22: F | BL22: 113 | BM22: 529 | BN22: 559 | BO22: F | BP22: 824 | BQ22: 139 | BR22: 120 | BX22: 16GD32 | BY22: 16GD31 | BZ22: 16QD31 | CA22: POP16QC06 | CB22: 卡萨帝16CJS | CC22: 海尔云程 | CD22: 厂直16QD06W | CE22: 能率16V36A | CF22: 海尔致远 | CG22: 16GD61R
A23: 45126 | B23: A | C23: 晚8点 | F23: 7.686 | G23: 21.8236 | H23: =IFERROR(E23/G23-1,"") | I23: 8.1 | J23: =IFERROR(E23/I23,"") | K23: =IFERROR(E23/#REF!,"") | L23: 43248 | M23: 251962 | N23: =L23/M23-1 -> -0.82835507 | T23: 0 | U23: 25856 | Y23: 11132 | AA23: 3913 | AC23: 3 | AE23: 78 | AF23: 12 | AG23: 12 | AI23: 146 | AJ23: 1927 | AK23: 3287 | AL23: 612 | AM23: 661 | AN23: 147 | AO23: 106 | AP23: 40 | AQ23: 332 | AR23: 963 | AS23: 1336 | AT23: 119 | AU23: 259 | AV23: 0.007 | AW23: 0.023 | BJ23: 0.9 | BK23: F | BL23: 112 | BM23: 556 | BN23: 1262 | BO23: F | BP23: 929 | BQ23: 127 | BR23: 281
A24: 45127 | B24: 0点预约 | F24: 5.399 | G24: 7.7493 | H24: =IFERROR(E24/G24-1,"") | I24: 15.3 | J24: =IFERROR(E24/I24,"") | K24: =IFERROR(E24/#REF!,"") | L24: 594040 | M24: 198620 | N24: =L24/M24-1 -> 1.9908368 | T24: 10298 | U24: 4599 | Y24: 10262 | AA24: 3453 | AC24: 3 | AE24: 87 | AF24: 10 | AG24: 26 | AI24: 146 | AJ24: 1739 | AK24: 2839 | AL24: 603 | AM24: 693 | AN24: 88 | AO24: 145 | AP24: 36 | AQ24: 257 | AR24: 864 | AS24: 1377 | AT24: 95 | AU24: 252 | AV24: 0.0037 | AW24: 0.0185 | BJ24: 0.9 | BK24: F | BL24: 135 | BM24: 440 | BN24: 1391 | BO24: F | BP24: 879 | BQ24: 107 | BR24: 285
A25: 45128 | B25: A | C25: 日销+闪购 | F25: 8.0585 | G25: 8.4485 | H25: =IFERROR(E25/G25-1,"") | I25: 11.7 | J25: =IFERROR(E25/I25,"") | K25: =IFERROR(E25/#REF!,"") | L25: 148057 | M25: 109517 | N25: =L25/M25-1 -> 0.35190884 | T25: 4599 | U25: 0 | Y25: 8779 | AA25: 2978 | AC25: 3 | AE25: 87 | AF25: 16 | AG25: 20 | AI25: 137 | AJ25: 1621 | AK25: 2490 | AL25: 480 | AM25: 543 | AN25: 101 | AO25: 163 | AP25: 945 | AQ25: 216 | AR25: 803 | AS25: 1244 | AT25: 84 | AU25: 199 | AV25: 0.0049 | AW25: 0.0185 | BJ25: 0.9 | BK25: F | BL25: 137 | BM25: 432 | BN25: 1245 | BO25: F | BP25: 702 | BQ25: 139 | BR25: 276
A26: 45129 | B26: A | C26: 预约 | F26: 4.8166 | G26: 1.6877 | H26: =IFERROR(E26/G26-1,"") | I26: 8.1 | J26: =IFERROR(E26/I26,"") | K26: =IFERROR(E26/#REF!,"") | L26: 25675 | M26: 244266 | N26: =L26/M26-1 -> -0.89488918 | T26: 0 | U26: 0 | Y26: 7125 | AA26: 2555 | AC26: 3 | AE26: 88 | AF26: 12 | AG26: 13 | AI26: 103 | AJ26: 1656 | AK26: 2003 | AL26: 513 | AM26: 610 | AN26: 69 | AO26: 160 | AP26: 1395 | AQ26: 163 | AR26: 800 | AS26: 939 | AT26: 71 | AU26: 173 | AV26: 0.003 | AW26: 0.0215 | BK26: F | BL26: 136 | BM26: 474 | BN26: 670 | BO26: F | BP26: 706 | BQ26: 159 | BR26: 146
A27: 45130 | B27: A | C27: 预约 | F27: 4.1191 | G27: 1.7997 | H27: =IFERROR(E27/G27-1,"") | I27: 8.1 | J27: =IFERROR(E27/I27,"") | K27: =IFERROR(E27/#REF!,"") | L27: 29194 | M27: 9092 | N27: =L27/M27-1 -> 2.2109547 | T27: 0 | U27: 0 | Y27: 6362 | AA27: 2309 | AC27: 3 | AE27: 83 | AF27: 14 | AG27: 17 | AI27: 83 | AJ27: 1819 | AK27: 1804 | AL27: 557 | AM27: 638 | AN27: 80 | AO27: 84 | AP27: 2890 | AQ27: 124 | AR27: 863 | AS27: 850 | AT27: 98 | AU27: 162 | AV27: 0.0016 | AW27: 0.0061 | BK27: F | BL27: 153 | BM27: 469 | BN27: 577 | BO27: F | BP27: 734 | BQ27: 150 | BR27: 119
A28: 45131 | B28: 0点预约 | C28: 晚8点 | F28: 7.5588 | G28: 17.9363 | H28: =IFERROR(E28/G28-1,"") | I28: 16.2 | J28: =IFERROR(E28/I28,"") | K28: =IFERROR(E28/#REF!,"") | L28: 46731 | M28: 127443 | N28: =L28/M28-1 -> -0.63331842 | T28: 13800 | U28: 32795 | Y28: 9615 | AA28: 2704 | AC28: 4 | AE28: 102 | AF28: 20 | AG28: 24 | AI28: 135 | AJ28: 1712 | AK28: 2170 | AL28: 664 | AM28: 645 | AN28: 96 | AO28: 124 | AP28: 2415 | AQ28: 183 | AR28: 704 | AS28: 979 | AT28: 120 | AU28: 223 | AV28: 0.0027 | AW28: 0.0185 | BJ28: 0.7 | BK28: F | BL28: 200 | BM28: 321 | BN28: 728 | BO28: F | BP28: 918 | BQ28: 101 | BR28: 205
A29: 45132 | B29: A | F29: 5.5791 | G29: 12.5385 | H29: =IFERROR(E29/G29-1,"") | I29: 12.6 | J29: =IFERROR(E29/I29,"") | K29: =IFERROR(E29/#REF!,"") | L29: 77503 | M29: 76923 | N29: =L29/M29-1 -> 0.0075400075 | T29: 0 | U29: 8998 | Y29: 7789 | AA29: 2570 | AC29: 3 | AE29: 90 | AF29: 15 | AG29: 11 | AI29: 121 | AJ29: 1877 | AK29: 2062 | AL29: 669 | AM29: 542 | AN29: 111 | AO29: 110 | AP29: 3213 | AQ29: 197 | AR29: 829 | AS29: 973 | AT29: 124 | AU29: 191 | AV29: 0.0015 | AW29: 0.0125 | BJ29: 0.95 | BK29: F | BL29: 156 | BM29: 391 | BN29: 891 | BO29: F | BP29: 823 | BQ29: 115 | BR29: 247 | BX29: 16GD32 | BY29: 16GD31 | BZ29: 五星16QC06 | CA29: 16QD31 | CB29: 海尔致远 | CC29: 海尔云程 | CD29: 能率16E4 | CE29: 13QD06W | CF29: 13GD31 | CG29: 海尔锦绣
A30: 45133 | B30: A | C30: 日销 | F30: 4.599 | G30: 0.9298 | H30: =IFERROR(E30/G30-1,"") | I30: 7.2 | J30: =IFERROR(E30/I30,"") | K30: =IFERROR(E30/#REF!,"") | L30: 24595 | M30: 27597 | N30: =L30/M30-1 -> -0.10877994 | T30: 0 | U30: 4499 | Y30: 7265 | AA30: 2450 | AC30: 3 | AE30: 86 | AF30: 19 | AG30: 23 | AI30: 105 | AJ30: 2089 | AK30: 1905 | AL30: 687 | AM30: 658 | AN30: 99 | AO30: 87 | AP30: 1269 | AQ30: 181 | AR30: 1048 | AS30: 834 | AT30: 107 | AU30: 184 | AV30: 0.0027 | AW30: 0.0033 | BK30: F | BL30: 127 | BM30: 470 | BN30: 558 | BO30: F | BP30: 709 | BQ30: 140 | BR30: 110
A31: 45134 | B31: A | C31: 日销 | F31: 8.1684 | G31: 13.527 | H31: =IFERROR(E31/G31-1,"") | I31: 9 | J31: =IFERROR(E31/I31,"") | K31: =IFERROR(E31/#REF!,"") | L31: 40990 | M31: 63502 | N31: =L31/M31-1 -> -0.35450852 | T31: 0 | U31: 19296 | Y31: 9864 | AA31: 3660 | AC31: 3 | AE31: 76 | AF31: 19 | AG31: 14 | AI31: 123 | AJ31: 1912 | AK31: 3132 | AL31: 753 | AM31: 643 | AN31: 92 | AO31: 148 | AP31: 1368 | AQ31: 174 | AR31: 997 | AS31: 977 | AT31: 105 | AU31: 223 | AV31: 0.004 | AW31: 0.0082 | BJ31: 0.95 | BK31: F | BL31: 110 | BM31: 500 | BN31: 774 | BO31: F | BP31: 658 | BQ31: 154 | BR31: 155
A32: 45135 | B32: A | C32: 日销 | F32: 10.1634 | G32: 6.9193 | H32: =IFERROR(E32/G32-1,"") | I32: 9 | J32: =IFERROR(E32/I32,"") | K32: =IFERROR(E32/#REF!,"") | L32: 38629 | M32: 47601 | N32: =L32/M32-1 -> -0.18848344 | T32: 5699 | U32: 8998 | Y32: 8805 | AA32: 2820 | AC32: 3 | AE32: 86 | AF32: 7 | AG32: 18 | AI32: 139 | AJ32: 1815 | AK32: 2272 | AL32: 490 | AM32: 600 | AN32: 129 | AO32: 117 | AP32: 1930 | AQ32: 220 | AR32: 905 | AS32: 1101 | AT32: 106 | AU32: 195 | AV32: 0.0053 | AW32: 0.0053 | BJ32: 0.95 | BK32: F | BL32: 120 | BM32: 474 | BN32: 1008 | BO32: F | BP32: 665 | BQ32: 151 | BR32: 287
A33: 45136 | B33: 预售 | C33: 预约 | F33: 0.72 | G33: 1.4802 | H33: =IFERROR(E33/G33-1,"") | I33: 0 | J33: =IFERROR(E33/I33,"") | K33: =IFERROR(E33/#REF!,"") | L33: 27693 | M33: 23481 | N33: =L33/M33-1 -> 0.17937907 | T33: 0 | U33: 0 | Y33: 6305 | AA33: 2182 | AC33: 3 | AE33: 85 | AF33: 21 | AG33: 15 | AI33: 82 | AJ33: 1917 | AK33: 1710 | AL33: 715 | AM33: 541 | AN33: 87 | AO33: 93 | AP33: 2232 | AQ33: 167 | AR33: 833 | AS33: 797 | AT33: 170 | AU33: 166 | AV33: 0.0002 | AW33: 0.0027 | BK33: F | BL33: 171 | BM33: 377 | BN33: 520 | BO33: F | BP33: 962 | BQ33: 100 | BR33: 104
A34: 45137 | B34: 预售 | C34: 预约 | F34: 0 | G34: 1.4356 | H34: =IFERROR(E34/G34-1,"") | I34: 0 | J34: =IFERROR(E34/I34,"") | K34: =IFERROR(E34/#REF!,"") | L34: 27589 | M34: 24651 | N34: =L34/M34-1 -> 0.11918381 | P34: 109.6808 | R34: / | S34: 0.0104 | T34: 0 | U34: 0 | Y34: 6959 | AA34: 2463 | AC34: 3 | AE34: 85 | AF34: 17 | AG34: 20 | AI34: 89 | AJ34: 2173 | AK34: 1840 | AL34: 856 | AM34: 745 | AN34: 119 | AO34: 79 | AP34: 2475 | AQ34: 182 | AR34: 1021 | AS34: 900 | AT34: 160 | AU34: 192 | AV34: 0 | AW34: 0.0045 | AX34: 0 | AY34: 139 | BB34: 0 | BC34: 14 | BD34: 0 | BE34: 0.1007 | BJ34: 0.95 | BK34: F | BL34: 137 | BM34: 502 | BN34: 558 | BO34: F | BP34: 827 | BQ34: 120 | BR34: 143
A35: 45138 | B35: 限时 | C35: 预约晚8点 | F35: =E35 | G35: 24.9305 | H35: =IFERROR(E35/G35-1,"") | I35: 27 | J35: =IFERROR(E35/I35,"") | K35: =IFERROR(E35/#REF!,"") | L35: 48577 | M35: 162894 | N35: =L35/M35-1 -> -0.70178767 | T35: 18396 | U35: 32193 | Y35: 9633 | AA35: 2900 | AC35: 3 | AE35: 96 | AF35: 13 | AG35: 26 | AI35: 119 | AJ35: 2168 | AK35: 2623 | AL35: 807 | AM35: 509 | AN35: 114 | AO35: 145 | AP35: 1601 | AQ35: 147 | AR35: 949 | AS35: 1250 | AT35: 125 | AU35: 253 | AV35: 0.0102 | AW35: 0.0217 | BJ35: 0.95 | BK35: F | BL35: 146 | BM35: 483 | BN35: 693 | BO35: F | BP35: 785 | BQ35: 133 | BR35: 150
A36: 45139 | B36: S级 | C36: 日销 | F36: =E36 | G36: 13.787865 | H36: =IFERROR(E36/G36-1,"") | I36: 14 | J36: =IFERROR(E36/I36,"") | K36: =IFERROR(E36/#REF!,"") | L36: 244332 | M36: 147010 | N36: =L36/M36-1 -> 0.66200939 | P36: 0.89 | Y36: 10194 | AA36: 3561 | AC36: 3 | AE36: 81 | AF36: 9 | AG36: 13 | AI36: 160 | AJ36: 3088 | AK36: 3051 | AL36: 664 | AM36: 618 | AN36: 131 | AO36: 143 | AP36: 2415 | AQ36: 185 | AR36: 1179 | AS36: 1210 | AT36: 140 | AU36: 203 | AV36: 0.005371187 | AX36: 20 | AY36: 136 | AZ36: 0.0038 | BA36: 0.026 | BJ36: 0.95 | BK36: F | BL36: 96 | BM36: 715 | BN36: 932 | BO36: F | BP36: 1219 | BQ36: 69 | BR36: 259 | BX36: 16GD31 | BY36: 16GD32 | BZ36: 13QD06W | CA36: 海尔云程 | CB36: 16QD31 | CC36: 13GD31 | CD36: 海尔锦绣 | CE36: 16QD06* | CF36: 能率16E4 | CG36: 16GD61R
A37: 45140 | B37: A级 | C37: 预约 | F37: =E37-2.7 -> #VALUE! | G37: 2.3344 | H37: =IFERROR(E37/G37-1,"") | I37: 8 | J37: =IFERROR(E37/I37,"") | K37: =IFERROR(E37/#REF!,"") | L37: 101149 | M37: 43528.55 | N37: =L37/M37-1 -> 1.3237392 | Y37: 7157 | AA37: 2491 | AC37: 3 | AE37: 85 | AF37: 10 | AG37: 13 | AI37: 107 | AJ37: 2933 | AK37: 2014 | AL37: 516 | AM37: 587 | AN37: 126 | AO37: 105 | AP37: 1425 | AQ37: 120 | AR37: 1087 | AS37: 940 | AT37: 135 | AU37: 176 | BJ37: 0.9 | BK37: E | BL37: 84 | BM37: 775 | BN37: 597 | BO37: F | BP37: 586 | BQ37: 193 | BR37: 148 | CE37: 16QD06* | CF37: 能率16E4
A38: 45141 | B38: A级 | C38: 预约晚8点 | F38: =E38-2.7 -> #VALUE! | G38: 11.9358 | H38: =IFERROR(E38/G38-1,"") | I38: 7 | J38: =IFERROR(E38/I38,"") | K38: =IFERROR(E38/#REF!,"") | L38: 40190 | M38: 117806 | N38: =L38/M38-1 -> -0.6588459 | Y38: 7467 | AA38: 2413 | AC38: 3 | AE38: 100 | AF38: 18 | AG38: 9 | AI38: 126 | AJ38: 2932 | AK38: 1939 | AL38: 573 | AM38: 624 | AN38: 95 | AO38: 101 | AP38: 2049 | AQ38: 126 | AR38: 1065 | AS38: 901 | AT38: 127 | AU38: 181 | BJ38: 0.9 | BK38: F | BL38: 126 | BM38: 535 | BN38: 491 | BO38: F | BP38: 611 | BQ38: 180 | BR38: 124 | CE38: 16QD06* | CF38: 能率16E4
A39: 45142 | B39: A级 | C39: 日销 | F39: =E39-2.7 -> #VALUE! | G39: 11.1676 | H39: =IFERROR(E39/G39-1,"") | I39: 9 | J39: =IFERROR(E39/I39,"") | K39: =IFERROR(E39/#REF!,"") | L39: 35181 | M39: 34099 | N39: =L39/M39-1 -> 0.031731136 | Y39: 6851 | AA39: 2371 | AC39: 3 | AE39: 80 | AF39: 15 | AG39: 10 | AI39: 102 | AJ39: 3000 | AK39: 1925 | AL39: 620 | AM39: 544 | AN39: 92 | AO39: 116 | AP39: 1607 | AQ39: 114 | AR39: 1169 | AS39: 875 | AT39: 143 | AU39: 170 | BJ39: 0.9 | BK39: F | BL39: 111 | BM39: 589 | BN39: 731 | BO39: F | BP39: 637 | BQ39: 168 | BR39: 137 | CE39: 16QD06* | CF39: 能率16E4
A40: 45143 | B40: 预售 | C40: 预约 | F40: =E40 | G40: 0.8298 | H40: =IFERROR(E40/G40-1,"") | I40: 0 | J40: =IFERROR(E40/I40,"") | K40: =IFERROR(E40/#REF!,"") | L40: 8999 | M40: 9401 | N40: =L40/M40-1 -> -0.042761408 | Y40: 5905 | AA40: 2177 | AC40: 3 | AE40: 86 | AF40: 21 | AG40: 16 | AI40: 98 | AJ40: 3522 | AK40: 1652 | AL40: 739 | AM40: 680 | AN40: 95 | AO40: 109 | AP40: 8650 | AQ40: 76 | AR40: 1112 | AS40: 669 | AT40: 221 | AU40: 148 | BJ40: 0.9 | BK40: F | BL40: 126 | BM40: 522 | BN40: 363 | BO40: F | BP40: 711 | BQ40: 146 | BR40: 63 | CE40: 16QD06* | CF40: 能率16E4
A41: 45144 | B41: 预售 | C41: 预约晚8点 | F41: =E41 | G41: 0 | H41: =IFERROR(E41/G41-1,"") | I41: 0 | J41: =IFERROR(E41/I41,"") | K41: =IFERROR(E41/#REF!,"") | L41: 8480 | M41: 2804 | N41: =L41/M41-1 -> 2.0242511 | Y41: 6508 | AA41: 2376 | AC41: 3 | AE41: 80 | AF41: 24 | AG41: 14 | AI41: 97 | AJ41: 3444 | AK41: 1828 | AL41: 879 | AM41: 769 | AN41: 113 | AO41: 93 | AP41: 1888 | AQ41: 75 | AR41: 1228 | AS41: 815 | AT41: 204 | AU41: 223 | BJ41: 0.9 | BK41: F | BL41: 103 | BM41: 692 | BN41: 474 | BO41: F | BP41: 559 | BQ41: 204 | BR41: 84 | CE41: 16QD06* | CF41: 能率16E4
A42: 45145 | B42: S级 | C42: 日销 | F42: =E42-0.9 -> #VALUE! | G42: 18.3966 | H42: =IFERROR(E42/G42-1,"") | I42: 25 | J42: =IFERROR(E42/I42,"") | K42: =IFERROR(E42/#REF!,"") | L42: 49573 | M42: 109126.8 | N42: =L42/M42-1 -> -0.54573029 | Y42: 10001 | AA42: 2931 | AC42: 3 | AE42: 103 | AF42: 19 | AG42: 11 | AI42: 151 | AJ42: 3927 | AK42: 2261 | AL42: 850 | AM42: 946 | AN42: 134 | AO42: 163 | AP42: 6843 | AQ42: 96 | AR42: 1175 | AS42: 950 | AT42: 224 | AU42: 256 | BJ42: 0.9 | BK42: F | BL42: 118 | BM42: 555 | BN42: 536 | BO42: F | BP42: 644 | BQ42: 173 | BR42: 102 | CE42: 16QD06* | CF42: 能率16E4
A43: 45146 | B43: S级 | C43: 日销 | F43: =E43-4 -> #VALUE! | G43: 14.2969 | H43: =IFERROR(E43/G43-1,"") | I43: 14 | J43: =IFERROR(E43/I43,"") | K43: =IFERROR(E43/#REF!,"") | L43: 68635 | M43: 81834 | N43: =L43/M43-1 -> -0.16128993 | Y43: 10166 | AA43: 2990 | AC43: 3 | AE43: 98 | AG43: 15 | AI43: 148 | AJ43: 3721 | AK43: 2426 | AL43: 801 | AM43: 787 | AN43: 144 | AO43: 147 | AP43: 4641 | AQ43: 99 | AR43: 1189 | AS43: 1216 | AT43: 219 | AU43: 226 | BJ43: 0.9 | BK43: F | BL43: 121 | BM43: 562 | BN43: 939 | BO43: F | BP43: 707 | BQ43: 146 | BR43: 197 | BX43: 16GD32 | BY43: 16GD31 | BZ43: 海尔云程 | CA43: 小店16QD06W | CB43: 13QD06W | CC43: 能率16V36A | CD43: 海尔锦绣 | CE43: 16QD31 | CF43: POP13QS04 | CG43: 16QC05
A44: 45147 | B44: A级 | C44: 日销 | F44: =E44-0.8 -> #VALUE! | G44: 9.3686 | H44: =IFERROR(E44/G44-1,"") | I44: 7 | J44: =IFERROR(E44/I44,"") | K44: =IFERROR(E44/#REF!,"") | L44: 44704 | M44: 37545 | N44: =L44/M44-1 -> 0.19067785 | Y44: 8756 | AA44: 2680 | AC44: 3 | AE44: 100 | AG44: 6 | AI44: 145 | AJ44: 3203 | AK44: 2259 | AL44: 664 | AM44: 626 | AN44: 147 | AO44: 127 | AP44: 1424 | AQ44: 91 | AR44: 1200 | AS44: 1116 | AT44: 211 | AU44: 233 | BJ44: 0.95 | BK44: E | BL44: 94 | BM44: 761 | BN44: 878 | BO44: F | BP44: 611 | BQ44: 174 | BR44: 202
A45: 45148 | B45: A级 | C45: 日销 | F45: =E45-1.35 -> #VALUE! | G45: 6.5286 | H45: =IFERROR(E45/G45-1,"") | I45: 8 | J45: =IFERROR(E45/I45,"") | K45: =IFERROR(E45/#REF!,"") | L45: 45133 | M45: 21676 | N45: =L45/M45-1 -> 1.0821646 | P45: 4.6 | Y45: 8169 | AA45: 2557 | AC45: 3 | AE45: 92 | AG45: 5 | AI45: 120 | AJ45: 3439 | AK45: 2148 | AL45: 713 | AM45: 560 | AN45: 98 | AO45: 80 | AP45: 7553 | AQ45: 109 | AR45: 1163 | AS45: 1076 | AT45: 166 | AU45: 195 | AX45: 177 | AY45: 139 | AZ45: 0.017866155 | BA45: 0.054360579 | BB45: 13 | BC45: 12 | BD45: 0.073446328 | BE45: 0.086330935 | BJ45: 1 | BK45: F | BL45: 113 | BM45: 554 | BN45: 1089 | BO45: F | BP45: 688 | BQ45: 145 | BR45: 223
A46: 45149 | B46: 预售 | C46: 预约 | G46: 0 | H46: =IFERROR(E46/G46-1,"") | I46: 0 | J46: =IFERROR(E46/I46,"") | K46: =IFERROR(E46/#REF!,"") | L46: 106272 | M46: 7547 | N46: =L46/M46-1 -> 13.081357 | P46: 2.2 | Y46: 7007 | AA46: 2259 | AC46: 3 | AE46: 94 | AI46: 102 | AJ46: 2913 | AK46: 1863 | AL46: 837 | AM46: 557 | AN46: 113 | AO46: 111 | AP46: 2686 | AQ46: 82 | AR46: 915 | AS46: 885 | AT46: 179 | AU46: 174 | AX46: 142 | AZ46: 0.027140673 | BA46: 0 | BB46: 11 | BD46: 0.077464789 | BE46: #DIV/0! | BJ46: 1 | BK46: F | BL46: 155 | BM46: 358 | BN46: 630 | BO46: F | BP46: 944 | BQ46: 102 | BR46: 117
A47: 45150 | B47: 预售 | C47: 预约 | F47: =E47 | G47: 0 | H47: =IFERROR(E47/G47-1,"") | I47: 0 | J47: =IFERROR(E47/I47,"") | K47: =IFERROR(E47/#REF!,"") | L47: 27301 | M47: 0 | N47: =L47/M47-1 -> #DIV/0! | P47: 5.1 | Y47: 5487 | AA47: 1966 | AC47: 3 | AE47: 85 | AI47: 75 | AJ47: 3385 | AK47: 1549 | AL47: 916 | AM47: 524 | AN47: 111 | AO47: 94 | AP47: 6643 | AQ47: 82 | AR47: 1038 | AS47: 689 | AT47: 205 | AU47: 145 | AX47: 153 | AZ47: 0.016675749 | BA47: 0 | BB47: 17 | BD47: 0.11111111 | BE47: #DIV/0! | BJ47: 1 | BK47: F | BL47: 124 | BM47: 515 | BN47: 435 | BO47: F | BP47: 806 | BQ47: 140 | BR47: 77
A48: 45151 | B48: 预售 | C48: 预约 | F48: =E48 | G48: 0 | H48: =IFERROR(E48/G48-1,"") | I48: 0 | J48: =IFERROR(E48/I48,"") | K48: =IFERROR(E48/#REF!,"") | L48: 0 | M48: 4880 | N48: =L48/M48-1 -> -1 | P48: 5.5 | Y48: 6928 | AA48: 2236 | AC48: 3 | AE48: 91 | AI48: 89 | AJ48: 3976 | AK48: 1753 | AL48: 1048 | AM48: 693 | AN48: 122 | AO48: 72 | AP48: 7100 | AQ48: 51 | AR48: 1260 | AS48: 802 | AT48: 276 | AU48: 170 | AX48: 182 | AZ48: 0.018068103 | BA48: 0 | BB48: 22 | BD48: 0.12087912 | BE48: #DIV/0! | BJ48: 0.96 | BK48: F | BL48: 135 | BM48: 470 | BN48: 574 | BO48: F | BP48: 711 | BQ48: 159 | BR48: 117
A49: 45152 | B49: 预售+S级 | C49: 预约晚8点 | F49: =E49 | G49: 43.2687 | H49: =IFERROR(E49/G49-1,"") | I49: 40 | J49: =IFERROR(E49/I49,"") | K49: =IFERROR(E49/#REF!,"") | L49: 158017 | M49: 287946 | N49: =L49/M49-1 -> -0.45122697 | P49: 10.9 | Y49: 12162 | AA49: 3259 | AC49: 4 | AE49: 109 | AI49: 146 | AJ49: 4278 | AK49: 2687 | AL49: 1167 | AM49: 791 | AN49: 150 | AO49: 144 | AP49: 3462 | AQ49: 123 | AR49: 1254 | AS49: 1147 | AT49: 257 | AU49: 267 | AX49: 251 | AZ49: 0.036808916 | BA49: 0 | BB49: 40 | BD49: 0.15936255 | BE49: #DIV/0! | BJ49: 0.96 | BK49: F | BL49: 152 | BM49: 463 | BN49: 1043 | BO49: F | BP49: 689 | BQ49: 170 | BR49: 219
A50: 45153 | B50: S级 | C50: 掌秒 | F50: =E50-5 -> #VALUE! | G50: 15.3414 | H50: =IFERROR(E50/G50-1,"") | I50: 18 | J50: =IFERROR(E50/I50,"") | K50: =IFERROR(E50/#REF!,"") | L50: 103717 | M50: 138435 | N50: =L50/M50-1 -> -0.25078918 | P50: 5.8 | Y50: 10617 | AA50: 3642 | AC50: 3 | AE50: 81 | AI50: 158 | AJ50: 3618 | AK50: 3260 | AL50: 961 | AM50: 479 | AN50: 122 | AO50: 142 | AP50: 3883 | AQ50: 126 | AR50: 1223 | AS50: 1267 | AT50: 192 | AU50: 233 | AX50: 156 | AZ50: 0.022674419 | BA50: 0 | BB50: 19 | BD50: 0.12179487 | BE50: #DIV/0! | BJ50: 0.96 | BK50: F | BL50: 124 | BM50: 497 | BN50: 1436 | BO50: F | BP50: 760 | BQ50: 151 | BR50: 288 | BX50: 16GD32 | BY50: 16GD31 | BZ50: 海尔锦绣 | CA50: POP16QC06 | CB50: 16QD31 | CC50: 16GD61R | CD50: 小店16QD06W | CE50: 海尔云程 | CF50: 13QD06W | CG50: 16QC06
A51: 45154 | B51: A级 | C51: 预约 | F51: =E51-2.2 -> #VALUE! | G51: 8.2581 | H51: =IFERROR(E51/G51-1,"") | I51: 0 | J51: =IFERROR(E51/I51,"") | K51: =IFERROR(E51/#REF!,"") | L51: 73994 | M51: 50079 | N51: =L51/M51-1 -> 0.47754548 | P51: 5.2 | Y51: 8736 | AA51: 2751 | AC51: 3 | AE51: 97 | AI51: 144 | AJ51: 3211 | AK51: 2379 | AL51: 959 | AM51: 407 | AN51: 121 | AO51: 180 | AP51: 4043 | AQ51: 94 | AR51: 1095 | AS51: 1068 | AT51: 179 | AU51: 216 | AX51: 173 | AZ51: 0.025717259 | BA51: 0 | BB51: 17 | BD51: 0.098265896 | BE51: #DIV/0! | BJ51: 1 | BK51: F | BL51: 133 | BM51: 464 | BN51: 1017 | BO51: F | BP51: 802 | BQ51: 143 | BR51: 211
A52: 45155 | B52: 预售+S级 | C52: 预约晚8点 | F52: =E52-0.45 -> #VALUE! | G52: 18.1262 | H52: =IFERROR(E52/G52-1,"") | I52: 23 | J52: =IFERROR(E52/I52,"") | K52: =IFERROR(E52/#REF!,"") | L52: 28203 | M52: 71680 | N52: =L52/M52-1 -> -0.60654297 | P52: 4.5 | Y52: 9398 | AA52: 2592 | AC52: 4 | AE52: 107 | AI52: 151 | AJ52: 3327 | AK52: 2176 | AL52: 941 | AM52: 547 | AN52: 91 | AO52: 141 | AP52: 2735 | AQ52: 114 | AR52: 1075 | AS52: 976 | AT52: 175 | AU52: 244 | AX52: 156 | AZ52: 0.02812331 | BA52: 0 | BB52: 16 | BD52: 0.1025641 | BE52: #DIV/0! | BJ52: 1 | BK52: F | BL52: 131 | BM52: 448 | BN52: 1016 | BO52: F | BP52: 851 | BQ52: 127 | BR52: 202
A53: 45156 | B53: S级 | C53: 掌秒 | F53: =E53-1.3 -> #VALUE! | G53: 18.1274 | H53: =IFERROR(E53/G53-1,"") | I53: 16 | J53: =IFERROR(E53/I53,"") | K53: =IFERROR(E53/#REF!,"") | L53: 83294 | M53: 130525 | N53: =L53/M53-1 -> -0.36185405 | P53: 5.3 | Y53: 11157 | AA53: 3575 | AC53: 3 | AE53: 87 | AI53: 162 | AJ53: 3302 | AK53: 3154 | AL53: 857 | AM53: 530 | AN53: 134 | AO53: 138 | AP53: 2813 | AQ53: 123 | AR53: 1096 | AS53: 1160 | AT53: 178 | AU53: 232 | AX53: 164 | AZ53: 0.029747869 | BA53: 0 | BB53: 16 | BD53: 0.097560976 | BE53: #DIV/0! | BJ53: 1 | BK53: F | BL53: 109 | BM53: 575 | BN53: 1041 | BO53: F | BP53: 764 | BQ53: 137 | BR53: 229
A54: 45157 | B54: A级 | C54: 日销 | F54: =E54 | G54: 13.0075 | H54: =IFERROR(E54/G54-1,"") | I54: 7 | J54: =IFERROR(E54/I54,"") | K54: =IFERROR(E54/#REF!,"") | L54: 21195 | M54: 25285 | N54: =L54/M54-1 -> -0.16175598 | P54: 2.5 | Y54: 7131 | AA54: 2618 | AC54: 3 | AE54: 82 | AI54: 135 | AJ54: 3116 | AK54: 2231 | AL54: 670 | AM54: 481 | AN54: 110 | AO54: 139 | AP54: 5144 | AQ54: 81 | AR54: 1089 | AS54: 951 | AT54: 180 | AU54: 149 | AX54: 138 | AZ54: 0.018246727 | BA54: 0 | BB54: 6 | BD54: 0.043478261 | BE54: #DIV/0! | BJ54: 1 | BK54: F | BL54: 111 | BM54: 528 | BN54: 734 | BO54: F | BP54: 752 | BQ54: 158 | BR54: 121
A55: 45158 | B55: A级 | C55: 日销 | F55: =E55 | G55: 8.0084 | H55: =IFERROR(E55/G55-1,"") | I55: 8 | J55: =IFERROR(E55/I55,"") | K55: =IFERROR(E55/#REF!,"") | L55: 22095 | M55: 26475 | N55: =L55/M55-1 -> -0.16543909 | P55: 2 | Y55: 7781 | AA55: 2680 | AC55: 3 | AE55: 84 | AI55: 131 | AJ55: 3130 | AK55: 2305 | AL55: 717 | AM55: 448 | AN55: 105 | AO55: 123 | AP55: 5129 | AQ55: 113 | AR55: 1022 | AS55: 1068 | AT55: 174 | AU55: 182 | AX55: 147 | AZ55: 0.019337017 | BA55: 0 | BB55: 10 | BD55: 0.068027211 | BE55: #DIV/0! | BJ55: 1 | BK55: F | BL55: 129 | BM55: 519 | BN55: 1016 | BO55: F | BP55: 782 | BQ55: 153 | BR55: 197
A56: 45159 | B56: A级 | C56: 日销 | F56: =E56-0.9 -> #VALUE! | G56: 4.3991 | H56: =IFERROR(E56/G56-1,"") | I56: 9 | J56: =IFERROR(E56/I56,"") | K56: =IFERROR(E56/#REF!,"") | L56: 44872 | M56: 13997 | N56: =L56/M56-1 -> 2.2058298 | P56: 4 | Y56: 7792 | AA56: 2774 | AC56: 3 | AE56: 76 | AI56: 112 | AJ56: 3394 | AK56: 2400 | AL56: 639 | AM56: 448 | AN56: 108 | AO56: 113 | AP56: 5952 | AQ56: 106 | AR56: 1256 | AS56: 1083 | AT56: 167 | AU56: 172 | AX56: 181 | AZ56: 0.021324222 | BA56: 0 | BB56: 12 | BD56: 0.066298343 | BE56: #DIV/0! | BJ56: 1 | BK56: F | BL56: 104 | BM56: 585 | BN56: 1046 | BO56: F | BP56: 651 | BQ56: 180 | BR56: 201
A57: 45160 | B57: A级 | C57: 预约 | F57: =E57-2 -> #VALUE! | G57: 0.3909 | H57: =IFERROR(E57/G57-1,"") | I57: 0 | J57: =IFERROR(E57/I57,"") | K57: =IFERROR(E57/#REF!,"") | L57: 54249 | M57: 14688 | N57: =L57/M57-1 -> 2.6934232 | P57: 2.2 | Y57: 7192 | AA57: 2711 | AC57: 3 | AE57: 75 | AI57: 90 | AJ57: 3025 | AK57: 2243 | AL57: 745 | AM57: 504 | AN57: 117 | AO57: 206 | AP57: 4756 | AQ57: 107 | AR57: 1004 | AS57: 784 | AT57: 161 | AU57: 170 | AX57: 151 | AZ57: 0.021045296 | BB57: 6 | BD57: 0.039735099 | BJ57: 1 | BK57: F | BL57: 130 | BM57: 435 | BN57: 610 | BO57: F | BP57: 793 | BQ57: 134 | BR57: 116 | BX57: 16GD32 | BY57: 16GD31 | BZ57: 13QD06W | CA57: 海尔云程 | CB57: 16QC06 | CC57: 16QD31 | CD57: POP16QC06 | CE57: 海尔锦绣 | CF57: 小店16QD06W | CG57: 能率16E4
A58: 45161 | B58: A级 | C58: 预约 | F58: =E58-3 -> #VALUE! | G58: 0 | H58: =IFERROR(E58/G58-1,"") | I58: 0 | J58: =IFERROR(E58/I58,"") | K58: =IFERROR(E58/#REF!,"") | L58: 50652 | M58: 23120 | N58: =L58/M58-1 -> 1.1908304 | P58: 1.38 | Y58: 7406 | AA58: 2863 | AC58: 3 | AE58: 75 | AI58: 88 | AJ58: 2561 | AK58: 2426 | AL58: 808 | AM58: 574 | AN58: 109 | AO58: 123 | AP58: 7925 | AQ58: 85 | AR58: 970 | AS58: 823 | AT58: 201 | AU58: 136 | AX58: 129 | AZ58: 0.01215605 | BB58: 9 | BD58: 0.069767442 | BK58: F | BL58: 169 | BM58: 370 | BN58: 646 | BO58: F | BP58: 858 | BQ58: 132 | BR58: 106
A59: 45162 | B59: A级 | C59: 预约 | F59: =E59-1.8 -> #VALUE! | G59: 1.5395 | H59: =IFERROR(E59/G59-1,"") | I59: 24 | J59: =IFERROR(E59/I59,"") | K59: =IFERROR(E59/#REF!,"") | L59: 55252 | M59: 12052.56 | N59: =L59/M59-1 -> 3.5842543 | P59: 4.91 | Y59: 7146 | AA59: 2641 | AC59: 3 | AE59: 78 | AI59: 76 | AJ59: 2644 | AK59: 2230 | AL59: 889 | AM59: 519 | AN59: 102 | AO59: 113 | AP59: 2569 | AQ59: 79 | AR59: 819 | AS59: 741 | AT59: 175 | AU59: 173 | AX59: 167 | AZ59: 0.033500502 | BB59: 17 | BD59: 0.10179641 | BK59: F | BL59: 136 | BM59: 472 | BN59: 491 | BO59: F | BP59: 995 | BQ59: 100 | BR59: 137
A60: 45163 | B60: A级 | C60: 预约晚8点 | F60: =E60-1.3 -> #VALUE! | G60: 32.8776 | H60: =IFERROR(E60/G60-1,"") | I60: 15 | J60: =IFERROR(E60/I60,"") | K60: =IFERROR(E60/#REF!,"") | L60: 75573 | M60: 187037 | N60: =L60/M60-1 -> -0.59594626 | P60: 2.69 | Y60: 9632 | AA60: 2902 | AC60: 3 | AE60: 91 | AI60: 120 | AJ60: 2502 | AK60: 2509 | AL60: 840 | AM60: 488 | AN60: 131 | AO60: 136 | AP60: 2725 | AQ60: 103 | AR60: 827 | AS60: 848 | AT60: 156 | AU60: 223 | AX60: 123 | AZ60: 0.024501992 | BB60: 9 | BD60: 0.073170732 | BK60: F | BL60: 146 | BM60: 459 | BN60: 887 | BO60: F | BP60: 989 | BQ60: 105 | BR60: 171
A61: 45164 | B61: A级 | C61: 日销 | F61: =E61 | G61: 12.5413 | H61: =IFERROR(E61/G61-1,"") | I61: 7 | J61: =IFERROR(E61/I61,"") | K61: =IFERROR(E61/#REF!,"") | L61: 32492 | M61: 117508 | N61: =L61/M61-1 -> -0.72349117 | P61: 3.4 | Y61: 8739 | AA61: 3453 | AC61: 3 | AE61: 71 | AI61: 127 | AJ61: 2514 | AK61: 3089 | AL61: 659 | AM61: 479 | AN61: 107 | AO61: 128 | AP61: 3995 | AQ61: 81 | AR61: 829 | AS61: 1071 | AT61: 158 | AU61: 173 | AX61: 126 | AZ61: 0.020554649 | BB61: 10 | BD61: 0.079365079 | BK61: F | BL61: 167 | BM61: 415 | BN61: 1001 | BO61: F | BP61: 1055 | BQ61: 112 | BR61: 234
A62: 45165 | B62: A级 | C62: 日销 | F62: =E62 | G62: 5.0589 | H62: =IFERROR(E62/G62-1,"") | I62: 8 | J62: =IFERROR(E62/I62,"") | K62: =IFERROR(E62/#REF!,"") | L62: 35670 | M62: 22704 | N62: =L62/M62-1 -> 0.57108879 | P62: 3.57 | Y62: 7103 | AA62: 2436 | AC62: 3 | AE62: 86 | AI62: 100 | AJ62: 2647 | AK62: 1943 | AL62: 594 | AM62: 646 | AN62: 94 | AO62: 101 | AP62: 3284 | AQ62: 65 | AR62: 847 | AS62: 1024 | AT62: 165 | AU62: 160 | AX62: 95 | AZ62: 0.017260174 | BB62: 11 | BD62: 0.11578947 | BK62: F | BL62: 136 | BM62: 565 | BN62: 744 | BO62: F | BP62: 835 | BQ62: 160 | BR62: 192
A63: 45166 | B63: A级 | C63: 日销 | F63: =E63 | G63: 4.632 | H63: =IFERROR(E63/G63-1,"") | I63: 9 | J63: =IFERROR(E63/I63,"") | K63: =IFERROR(E63/#REF!,"") | L63: 29892 | M63: 29044 | N63: =L63/M63-1 -> 0.02919708 | P63: 0.93 | Y63: 7679 | AA63: 2554 | AC63: 3 | AE63: 92 | AI63: 141 | AJ63: 2840 | AK63: 2155 | AL63: 463 | AM63: 511 | AN63: 110 | AO63: 98 | AP63: 4214 | AQ63: 74 | AR63: 812 | AS63: 1157 | AT63: 185 | AU63: 219 | AX63: 130 | AZ63: 0.020299813 | BB63: 2 | BD63: 0.015384615 | BK63: F | BL63: 169 | BM63: 451 | BN63: 1154 | BO63: F | BP63: 1085 | BQ63: 113 | BR63: 222
A64: 45167 | B64: 预售 | C64: 预约 | F64: =E64 | G64: 0 | H64: =IFERROR(E64/G64-1,"") | I64: 0 | J64: =IFERROR(E64/I64,"") | K64: =IFERROR(E64/#REF!,"") | L64: 6597 | M64: 37786 | N64: =L64/M64-1 -> -0.82541153 | P64: 3.12 | Y64: 8051 | AA64: 2642 | AC64: 3 | AE64: 93 | AI64: 128 | AJ64: 2189 | AK64: 2091 | AL64: 4242 | AM64: 710 | AN64: 148 | AO64: 117 | AP64: 612 | AQ64: 98 | AR64: 773 | AS64: 987 | AT64: 245 | AU64: 198 | AX64: 141 | AZ64: 0.021082536 | BB64: 10 | BD64: 0.070921986 | BK64: F | BL64: 179 | BM64: 386 | BN64: 895 | BO64: F | BP64: 1193 | BQ64: 101 | BR64: 149 | BX64: 16GD32 | BY64: 16GD31 | BZ64: 卡萨帝16CWS | CA64: 13QD06W | CB64: 海尔云程 | CC64: 16GD61R | CD64: POP16QC06 | CE64: 能率16E4 | CF64: 16QD31 | CG64: 16QC06
A65: 45168 | B65: 预售 | C65: 预约 | F65: =E65 | G65: 0 | H65: =IFERROR(E65/G65-1,"") | I65: 0 | J65: =IFERROR(E65/I65,"") | K65: =IFERROR(E65/#REF!,"") | L65: 2920 | M65: 50673 | N65: =L65/M65-1 -> -0.94237562 | P65: 4.22 | Y65: 7230 | AA65: 2437 | AC65: 3 | AE65: 96 | AI65: 111 | AJ65: 2009 | AK65: 1937 | AL65: 594 | AM65: 545 | AN65: 117 | AO65: 166 | AP65: 3905 | AQ65: 118 | AR65: 724 | AS65: 905 | AT65: 199 | AU65: 162 | AX65: 133 | AZ65: 0.021650659 | BB65: 14 | BD65: 0.10526316 | BK65: F | BL65: 161 | BM65: 395 | BN65: 782 | BO65: F | BP65: 1098 | BQ65: 114 | BR65: 152
A66: 45169 | B66: 31号晚8开门红 | C66: 预约晚8点 | F66: =E66 | G66: 33.3633 | H66: =IFERROR(E66/G66-1,"") | I66: 30 | J66: =IFERROR(E66/I66,"") | K66: =IFERROR(E66/#REF!,"") | L66: 68807 | M66: 199577 | N66: =L66/M66-1 -> -0.65523582 | P66: 6.64 | Y66: 8912 | AA66: 2379 | AC66: 4 | AE66: 102 | AI66: 116 | AJ66: 2158 | AK66: 1987 | AL66: 793 | AM66: 452 | AN66: 101 | AO66: 125 | AP66: 2811 | AQ66: 111 | AR66: 836 | AS66: 846 | AT66: 218 | AU66: 203 | AX66: 144 | AZ66: 0.026930989 | BB66: 20 | BD66: 0.13888889 | BK66: F | BL66: 189 | BM66: 349 | BN66: 868 | BO66: F | BP66: 1181 | BQ66: 101 | BR66: 210
A67: 45170 | C67: 开门红/掌秒 | F67: =E67 | G67: 15.2387 | H67: =IFERROR(E67/G67-1,"") | J67: =IFERROR(E67/I67,"") | K67: =IFERROR(E67/#REF!,"") | L67: 33392 | M67: 214175 | N67: =L67/M67-1 -> -0.84409011 | P67: 1.16 | Y67: 8441 | AA67: 3319 | AC67: 2.54 | AE67: 69.87 | AI67: 123 | AJ67: 2418 | AK67: 3696 | AL67: 597 | AM67: 454 | AN67: 138 | AO67: 145 | AP67: 2442 | AQ67: 100 | AR67: 791 | AS67: 989 | AT67: 157 | AU67: 205 | AX67: 116 | AZ67: 0.025511326 | BB67: 5 | BD67: 0.043103448 | BK67: F | BL67: 161 | BM67: 379 | BN67: 1081 | BO67: F | BP67: 1196 | BQ67: 94 | BR67: 199
A68: 45171 | B68: 日销 | C68: 日销 | F68: =E68 | G68: 13.497 | H68: =IFERROR(E68/G68-1,"") | J68: =IFERROR(E68/I68,"") | K68: =IFERROR(E68/#REF!,"") | L68: 32854 | M68: 6998 | N68: =L68/M68-1 -> 3.6947699 | P68: 3.05 | Y68: 7774 | AA68: 2463 | AC68: 3.16 | AE68: 91.49 | AI68: 132 | AJ68: 2513 | AK68: 2775 | AL68: 713 | AM68: 423 | AN68: 121 | AO68: 120 | AP68: 3371 | AQ68: 107 | AR68: 829 | AS68: 930 | AT68: 166 | AU68: 179 | AX68: 150 | AZ68: 0.026896181 | BB68: 9 | BD68: 0.06 | BK68: F | BL68: 167 | BM68: 389 | BN68: 805 | BO68: F | BP68: 1168 | BQ68: 117 | BR68: 167
A69: 45172 | B69: 预售 | C69: 预约 | F69: =E69 | G69: 0 | H69: =IFERROR(E69/G69-1,"") | J69: =IFERROR(E69/I69,"") | K69: =IFERROR(E69/#REF!,"") | L69: 8598 | M69: 11580 | N69: =L69/M69-1 -> -0.25751295 | P69: 1.49 | Y69: 7006 | AA69: 2144 | AC69: 3.27 | AE69: 96.32 | AI69: 116 | AJ69: 2477 | AK69: 2350 | AL69: 614 | AM69: 476 | AN69: 93 | AO69: 106 | AP69: 2868 | AQ69: 73 | AR69: 641 | AS69: 826 | AT69: 237 | AU69: 172 | AX69: 125 | AZ69: 0.024831148 | BB69: 7 | BD69: 0.056 | BK69: F | BL69: 302 | BM69: 244 | BN69: 494 | BO69: F | BP69: 1459 | BQ69: 84 | BR69: 111
A70: 45173 | B70: 晚8点 | C70: 晚8点 | F70: =E70 | G70: 24.9446 | H70: =IFERROR(E70/G70-1,"") | J70: =IFERROR(E70/I70,"") | K70: =IFERROR(E70/#REF!,"") | L70: 54086 | M70: 100863.21 | N70: =L70/M70-1 -> -0.4637688 | P70: 4.58 | Y70: 9029 | AA70: 2459 | AC70: 3.67 | AE70: 109.88 | AI70: 151 | AJ70: 2580 | AK70: 2937 | AL70: 834 | AM70: 452 | AN70: 123 | AO70: 125 | AP70: 2248 | AQ70: 90 | AR70: 658 | AS70: 925 | AT70: 220 | AU70: 230 | AX70: 147 | AZ70: 0.032500553 | BB70: 15 | BD70: 0.10204082 | BK70: F | BL70: 252 | BM70: 263 | BN70: 731 | BO70: F | BP70: 81 | BQ70: 1336 | BR70: 148
A71: 45174 | B71: 预售 | C71: 日销/掌秒 | F71: =E71 | G71: 12.7275 | H71: =IFERROR(E71/G71-1,"") | J71: =IFERROR(E71/I71,"") | K71: =IFERROR(E71/#REF!,"") | L71: 10080 | M71: 82597 | N71: =L71/M71-1 -> -0.87796167 | P71: 4.16 | Y71: 10682 | AA71: 3564 | AC71: 3 | AE71: 87.71 | AI71: 146 | AJ71: 2048 | AK71: 4011 | AL71: 883 | AM71: 547 | AN71: 116 | AO71: 118 | AP71: 2147 | AQ71: 121 | AR71: 832 | AS71: 1154 | AT71: 216 | AU71: 234 | AX71: 140 | AZ71: 0.029523408 | BB71: 9 | BD71: 0.064285714 | BK71: F | BL71: 162 | BM71: 380 | BN71: 1142 | BO71: F | BP71: 985 | BQ71: 114 | BR71: 281 | BX71: 16GD32 | BY71: 16QC06 | BZ71: 16GD31 | CA71: POP16QC06 | CB71: 海尔16Meta | CC71: 13GD31 | CD71: 海尔锦绣 | CE71: 海尔16LU1 | CF71: 能率16V36A | CG71: 卡萨帝16CW3
A72: 45175 | B72: 预售 | C72: 预约 | F72: =E72 | G72: 8.5481 | H72: =IFERROR(E72/G72-1,"") | J72: =IFERROR(E72/I72,"") | K72: =IFERROR(E72/#REF!,"") | L72: 7798 | M72: 28892 | N72: =L72/M72-1 -> -0.7300983 | P72: 3.71 | Y72: 8820 | AA72: 2978 | AC72: 2.96 | AE72: 88.28 | AI72: 150 | AJ72: 2080 | AK72: 3314 | AL72: 952 | AM72: 547 | AN72: 125 | AO72: 162 | AP72: 2458 | AQ72: 127 | AR72: 783 | AS72: 1077 | AT72: 216 | AU72: 280 | AX72: 161 | AZ72: 0.031612016 | BB72: 15 | BD72: 0.093167702 | BK72: F | BL72: 163 | BM72: 394 | BN72: 780 | BO72: F | BP72: 1041 | BQ72: 98 | BR72: 166
A73: 45176 | B73: 7号晚8 | C73: 预约 | F73: =E73 | G73: 0 | H73: =IFERROR(E73/G73-1,"") | J73: =IFERROR(E73/I73,"") | K73: =IFERROR(E73/#REF!,"") | L73: 58367 | M73: 18634 | N73: =L73/M73-1 -> 2.1322851 | P73: 5.17 | Y73: 6727 | AA73: 2309 | AC73: 2.91 | AE73: 87.58 | AI73: 101 | AJ73: 2210 | AK73: 2353 | AL73: 865 | AM73: 581 | AN73: 120 | AO73: 147 | AP73: 2493 | AQ73: 87 | AR73: 852 | AS73: 755 | AT73: 215 | AU73: 182 | AX73: 136 | AZ73: 0.026464293 | BB73: 16 | BD73: 0.11764706 | BK73: F | BL73: 178 | BM73: 381 | BN73: 441 | BO73: F | BP73: 932 | BQ73: 114 | BR73: 75
A74: 45177 | C74: 晚8点 | F74: =E74 | G74: 19.2395 | H74: =IFERROR(E74/G74-1,"") | J74: =IFERROR(E74/I74,"") | K74: =IFERROR(E74/#REF!,"") | L74: 43471 | M74: 198209 | N74: =L74/M74-1 -> -0.780681 | P74: 2.09 | Y74: 7852 | AA74: 2441 | AC74: 3.22 | AE74: 95.77 | AI74: 117 | AJ74: 2618 | AK74: 2656 | AL74: 849 | AM74: 615 | AN74: 92 | AO74: 128 | AP74: 2667 | AQ74: 148 | AR74: 923 | AS74: 799 | AT74: 162 | AU74: 232 | AX74: 121 | AZ74: 0.02369297 | BB74: 6 | BD74: 0.049586777 | BK74: F | BL74: 156 | BM74: 445 | BN74: 452 | BO74: F | BP74: 798 | BQ74: 139 | BR74: 99
A75: 45178 | C75: 日销 | F75: =E75 | G75: 12.2778 | H75: =IFERROR(E75/G75-1,"") | J75: =IFERROR(E75/I75,"") | K75: =IFERROR(E75/#REF!,"") | L75: 43455 | M75: 135546 | N75: =L75/M75-1 -> -0.67940773 | P75: 2.05 | Y75: 6964 | AA75: 2353 | AC75: 2.96 | AE75: 86.8 | AI75: 124 | AJ75: 3022 | AK75: 2639 | AL75: 895 | AM75: 489 | AN75: 86 | AO75: 81 | AP75: 2863 | AQ75: 107 | AR75: 1019 | AS75: 866 | AT75: 231 | AU75: 227 | AX75: 136 | AZ75: 0.024548736 | BB75: 9 | BD75: 0.066176471 | BK75: F | BL75: 160 | BM75: 465 | BN75: 774 | BO75: F | BP75: 1109 | BQ75: 93 | BR75: 200
A76: 45179 | B76: 预售 | C76: 日销 | F76: =E76 | G76: 5.9645 | H76: =IFERROR(E76/G76-1,"") | J76: =IFERROR(E76/I76,"") | K76: =IFERROR(E76/#REF!,"") | L76: 12957 | M76: 66814 | N76: =L76/M76-1 -> -0.80607358 | P76: 1.21 | Y76: 6085 | AA76: 1976 | AC76: 3.08 | AE76: 84.04 | AI76: 120 | AJ76: 2976 | AK76: 2173 | AL76: 885 | AM76: 444 | AN76: 108 | AO76: 64 | AP76: 2983 | AQ76: 83 | AR76: 1074 | AS76: 838 | AT76: 172 | AU76: 165 | AX76: 177 | AZ76: 0.031107206 | BB76: 4 | BD76: 0.02259887 | BK76: F | BL76: 175 | BM76: 432 | BN76: 673 | BO76: F | BP76: 917 | BQ76: 125 | BR76: 186
A77: 45180 | B77: 预售 | C77: 日销 | F77: =E77 | G77: 3.9991 | H77: =IFERROR(E77/G77-1,"") | J77: =IFERROR(E77/I77,"") | K77: =IFERROR(E77/#REF!,"") | L77: 42854 | M77: 106234 | N77: =L77/M77-1 -> -0.59660749 | P77: 5.94 | Y77: 8072 | AA77: 2405 | AC77: 3.36 | AE77: 95.49 | AI77: 105 | AJ77: 2300 | AK77: 2646 | AL77: 813 | AM77: 481 | AN77: 108 | AO77: 149 | AP77: 2241 | AQ77: 106 | AR77: 1053 | AS77: 931 | AT77: 188 | AU77: 219 | AX77: 137 | AZ77: 0.027421938 | BB77: 14 | BD77: 0.10218978 | BK77: F | BL77: 131 | BM77: 557 | BN77: 749 | BO77: F | BP77: 908 | BQ77: 122 | BR77: 184
